Workbook
Name a: '[1]BOM '!#REF!
Name a: '[1]BOM '!#REF!
Name a: '[1]BOM '!#REF!
Name a: '[1]BOM '!#REF!
Name a: '[1]BOM '!#REF!
Name a: '[1]BOM '!#REF!
Name a: '[1]BOM '!#REF!
Name a: '[1]BOM '!#REF!
Name a: '[1]BOM '!#REF!
Name a: '[1]BOM '!#REF!
Name a: '[1]BOM '!#REF!
Name a: '[1]BOM '!#REF!
Name a: '[1]BOM '!#REF!
Name a: '[1]BOM '!#REF!
Name a: #REF!
Name a: #REF!
Name a_1: #REF!
Name a_1: #REF!
Name a_1: #REF!
Name a_1: #REF!
Name a_1: #REF!
Name a_1: #REF!
Name a_1: #REF!
Name a_1: #REF!
Name a_1: #REF!
Name a_1: #REF!
Name a_1: #REF!
Name a_1: #REF!
Name a_1: #REF!
Name a_1: #REF!
Name a_1: #REF!
Name a_1: #REF!
Name b: #REF!
Name b: #REF!
Name b: #REF!
Name b: #REF!
Name b: #REF!
Name b: #REF!
Name b: #REF!
Name b: #REF!
Name b: #REF!
Name b: #REF!
Name b: #REF!
Name b: #REF!
Name b: #REF!
Name b: #REF!
Name b: #REF!
Name b: #REF!

Sheet Customer Data 
A1: S.NO | B1: PartID | C1: Description | D1: Usage
A2: 1 | B2: AY30013 | C2: WELDMENT, PC4100 R2D SLAVE SKID, PC4100 | D2: 1
A3: 2 | B3: AY30017 | C3: WELDMENT, FALSE FLOOR, PC4100 | D3: 2
A4: 3 | B4: AY30018 | C4: WELDMENT, HINGED FLOOR, PC4100 | D4: 1
A5: 4 | B5: AY30027 | C5: WELDMENT, HINGED FLOOR, PC4100 | D5: 23
A6: 5 | B6: AY30062 | C6: WELDMENT, SAFETY BAR, PC4100 | D6: 1
A7: 6 | B7: AY30084 | C7: HAND RAIL, WELDMENT, 42" CATWALK, PC4100 | D7: 4
A8: 7 | B8: AY30107 | C8: WELDMENT,SKATE BODY, REVERSE VEE,PC4100 | D8: 1
A9: 8 | B9: AY30133 | C9: WELDMENT, RAMP RAIL, PC4100 | D9: 1
A10: 9 | B10: AY30134 | C10: WLDMNT, RAMP, SHEAVE SUB B, PC4100 | D10: 1
A11: 10 | B11: AY30144 | C11: WELDMENT, 30FT LIFT ARM, PC4100 | D11: 1
A12: 11 | B12: AY30150 | C12: WELDMENT, SPEAR FRAME, PC4100 | D12: 1
A13: 12 | B13: AY30160 | C13: WELDMENT, 42D CARRIER REAR, PC4100 | D13: 1
... A16: 15 | B16: AY50135 | C16: KIT, LABELS, SAFETY, ENG/ARA, PC4000 | D16: 1

Sheet Quote Package PC4100
D1: ITEM-1 | F1: ITEM-2 | H1: ITEM-3 | J1: ITEM-4 | L1: ITEM-5 | N1: ITEM-6 | P1: ITEM-7 | R1: ITEM-8 | T1: ITEM-9 | V1: ITEM-10 | X1: ITEM-11 | Z1: ITEM-12 | AB1: ITEM-13 | AD1: ITEM-14
A2: RECURRING COST | D2: Assy. No | E2: Qty. | F2: Assy. No | G2: Qty. | H2: Assy. No | I2: Qty. | J2: Assy. No | K2: Qty. | L2: Assy. No | M2: Qty. | N2: Assy. No | O2: Qty. | P2: Assy. No | Q2: Qty. | R2: Assy. No | S2: Qty. | T2: Assy. No | U2: Qty. | V2: Assy. No | W2: Qty. | X2: Assy. No | Y2: Qty. | Z2: Assy. No | AA2: Qty. | AB2: Assy. No | AC2: Qty. | AD2: Assy. No | AE2: Qty.
D3: ='BOM R2D CatWalk'!G4 -> AY30013 | E3: ='BOM R2D CatWalk'!K4 -> 1 | F3: ='BOM R2D CatWalk'!G93 -> AY30017 | G3: ='BOM R2D CatWalk'!K93 -> 2 | H3: ='BOM R2D CatWalk'!G97 -> AY30018 | I3: ='BOM R2D CatWalk'!K97 -> 1 | J3: ='BOM R2D CatWalk'!G100 -> AY30027 | K3: ='BOM R2D CatWalk'!K100 -> 23 | L3: ='BOM R2D CatWalk'!G105 -> AY30062 | M3: ='BOM R2D CatWalk'!K105 -> 1 | N3: ='BOM R2D CatWalk'!G109 -> AY30084 | O3: ='BOM R2D CatWalk'!K109 -> 4 | P3: ='BOM R2D CatWalk'!G114 -> AY30107 | Q3: ='BOM R2D CatWalk'!K114 -> 1 | R3: ='BOM R2D CatWalk'!G119 -> AY30133 | S3: ='BOM R2D CatWalk'!K119 -> 1 | T3: ='BOM R2D CatWalk'!G128 -> AY30134 | U3: ='BOM R2D CatWalk'!K128 -> 1 | V3: ='BOM R2D CatWalk'!G145 -> AY30144 | W3: ='BOM R2D CatWalk'!K145 -> 1 | X3: ='BOM R2D CatWalk'!G162 -> AY30150 | Y3: ='BOM R2D CatWalk'!K162 -> 1 | Z3: ='BOM R2D CatWalk'!G171 -> AY30160 | AA3: ='BOM R2D CatWalk'!K171 -> 1 | AB3: ='BOM R2D CatWalk'!G187 -> AY51606 | AC3: ='BOM R2D CatWalk'!K187 -> 1 | AD3: ='BOM R2D CatWalk'!G201 -> AY30130 | AE3: ='BOM R2D CatWalk'!K201 -> 1
A4: A. | B4: RM Cost | D4: Weight in Kg. | E4: Price in INR | F4: Weight in Kg. | G4: Price in INR | H4: Weight in Kg. | I4: Price in INR | J4: Weight in Kg. | K4: Price in INR | L4: Weight in Kg. | M4: Price in INR | N4: Weight in Kg. | O4: Price in INR | P4: Weight in Kg. | Q4: Price in INR | R4: Weight in Kg. | S4: Price in INR | T4: Weight in Kg. | U4: Price in INR | V4: Weight in Kg. | W4: Price in INR | X4: Weight in Kg. | Y4: Price in INR | Z4: Weight in Kg. | AA4: Price in INR | AB4: Weight in Kg. | AC4: Price in INR | AD4: Weight in Kg. | AE4: Price in INR
A5: i. | B5: RM Gross Weight | D5: ='Item-1_AY30013'!H8 -> 5297.8014 | F5: ='Item-2_AY30017'!F8 -> 159.73139 | H5: ='Item-3_AY30018'!F8 -> 29.666872 | J5: ='Item-4_AY30027'!F8 -> 490.53806 | L5: ='Item-5_AY30062'!F8 -> 61.97492 | N5: ='Item-6_AY30084'!F8 -> 97.8406 | P5: ='Item-7_AT30107'!F8 -> 137.44273 | R5: ='Item-8_AT30133'!F8 -> 137.03074 | T5: ='Item-9_AT30134'!F8 -> 900.30678 | V5: ='Item-10_AT30144'!G8 -> 1231.9456 | X5: ='Item-11_AT30150'!G8 -> 100.98498 | Z5: ='Item-12_AY30160'!G8 -> 1032.2847 | AB5: ='Item-13_AY51606'!G8 -> 250.32865 | AD5: ='Item-14_AY30130'!G8 -> 4814.2978
A6: ii. | B6: RM Net Weight | D6: ='Item-1_AY30013'!H9 -> 4052.0664 | F6: ='Item-2_AY30017'!F9 -> 130.332 | H6: ='Item-3_AY30018'!F9 -> 26.8 | J6: ='Item-4_AY30027'!F9 -> 443.05813 | L6: ='Item-5_AY30062'!F9 -> 20.6876 | N6: ='Item-6_AY30084'!F9 -> 88.946 | P6: ='Item-7_AT30107'!F9 -> 80.5 | R6: ='Item-8_AT30133'!F9 -> 124.5734 | T6: ='Item-9_AT30134'!F9 -> 370.42611 | V6: ='Item-10_AT30144'!G9 -> 1044.4723 | X6: ='Item-11_AT30150'!G9 -> 65.53 | Z6: ='Item-12_AY30160'!G9 -> 579.6 | AB6: ='Item-13_AY51606'!G9 -> 177.87298 | AD6: ='Item-14_AY30130'!G9 -> 4086.1094
A7: iii. | B7: Raw Material Cost | E7: ='Item-1_AY30013'!H13 -> 545874.98 | G7: ='Item-2_AY30017'!F13 -> 16346.24 | I7: ='Item-3_AY30018'!F13 -> 2601.2135 | K7: ='Item-4_AY30027'!F13 -> 43008.907 | M7: ='Item-5_AY30062'!F13 -> 5758.6471 | O7: ='Item-6_AY30084'!F13 -> 19354.65 | Q7: ='Item-7_AT30107'!F13 -> 11003.22 | S7: ='Item-8_AT30133'!F13 -> 27107.172 | U7: ='Item-9_AT30134'!F13 -> 74070.474 | W7: ='Item-10_AT30144'!G13 -> 228672.72 | Y7: ='Item-11_AT30150'!G13 -> 16765.529 | AA7: ='Item-12_AY30160'!G13 -> 156415.22 | AC7: ='Item-13_AY51606'!G13 -> 20790.642 | AE7: ='Item-14_AY30130'!G13 -> 580640.73
A8: iv. | B8: Shaft Cost /Fastener/ BOP | E8: ='Item-1_AY30013'!G17 -> 8000 | G8: 0 | I8: 0 | K8: 0 | M8: 0 | O8: 0 | Q8: 0 | S8: 0 | U8: 0 | W8: 0 | Y8: 0 | AA8: 0 | AC8: 0 | AE8: 0
B9: TOTAL RM COST | E9: =SUM(E7:E8) -> 553874.98 | G9: =SUM(G7:G8) -> 16346.24 | I9: =SUM(I7:I8) -> 2601.2135 | K9: =SUM(K7:K8) -> 43008.907 | M9: =SUM(M7:M8) -> 5758.6471 | O9: =SUM(O7:O8) -> 19354.65 | Q9: =SUM(Q7:Q8) -> 11003.22 | S9: =SUM(S7:S8) -> 27107.172 | U9: =SUM(U7:U8) -> 74070.474 | W9: =SUM(W7:W8) -> 228672.72 | Y9: =SUM(Y7:Y8) -> 16765.529 | AA9: =SUM(AA7:AA8) -> 156415.22 | AC9: =SUM(AC7:AC8) -> 20790.642 | AE9: =SUM(AE7:AE8) -> 580640.73
D10: =(D5-D6)/D6 -> 0.30743205 | F10: =(F5-F6)/F6 -> 0.22557306 | H10: =(H5-H6)/H6 -> 0.10697282 | J10: =(J5-J6)/J6 -> 0.10716412 | L10: =(L5-L6)/L6 -> 1.995752 | N10: =(N5-N6)/N6 -> 0.1 | P10: =(P5-P6)/P6 -> 0.70736315 | R10: =(R5-R6)/R6 -> 0.1 | T10: =(T5-T6)/T6 -> 1.4304626 | V10: =(V5-V6)/V6 -> 0.17949093 | X10: =(X5-X6)/X6 -> 0.54104963 | Z10: =(Z5-Z6)/Z6 -> 0.78102942 | AB10: =(AB5-AB6)/AB6 -> 0.40734503 | AD10: =(AD5-AD6)/AD6 -> 0.17821071
A11: B. | B11: Process Cost
A12: i. | B12: Assy Cost | C12: 0 | E12: 0 | G12: 0 | I12: 0 | K12: 0 | M12: 0 | O12: 0 | Q12: 0 | S12: 0 | U12: 0 | W12: 0 | Y12: 0 | AA12: 0 | AC12: 0 | AE12: 0
A13: ii. | B13: Fabrication / Process Cost | C13: 0 | E13: ='Item-1_AY30013'!G33 -> 336234.83 | G13: ='Item-2_AY30017'!E33 -> 10766.814 | I13: ='Item-3_AY30018'!E33 -> 2807.9474 | K13: ='Item-4_AY30027'!E33 -> 55898.463 | M13: ='Item-5_AY30062'!E33 -> 1667.0183 | O13: ='Item-6_AY30084'!E33 -> 8215.6491 | Q13: ='Item-7_AT30107'!E33 -> 9116.1528 | S13: ='Item-8_AT30133'!E33 -> 12697.733 | U13: ='Item-9_AT30134'!E33 -> 42971.149 | W13: ='Item-10_AT30144'!F33 -> 93760.099 | Y13: ='Item-11_AT30150'!F33 -> 7281.4489 | AA13: ='Item-12_AY30160'!F33 -> 50850.186 | AC13: ='Item-13_AY51606'!F33 -> 13325.958 | AE13: ='Item-14_AY30130'!F33 -> 443934.3
A14: iii. | B14: Paint | C14: 20 | E14: =D6*$C$14 -> 81041.327 | G14: =F6*$C$14 -> 2606.64 | I14: =H6*$C$14 -> 536 | K14: =J6*$C$14 -> 8861.1626 | M14: =L6*$C$14 -> 413.752 | O14: =N6*$C$14 -> 1778.92 | Q14: =P6*$C$14 -> 1610 | S14: =R6*$C$14 -> 2491.468 | U14: =T6*$C$14 -> 7408.5221 | W14: =V6*$C$14 -> 20889.446 | Y14: =X6*$C$14 -> 1310.6 | AA14: =Z6*$C$14 -> 11592 | AC14: =AB6*$C$14 -> 3557.4595 | AE14: =AD6*$C$14 -> 81722.187
A15: iv. | B15: Inspection and Testing | C15: 12 | E15: =D6*$C$15 -> 48624.796 | G15: =F6*$C$15 -> 1563.984 | I15: =H6*$C$15 -> 321.6 | K15: =J6*$C$15 -> 5316.6976 | M15: =L6*$C$15 -> 248.2512 | O15: =N6*$C$15 -> 1067.352 | Q15: =P6*$C$15 -> 966 | S15: =R6*$C$15 -> 1494.8808 | U15: =T6*$C$15 -> 4445.1133 | W15: =V6*$C$15 -> 12533.668 | Y15: =X6*$C$15 -> 786.36 | AA15: =Z6*$C$15 -> 6955.2 | AC15: =AB6*$C$15 -> 2134.4757 | AE15: =AD6*$C$15 -> 49033.312
A16: v. | B16: Packaging | C16: Canrig Scope | E16: 0 | G16: 0 | I16: 0 | K16: 0 | M16: 0 | O16: 0 | Q16: 0 | S16: 0 | U16: 0 | W16: 0 | Y16: 0 | AA16: 0 | AC16: 0 | AE16: 0
B17: TOTAL BASIC COST | E17: =SUM(E9:E16) -> 1019775.9 | G17: =SUM(G9:G16) -> 31283.677 | I17: =SUM(I9:I16) -> 6266.761 | K17: =SUM(K9:K16) -> 113085.23 | M17: =SUM(M9:M16) -> 8087.6686 | O17: =SUM(O9:O16) -> 30416.571 | Q17: =SUM(Q9:Q16) -> 22695.373 | S17: =SUM(S9:S16) -> 43791.254 | U17: =SUM(U9:U16) -> 128895.26 | W17: =SUM(W9:W16) -> 355855.93 | Y17: =SUM(Y9:Y16) -> 26143.938 | AA17: =SUM(AA9:AA16) -> 225812.6 | AC17: =SUM(AC9:AC16) -> 39808.535 | AE17: =SUM(AE9:AE16) -> 1155330.5
A19: C. | B19: Fixed Cost
A20: i | B20: ICC Cost | C20: 0.015 | E20: =E22*$C$20 -> 15769.731 | G20: =G22*$C$20 -> 483.76821 | I20: =I22*$C$20 -> 96.908675 | K20: =K22*$C$20 -> 1748.7407 | M20: =M22*$C$20 -> 125.06704 | O20: =O22*$C$20 -> 470.35934 | Q20: =Q22*$C$20 -> 350.95938 | S20: =S22*$C$20 -> 677.18434 | U20: =U22*$C$20 -> 1993.2256 | W20: =W22*$C$20 -> 5502.9268 | Y20: =Y22*$C$20 -> 404.2877 | AA20: =AA22*$C$20 -> 3491.9475 | AC20: =AC22*$C$20 -> 615.59591 | AE20: =AE22*$C$20 -> 17865.936
A21: ii | B21: Rejection | C21: 0.015 | E21: =E22*$C$21 -> 15769.731 | G21: =G22*$C$21 -> 483.76821 | I21: =I22*$C$21 -> 96.908675 | K21: =K22*$C$21 -> 1748.7407 | M21: =M22*$C$21 -> 125.06704 | O21: =O22*$C$21 -> 470.35934 | Q21: =Q22*$C$21 -> 350.95938 | S21: =S22*$C$21 -> 677.18434 | U21: =U22*$C$21 -> 1993.2256 | W21: =W22*$C$21 -> 5502.9268 | Y21: =Y22*$C$21 -> 404.2877 | AA21: =AA22*$C$21 -> 3491.9475 | AC21: =AC22*$C$21 -> 615.59591 | AE21: =AE22*$C$21 -> 17865.936
B22: Sub Total | E22: =SUM(E20:E21)+E17 -> 1051315.4 | G22: =SUM(G20:G21)+G17 -> 32251.214 | I22: =SUM(I20:I21)+I17 -> 6460.5783 | K22: =SUM(K20:K21)+K17 -> 116582.71 | M22: =SUM(M20:M21)+M17 -> 8337.8027 | O22: =SUM(O20:O21)+O17 -> 31357.289 | Q22: =SUM(Q20:Q21)+Q17 -> 23397.292 | S22: =SUM(S20:S21)+S17 -> 45145.622 | U22: =SUM(U20:U21)+U17 -> 132881.71 | W22: =SUM(W20:W21)+W17 -> 366861.79 | Y22: =SUM(Y20:Y21)+Y17 -> 26952.513 | AA22: =SUM(AA20:AA21)+AA17 -> 232796.5 | AC22: =SUM(AC20:AC21)+AC17 -> 41039.727 | AE22: =SUM(AE20:AE21)+AE17 -> 1191062.4
A24: D. | B24: Variable Cost
A25: i. | B25: Contingency / Warranty | C25: 0.01 | E25: =E28*$C$25 -> 14017.539 | G25: =G28*$C$25 -> 430.01618 | I25: =I28*$C$25 -> 86.141044 | K25: =K28*$C$25 -> 1554.4362 | M25: =M28*$C$25 -> 111.1707 | O25: =O28*$C$25 -> 418.09719 | Q25: =Q28*$C$25 -> 311.96389 | S25: =S28*$C$25 -> 601.94163 | U25: =U28*$C$25 -> 1771.7561 | W25: =W28*$C$25 -> 4891.4905 | Y25: =Y28*$C$25 -> 359.36684 | AA25: =AA28*$C$25 -> 3103.9533 | AC25: =AC28*$C$25 -> 547.19636 | AE25: =AE28*$C$25 -> 15880.832
A26: ii. | B26: Overheads | C26: 0.12 | E26: =E28*$C$26 -> 168210.46 | G26: =G28*$C$26 -> 5160.1942 | I26: =I28*$C$26 -> 1033.6925 | K26: =K28*$C$26 -> 18653.234 | M26: =M28*$C$26 -> 1334.0484 | O26: =O28*$C$26 -> 5017.1663 | Q26: =Q28*$C$26 -> 3743.5667 | S26: =S28*$C$26 -> 7223.2996 | U26: =U28*$C$26 -> 21261.074 | W26: =W28*$C$26 -> 58697.886 | Y26: =Y28*$C$26 -> 4312.4021 | AA26: =AA28*$C$26 -> 37247.44 | AC26: =AC28*$C$26 -> 6566.3563 | AE26: =AE28*$C$26 -> 190569.98
A27: iii. | B27: Contribution / Profit | C27: 0.12 | E27: =E28*$C$27 -> 168210.46 | G27: =G28*$C$27 -> 5160.1942 | I27: =I28*$C$27 -> 1033.6925 | K27: =K28*$C$27 -> 18653.234 | M27: =M28*$C$27 -> 1334.0484 | O27: =O28*$C$27 -> 5017.1663 | Q27: =Q28*$C$27 -> 3743.5667 | S27: =S28*$C$27 -> 7223.2996 | U27: =U28*$C$27 -> 21261.074 | W27: =W28*$C$27 -> 58697.886 | Y27: =Y28*$C$27 -> 4312.4021 | AA27: =AA28*$C$27 -> 37247.44 | AC27: =AC28*$C$27 -> 6566.3563 | AE27: =AE28*$C$27 -> 190569.98
B28: Total Price | E28: =SUM(E22:E27) -> 1401753.9 | G28: =SUM(G22:G27) -> 43001.618 | I28: =SUM(I22:I27) -> 8614.1044 | K28: =SUM(K22:K27) -> 155443.62 | M28: =SUM(M22:M27) -> 11117.07 | O28: =SUM(O22:O27) -> 41809.719 | Q28: =SUM(Q22:Q27) -> 31196.389 | S28: =SUM(S22:S27) -> 60194.163 | U28: =SUM(U22:U27) -> 177175.61 | W28: =SUM(W22:W27) -> 489149.05 | Y28: =SUM(Y22:Y27) -> 35936.684 | AA28: =SUM(AA22:AA27) -> 310395.33 | AC28: =SUM(AC22:AC27) -> 54719.636 | AE28: =SUM(AE22:AE27) -> 1588083.2
A30: F | B30: Transportation | C30: EX Works | E30: 0 | G30: 0 | I30: 0 | K30: 0 | M30: 0 | O30: 0 | Q30: 0 | S30: 0 | U30: 0 | W30: 0 | Y30: 0 | AA30: 0 | AC30: 0 | AE30: 0
B31: Total Price for X Parts | D31: =E3 -> 1 | E31: =SUM(E28:E30) -> 1401753.9 | F31: =G3 -> 2 | G31: =SUM(G28:G30) -> 43001.618 | H31: =I3 -> 1 | I31: =SUM(I28:I30) -> 8614.1044 | J31: =K3 -> 23 | K31: =SUM(K28:K30) -> 155443.62 | L31: =M3 -> 1 | M31: =SUM(M28:M30) -> 11117.07 | N31: =O3 -> 4 | O31: =SUM(O28:O30) -> 41809.719 | P31: =Q3 -> 1 | Q31: =SUM(Q28:Q30) -> 31196.389 | R31: =S3 -> 1 | S31: =SUM(S28:S30) -> 60194.163 | T31: =U3 -> 1 | U31: =SUM(U28:U30) -> 177175.61 | V31: =W3 -> 1 | W31: =SUM(W28:W30) -> 489149.05 | X31: =Y3 -> 1 | Y31: =SUM(Y28:Y30) -> 35936.684 | Z31: =AA3 -> 1 | AA31: =SUM(AA28:AA30) -> 310395.33 | AB31: =AC3 -> 1 | AC31: =SUM(AC28:AC30) -> 54719.636 | AD31: =AE3 -> 1 | AE31: =SUM(AE28:AE30) -> 1588083.2 | AF31: =SUM(E31:AE31) -> 4408629.1
B32: Total Cost Each Part | E32: =E31/E3 -> 1401753.9 | G32: =G31/G3 -> 21500.809 | I32: =I31/I3 -> 8614.1044 | K32: =K31/K3 -> 6758.4181 | M32: =M31/M3 -> 11117.07 | O32: =O31/O3 -> 10452.43 | Q32: =Q31/Q3 -> 31196.389 | S32: =S31/S3 -> 60194.163 | U32: =U31/U3 -> 177175.61 | W32: =W31/W3 -> 489149.05 | Y32: =Y31/Y3 -> 35936.684 | AA32: =AA31/AA3 -> 310395.33 | AC32: =AC31/AC3 -> 54719.636 | AE32: =AE31/AE3 -> 1588083.2
B34: Rate Per Gross Wt kg | E34: =E31/D5 -> 264.59162 | G34: =G31/F5 -> 269.21207 | I34: =I31/H5 -> 290.36107 | K34: =K31/J5 -> 316.8839 | M34: =M31/L5 -> 179.38015 | O34: =O31/N5 -> 427.32484 | Q34: =Q31/P5 -> 226.97736 | S34: =S31/R5 -> 439.27489 | U34: =U31/T5 -> 196.79471 | W34: =W31/V5 -> 397.05409 | Y34: =Y31/X5 -> 355.86167 | AA34: =AA31/Z5 -> 300.68773 | AC34: =AC31/AB5 -> 218.59118 | AE34: =AE31/AD5 -> 329.86809
B35: Rate Per Net Wt kg | E35: =E31/D6 -> 345.93556 | G35: =G31/F6 -> 329.93907 | I35: =I31/H6 -> 321.42181 | K35: =K31/J6 -> 350.84249 | M35: =M31/L6 -> 537.37844 | O35: =O31/N6 -> 470.05733 | Q35: =Q31/P6 -> 387.53279 | S35: =S31/R6 -> 483.20238 | U35: =U31/T6 -> 478.30218 | W35: =W31/V6 -> 468.3217 | Y35: =Y31/X6 -> 548.40049 | AA35: =AA31/Z6 -> 535.5337 | AC35: =AC31/AB6 -> 307.63322 | AE35: =AE31/AD6 -> 388.65411
B36: Internal Cal. Cost Per X parts | D36: =E3 -> 1 | E36: ='Item-1_AY30013'!G36 -> 979120.8 | F36: =G3 -> 2 | G36: ='Item-2_AY30017'!E36 -> 29824.359 | H36: =I3 -> 1 | I36: ='Item-3_AY30018'!E36 -> 5950.0771 | J36: =K3 -> 23 | K36: ='Item-4_AY30027'!E36 -> 108798.11 | L36: =M3 -> 1 | M36: ='Item-5_AY30062'!E36 -> 8168.2319 | N36: =O3 -> 4 | O36: ='Item-6_AY30084'!E36 -> 30327.329 | P36: =Q3 -> 1 | Q36: ='Item-7_AT30107'!E36 -> 22131.311 | R36: =S3 -> 1 | S36: ='Item-8_AT30133'!E36 -> 43785.395 | T36: =U3 -> 1 | U36: ='Item-9_AT30134'!E36 -> 128745.79 | V36: =W3 -> 1 | W36: ='Item-10_AT30144'!F36 -> 354676.1 | X36: =Y3 -> 1 | Y36: ='Item-11_AT30150'!F36 -> 26451.676 | Z36: =AA3 -> 1 | AA36: ='Item-12_AY30160'!F36 -> 227991.94 | AB36: =AC3 -> 1 | AC36: ='Item-13_AY51606'!F36 -> 37528.26 | AD36: =AE3 -> 1 | AE36: ='Item-14_AY30130'!F36 -> 1127032.5
B37: Margin | E37: =E31-E36 -> 422633.07 | G37: =G31-G36 -> 13177.26 | I37: =I31-I36 -> 2664.0274 | K37: =K31-K36 -> 46645.509 | M37: ='Item-5_AY30062'!E36 -> 8168.2319 | O37: =O31-O36 -> 11482.391 | Q37: =Q31-Q36 -> 9065.0788 | S37: =S31-S36 -> 16408.768 | U37: =U31-U36 -> 48429.828 | W37: =W31-W36 -> 134472.95 | Y37: =Y31-Y36 -> 9485.0087 | AA37: =AA31-AA36 -> 82403.388 | AC37: =AC31-AC36 -> 17191.376 | AE37: =AE31-AE36 -> 461050.67
B38: Margin % | E38: =(E31-E36)/E31 -> 0.30150305 | G38: =(G31-G36)/G31 -> 0.30643637 | I38: =(I31-I36)/I31 -> 0.30926342 | K38: =(K31-K36)/K31 -> 0.30007992 | M38: =(M31-M36)/M31 -> 0.26525319 | O38: =(O31-O36)/O31 -> 0.27463448 | Q38: =(Q31-Q36)/Q31 -> 0.29058102 | S38: =(S31-S36)/S31 -> 0.27259732 | U38: =(U31-U36)/U31 -> 0.27334364 | W38: =(W31-W36)/W31 -> 0.27491201 | Y38: =(Y31-Y36)/Y31 -> 0.26393667 | AA38: =(AA31-AA36)/AA31 -> 0.26547882 | AC38: =(AC31-AC36)/AC31 -> 0.31417197 | AE38: =(AE31-AE36)/AE31 -> 0.29031896
B40: FOR EQS 25% margin | E40: =E32*(100%-75%)/100% -> 350438.47 | G40: =G32*(100%-75%)/100% -> 5375.2023 | I40: =I32*(100%-75%)/100% -> 2153.5261 | K40: =K32*(100%-75%)/100% -> 1689.6045 | M40: =M32*(100%-75%)/100% -> 2779.2676 | O40: =O32*(100%-75%)/100% -> 2613.1074 | Q40: =Q32*(100%-75%)/100% -> 7799.0973 | S40: =S32*(100%-75%)/100% -> 15048.541 | U40: =U32*(100%-75%)/100% -> 44293.903 | W40: =W32*(100%-75%)/100% -> 122287.26 | Y40: =Y32*(100%-75%)/100% -> 8984.171 | AA40: =AA32*(100%-75%)/100% -> 77598.833 | AC40: =AC32*(100%-75%)/100% -> 13679.909 | AE40: =AE32*(100%-75%)/100% -> 397020.8
C41: Per Pcs | E41: =E32-E40 -> 1051315.4 | G41: =G32-G40 -> 16125.607 | I41: =I32-I40 -> 6460.5783 | K41: =K32-K40 -> 5068.8136 | M41: =M32-M40 -> 8337.8027 | O41: =O32-O40 -> 7839.3223 | Q41: =Q32-Q40 -> 23397.292 | S41: =S32-S40 -> 45145.622 | U41: =U32-U40 -> 132881.71 | W41: =W32-W40 -> 366861.79 | Y41: =Y32-Y40 -> 26952.513 | AA41: =AA32-AA40 -> 232796.5 | AC41: =AC32-AC40 -> 41039.727 | AE41: =AE32-AE40 -> 1191062.4 | AF41: =SUM(E41:AE41) -> 3155285.1
A44: NON-RECURRING COST | D44: ITEM-1 | F44: ITEM-2 | H44: ITEM-3 | J44: ITEM-4 | L44: ITEM-5 | N44: ITEM-6 | P44: ITEM-7 | R44: ITEM-8 | T44: ITEM-9 | V44: ITEM-10 | X44: ITEM-11 | Z44: ITEM-12 | AB44: ITEM-13 | AD44: ITEM-14
A45: 1 | B45: ENGINEERING CHARGES | E45: ='Item-1_AY30013'!D51 -> 37500 | G45: ='Item-2_AY30017'!D51 -> 5000 | I45: ='Item-3_AY30018'!D51 -> 0 | K45: ='Item-4_AY30027'!D51 -> 0 | M45: ='Item-5_AY30062'!D51 -> 0 | O45: ='Item-6_AY30084'!D51 -> 0 | Q45: ='Item-7_AT30107'!D51 -> 5000 | S45: ='Item-8_AT30133'!D51 -> 0 | U45: ='Item-9_AT30134'!D51 -> 10000 | W45: ='Item-10_AT30144'!D51 -> 20000 | Y45: ='Item-11_AT30150'!D51 -> 5000 | AA45: ='Item-12_AY30160'!D51 -> 12500 | AC45: ='Item-13_AY51606'!D51 -> 0 | AE45: ='Item-14_AY30130'!D51 -> 17500
A46: 2 | B46: DEVELOPMENT OF JIG AND FIXTURES (01 time) | E46: ='Item-1_AY30013'!D50 -> 421553 | G46: ='Item-2_AY30017'!D50 -> 13585 | I46: ='Item-3_AY30018'!D50 -> 0 | K46: ='Item-4_AY30027'!D50 -> 0 | M46: ='Item-5_AY30062'!D50 -> 0 | O46: ='Item-6_AY30084'!D50 -> 0 | Q46: ='Item-7_AT30107'!D50 -> 14212 | S46: ='Item-8_AT30133'!D50 -> 0 | U46: ='Item-9_AT30134'!D50 -> 56491.875 | W46: ='Item-10_AT30144'!D50 -> 239065.88 | Y46: ='Item-11_AT30150'!D50 -> 7132.875 | AA46: ='Item-12_AY30160'!D50 -> 153574.05 | AC46: ='Item-13_AY51606'!D50 -> 0 | AE46: ='Item-14_AY30130'!D50 -> 542906.87
B47: Sub Total | E47: =SUM(E45:E46) -> 459053 | G47: =SUM(G45:G46) -> 18585 | I47: =SUM(I45:I46) -> 0 | K47: =SUM(K45:K46) -> 0 | M47: =SUM(M45:M46) -> 0 | O47: =SUM(O45:O46) -> 0 | Q47: =SUM(Q45:Q46) -> 19212 | S47: =SUM(S45:S46) -> 0 | U47: =SUM(U45:U46) -> 66491.875 | W47: =SUM(W45:W46) -> 259065.88 | Y47: =SUM(Y45:Y46) -> 12132.875 | AA47: =SUM(AA45:AA46) -> 166074.05 | AC47: =SUM(AC45:AC46) -> 0 | AE47: =SUM(AE45:AE46) -> 560406.87
B48: Overheads | C48: 0.1 | E48: =E50*$C$48 -> 58852.949 | G48: =G50*$C$48 -> 2382.6923 | I48: =I50*$C$48 -> 0 | K48: =K50*$C$48 -> 0 | M48: =M50*$C$48 -> 0 | O48: =O50*$C$48 -> 0 | Q48: =Q50*$C$48 -> 2463.0769 | S48: =S50*$C$48 -> 0 | U48: =U50*$C$48 -> 8524.5994 | W48: =W50*$C$48 -> 33213.574 | Y48: =Y50*$C$48 -> 1555.4968 | AA48: =AA50*$C$48 -> 21291.545 | AC48: =AC50*$C$48 -> 0 | AE48: =AE50*$C$48 -> 71847.035
B49: Contribution / Profit | C49: 0.12 | E49: =E50*$C$49 -> 70623.538 | G49: =G50*$C$49 -> 2859.2308 | I49: =I50*$C$49 -> 0 | K49: =K50*$C$49 -> 0 | M49: =M50*$C$49 -> 0 | O49: =O50*$C$49 -> 0 | Q49: =Q50*$C$49 -> 2955.6923 | S49: =S50*$C$49 -> 0 | U49: =U50*$C$49 -> 10229.519 | W49: =W50*$C$49 -> 39856.288 | Y49: =Y50*$C$49 -> 1866.5962 | AA49: =AA50*$C$49 -> 25549.854 | AC49: =AC50*$C$49 -> 0 | AE49: =AE50*$C$49 -> 86216.442
B50: Total | E50: =SUM(E47:E49) -> 588529.49 | G50: =SUM(G47:G49) -> 23826.923 | I50: =SUM(I47:I49) -> 0 | K50: =SUM(K47:K49) -> 0 | M50: =SUM(M47:M49) -> 0 | O50: =SUM(O47:O49) -> 0 | Q50: =SUM(Q47:Q49) -> 24630.769 | S50: =SUM(S47:S49) -> 0 | U50: =SUM(U47:U49) -> 85245.994 | W50: =SUM(W47:W49) -> 332135.74 | Y50: =SUM(Y47:Y49) -> 15554.968 | AA50: =SUM(AA47:AA49) -> 212915.45 | AC50: =SUM(AC47:AC49) -> 0 | AE50: =SUM(AE47:AE49) -> 718470.35 | AF50: =SUM(E50:AE50) -> 2001309.7
B52: Actual Quotated (10-06-2025) Jigs & Fixture | E52: 750000 | G52: 35000 | Q52: 26300 | U52: 105000 | W52: 422000 | Y52: 25400 | AA52: 270000 | AE52: 890000 | AF52: =SUM(E52:AE52) -> 2523700
B53: Actual Quotated (10-06-2025) Engg. | E53: 80000 | G53: 8000 | Q53: 8000 | U53: 12000 | W53: 80000 | Y53: 8000 | AA53: 80000 | AE53: 100000 | AF53: =SUM(E53:AE53) -> 376000
B54: Total | E54: =SUM(E52:E53) -> 830000 | G54: =SUM(G52:G53) -> 43000 | Q54: =SUM(Q52:Q53) -> 34300 | U54: =SUM(U52:U53) -> 117000 | W54: =SUM(W52:W53) -> 502000 | Y54: =SUM(Y52:Y53) -> 33400 | AA54: =SUM(AA52:AA53) -> 350000 | AE54: =SUM(AE52:AE53) -> 990000 | AF54: =SUM(E54:AE54) -> 2899700
B55: NRC Cost Without 20% Margin | E55: =E54*80% -> 664000 | G55: =G54*80% -> 34400 | Q55: =Q54*80% -> 27440 | U55: =U54*80% -> 93600 | W55: =W54*80% -> 401600 | Y55: =Y54*80% -> 26720 | AA55: =AA54*80% -> 280000 | AE55: =AE54*80% -> 792000

Sheet Material Conversion details
B2: Type | C2: DRG. Material | D2: Alt. Material | G2: Type | H2: Size (mm) | I2: Alternate size (mm) (As per indian availablity) | J2: Remarks
B3: Beam | C3: ASTM A572 Gr. 50 / S355JR | D3: IS 2062 E350 A/BR | G3: Beam | H3: W-BEAM, 190 X 450 | I3: NPB 450x190x 67.16
B4: BOP Unistruct | C4: G40.21-44W / A572 G50 | D4: Gi Sheet 2mm thk | G4: Beam | H4: W-BEAM 600 X 220 | I4: NPB 600x 220x 107.57
B5: Channel | C5: A36/S275JR | D5: IS 2062 E250 A/BR | G5: Channel | H5: UPN 200 x 75 | I5: ISMC 200 x 75
B6: Channel | C6: ASTM A572 Gr. 50 / S355JR | D6: IS 2062 E350 A/BR | G6: Channel | H6: UPN 160 X 65 | I6: ISMC 175x 75 | J6: Or builtup to achive the Dimension as per UPN 160 with suitable thickness and material
B7: Pipe | C7: ASTM A106 GR.B | D7: ASTM A106 GR.B | G7: Channel | H7: UPN 80 X 45 | I7: ISMC 75x40 | J7: Or builtup to achive the Dimension as per UPN 160 with suitable thickness and material
B8: Pipe | C8: G40.21-44W | D8: ASTM A106 GR.B | G8: Rec Tube | H8: 100x80x 5thk | I8: 100x80x6
B9: Pipe | C9: G40.21-44W / A572 G50 | D9: ASTM A106 GR.B | G9: Rec Tube | H9: 120x80x 5thk | I9: 120x80x6.5
B10: Pipe | C10: EN 10216-2 P265GH | D10: ASTM A106 GR.B | G10: Rec Tube | H10: 150x100x 12thk | I10: 150x100x11to12
B11: Plate | C11: ASTM A572 Gr. 50 / A516 Gr.70 / S355JR/ G40.21-44W | D11: IS 2062 E350 A/BR | G11: Rec Tube | H11: 150x80x 10thk | I11: 150x80x9.5 to 10thk
B12: Plate | C12: A36/S275JR/SA 516 GR.70 | D12: IS 2062 E250 A/BR | G12: Rec Tube | H12: 200x150x 12thk | J12: Available as required
B13: Plate | C13: A.S.T.M. A106 GR.B | D13: IS 2062 E350 A/BR | G13: Rec Tube | H13: 150x50x 6thk | J13: Available as required
B14: Plate | C14: EN 10025-2 S355J2 | D14: IS 2062 E350 A/BR | G14: Sq. Tube | H14: 40x40x 5thk | J14: Available as required
B15: Rod | C15: A36/275JR | D15: IS 2062 E250 A/BR | G15: Sq. Tube | H15: 50x50x 5thk | J15: Available as required
B16: Rod | C16: BROWNING SCS-2 | D16: EN 19 | G16: Sq. Tube | H16: 80x80x 10thk | I16: 80x80x 8thk
B17: Rod | C17: AISI C1045 | D17: EN 19 | G17: Pipe | H17: Dia 101.6 x 8.08 thk | J17: Available as required
B18: Rod | C18: A572 Gr. 50 | D18: IS 2062 E350 A/BR | G18: Pipe | H18: Dia 114.3 x 8.56 thk | J18: Available as required
B19: Tube | C19: A36/S275JR | D19: YST 310 | G19: Pipe | H19: Dia 168.28 x 10.97thk | J19: Available as required
B20: Tube | C20: ASTM A516 Gr.70/S275JR | D20: YST 310 | G20: Pipe | H20: Dia 21.3 x 2.77 thk | J20: Available as required
B21: Tube | C21: ASTM A500 GR B | D21: YST 310 | G21: Pipe | H21: Dia 33.4x 6.35 | J21: Available as required
B22: Tube | C22: EN 10025-2 S355J2 | D22: YST 310 | G22: Pipe | H22: Dia 60.3 x 3.91 thk | J22: Available as required

Sheet Item-14_AY30130
A1: COSTING SHEET
A2: PRODUCT NAME:- | B2: ='BOM R2D CatWalk'!I201 -> WELDMENT, PC4100,42' CATWALK, RAMP B | E2: RFQ Ref.
A3: ITEM DRG NO | B3: ='BOM R2D CatWalk'!G201 -> AY30130 | E3: Total Quantity | F3: ='BOM R2D CatWalk'!K201 -> 1
A4: Total Net WT as per Drawing | C4: ='BOM R2D CatWalk'!N201 -> 4003
A5: COSTBREAKUP OF COMPONENT (QTY-01 No.) | J5: Assy No | Q5: ='RM Details'!H183 -> AY30130
A6: RAW MATERIAL COST | J6: S.No | K6: Type | L6: Size (mm) | M6: Material | N6: Sum of Total Weight (Kg) | O6: Sum of Gross Wt (kg) | P6: MOQ Weight | Q6: Remarks | R6: Cal. Weight | S6: Rate/Kg | T6: Cost
A7: SPEC | B7: IS 2062 E350 A/BO | C7: IS 2062 E250 A/BO | D7: YST 310 | E7: =M14 -> AISI C1045 | F7: Rolled Section E350A | J7: 1 | K7: Plate | L7: 6 | M7: E350 A/BR | N7: ='RM Details'!E185 -> 1.6 | O7: ='RM Details'!F185 -> 2.5667192 | R7: =IF(P7>O7,P7,IF(P7<O7,O7)) -> 2.5667192 | S7: 90 | T7: =S7*R7 -> 231.00473
A8: GROSS WT. (KG) | B8: =SUM(O7:O9) -> 1607.8875 | C8: =SUM(O10:O11) -> 259.71541 | D8: =SUM(O12:O13) -> 950.36093 | E8: =O14 -> 13.35774 | F8: =O15+O16 -> 1982.9762 | G8: =SUM(B8:F8) -> 4814.2978 | J8: 2 | K8: Plate | L8: 10 | M8: E350 A/BR | N8: ='RM Details'!E186 -> 978.4 | O8: ='RM Details'!F186 -> 1102.0319 | R8: =IF(P8>O8,P8,IF(P8<O8,O8)) -> 1102.0319 | S8: 90 | T8: =S8*R8 -> 99182.867
A9: NET WT (KG) | B9: =SUM(N7:N9) -> 1231.6685 | C9: =SUM(N10:N11) -> 181.0556 | D9: =SUM(N12:N13) -> 863.96448 | E9: =N14 -> 11.2 | F9: =N15+N16 -> 1798.2208 | G9: =SUM(B9:F9) -> 4086.1094 | J9: 3 | K9: Plate | L9: 12 | M9: E350 A/BR | N9: ='RM Details'!E187 -> 251.66848 | O9: ='RM Details'!F187 -> 503.28897 | R9: =IF(P9>O9,P9,IF(P9<O9,O9)) -> 503.28897 | S9: 90 | T9: =S9*R9 -> 45296.007
A10: SCRAP (KG) | B10: =(B8-B9)*80% -> 300.97526 | C10: =(C8-C9)*80% -> 62.92785 | D10: =(D8-D9)*80% -> 69.117158 | E10: =(E8-E9)*80% -> 1.726192 | F10: =(F8-F9)*80% -> 147.80429 | G10: =(G8-G9)/G9 -> 0.17821071 | J10: 4 | K10: Plate | L10: 12 | M10: E250 A/BR | N10: ='RM Details'!E188 -> 29.9556 | O10: ='RM Details'!F188 -> 32.95116 | R10: =IF(P10>O10,P10,IF(P10<O10,O10)) -> 32.95116 | S10: 90 | T10: =S10*R10 -> 2965.6044
A11: RM RATE (RS/KG) | B11: 90 | C11: 90 | D11: 200 | E11: 150 | F11: 120 | G11: =SUMPRODUCT(B11:F11,B8:F8) -> 598117.25 | J11: 5 | K11: Plate | L11: 20 | M11: E250 A/BR | N11: ='RM Details'!E189 -> 151.1 | O11: ='RM Details'!F189 -> 226.76425 | R11: =IF(P11>O11,P11,IF(P11<O11,O11)) -> 226.76425 | S11: 90 | T11: =S11*R11 -> 20408.783
A12: SCRAP RATE (RS/KG) | B12: 30 | C12: 30 | D12: 30 | E12: 30 | F12: 30 | J12: 6 | K12: Rec Tube | L12: 150x50x 6thk | M12: YST 310 | N12: ='RM Details'!E190 -> 39.95376 | O12: ='RM Details'!F190 -> 43.949136 | P12: =17.71*6 -> 106.26 | R12: =IF(P12>O12,P12,IF(P12<O12,O12)) -> 106.26 | S12: 200 | T12: =S12*R12 -> 21252
A13: NET RM COST (RS) | B13: =(B8*B11)-(B10*B12) -> 135680.62 | C13: =(C8*C11)-(C10*C12) -> 21486.552 | D13: =(D8*D11)-(D10*D12) -> 187998.67 | E13: =(E8*E11)-(E10*E12) -> 1951.8752 | F13: =(F8*F11)-(F10*F12) -> 233523.01 | G13: =SUM(B13:F13) -> 580640.73 | J13: 7 | K13: Rec Tube | L13: 200x150x 12thk | M13: YST 310 | N13: ='RM Details'!E191 -> 824.01072 | O13: ='RM Details'!F191 -> 906.41179 | P13: =61.42*6 -> 368.52 | R13: =IF(P13>O13,P13,IF(P13<O13,O13)) -> 906.41179 | S13: 200 | T13: =S13*R13 -> 181282.36 | U13: =(T12+T13)/(R12+R13) -> 200
A14: TOTAL (RS) | B14: =SUM(B13:F13) -> 580640.73 | G14: =G13/G8 -> 120.60756 | J14: 8 | K14: ROD | L14: Dia 30 | M14: ='RM Details'!D192 -> AISI C1045 | N14: ='RM Details'!E192 -> 11.2 | O14: ='RM Details'!F192 -> 13.35774 | P14: =5.55*1 -> 5.55 | R14: =IF(P14>O14,P14,IF(P14<O14,O14)) -> 13.35774 | S14: 150 | T14: =S14*R14 -> 2003.661
A15: BOP COST | J15: 9 | K15: ROD | L15: Dia 142 | M15: E350 A/BR | N15: ='RM Details'!E193 -> 32.2 | O15: ='RM Details'!F193 -> 49.23072 | P15: =124.32*1 -> 124.32 | R15: =IF(P15>O15,P15,IF(P15<O15,O15)) -> 124.32 | S15: 120 | T15: =S15*R15 -> 14918.4
A16: BOP COST (RS) | J16: 10 | K16: Plate | L16: UPN 160 X 65 X 18.8 | M16: E350 A/BR | N16: ='RM Details'!E194 -> 1766.0208 | O16: ='RM Details'!F194 -> 1933.7454 | P16: =18.8*6 -> 112.8 | R16: =IF(P16>O16,P16,IF(P16<O16,O16)) -> 1933.7454 | S16: 120 | T16: =S16*R16 -> 232049.45
A17: TOTAL BOP | F17: =SUM(F16:F16) -> 0 | L17: Total | N17: =SUM(N7:N16) -> 4086.1094 | O17: =SUM(O7:O16) -> 4814.2978 | R17: =SUM(R7:R16) -> 4951.6979 | S17: =T17/R17 -> 125.1268 | T17: =SUM(T7:T16) -> 619590.14
A18: TOTAL OF RM + BOP (RS) | F18: =B14+F17 -> 580640.73
A19: PROCESS COST
A20: SPEC | B20: QTY | D20: RATE | F20: TOTAL COST
A21: LASER /PLASMA/PIPE - Cutting (Min.) | B21: ='BOM R2D CatWalk'!X201 -> 233.00992 | D21: 50 | F21: =B21*D21 -> 11650.496 | H21: =F21/$G$9 -> 2.8512443
A22: Machining (Hrs) | B22: ='BOM R2D CatWalk'!AB201/60+1 -> 3.3333333 | D22: 1000 | F22: =B22*D22 -> 3333.3333 | H22: =F22/$G$9 -> 0.81577193
A23: BENDING BY CNC BENDING (STROKE) | B23: ='BOM R2D CatWalk'!Z201 -> 12 | D23: 100 | F23: =B23*D23 -> 1200 | H23: =F23/$G$9 -> 0.2936779
A24: MIG WELDING (MTR.) | B24: 502 | D24: 300 | F24: =B24*D24 -> 150600 | H24: =F24/$G$9 -> 36.856576
A25: GRINDING/BUFFING & FINISHING (hrs) | B25: =B24/12.5 -> 40.16 | D25: 250 | F25: =B25*D25 -> 10040 | H25: =F25/$G$9 -> 2.4571051
A26: INSPECTION & TESTING (HRS) | B26: =G9/95 -> 43.011677 | D26: 1200 | F26: =B26*D26 -> 51614.013 | H26: =F26/$G$9 -> 12.631579
A27: STRESS RELIEVING | D27: 250 | F27: =B27*D27 -> 0 | G27: As Actual, If required | H27: =F27/$G$9 -> 0
A28: Shot Blasting | D28: 5 | F28: =D28*G9 -> 20430.547 | H28: =F28/$G$9 -> 5
A29: Hot Dip Galvanization | B29: 0 | D29: 50 | F29: =B29*D29 -> 0 | H29: =F29/$G$9 -> 0
A30: PAINTING (including material & Labor) | B30: ='BOM R2D CatWalk'!AI201 -> 147.17993 | D30: 1200 | F30: =B30*D30 -> 176615.92 | G30: No paint Detail Found | H30: =F30/$G$9 -> 43.223492
A31: Stamping Cost (HRS) | B31: =15/60 -> 0.25 | D31: 250 | F31: =B31*D31 -> 62.5 | H31: =F31/$G$9 -> 0.015295724
A32: FE cost | D32: 4.5 | F32: =D32*G9 -> 18387.492 | H32: =F32/$G$9 -> 4.5
A33: TOTAL PROCESS COST OF PC | F33: =SUM(F21:F32) -> 443934.3 | H33: =F33/$G$9 -> 108.64474
A34: TOTAL RM+BOP+PC | F34: =F18+F33 -> 1024575
A35: OH + Contingency | E35: 0.1 | F35: =F34*E35 -> 102457.5 | H35: =F35/$G$9 -> 25.074587
A36: Total Product Cost Without Profit | F36: =SUM(F34:F35) -> 1127032.5 | H36: =F36/G9 -> 275.82045
G39: Min.
A40: NOTES:- | F40: OTHER COST | G40: Min.
A41: No BOP found in the Drawing Details
A42: Stress relieveing NOT FOUND ON PRINTS, IF REQUIRED | F42: As Actual
A45: NRC COST BREAKUP
A46: Fixture Details | B46: Approx Wt /Days | C46: Rate | D46: Cost
A47: Tacking Fixture main Frame | B47: =C4*1.2 -> 4803.6 | C47: 100 | D47: =B47*C47 -> 480360
A48: Templates | B48: =C4*0.1/2 -> 200.15 | C48: 200 | D48: =B48*C48 -> 40030
A49: FE COST | B49: =SUM(B47:B48) -> 5003.75 | C49: 4.5 | D49: =B49*C49 -> 22516.875
A50: SUB TOTAL | D50: =SUM(D47:D49) -> 542906.87
A51: Development and Engg | B51: 7 | C51: =75000/30 -> 2500 | D51: =B51*C51 -> 17500
A52: OH + Contingency | C52: 0.0255 | D52: =(D50+D51)*C52 -> 14290.375
A53: Total Cost | D53: =SUM(D50:D52) -> 574697.25

Sheet Item-13_AY51606
A1: COSTING SHEET
A2: PRODUCT NAME:- | B2: ='BOM R2D CatWalk'!I187 -> KIT, SHIPPING BRKTS, LONG,PC4000 | D2: RFQ Ref.
A3: ITEM DRG NO | B3: ='BOM R2D CatWalk'!G187 -> AY51606 | D3: Total Quantity | E3: ='BOM R2D CatWalk'!K187 -> 1
A4: Total Net WT as per Drawing | B4: ='BOM R2D CatWalk'!N187 -> 175.0738 | J4: Assy No | Q4: ='RM Details'!H172 -> AY51606
A5: COSTBREAKUP OF COMPONENT (QTY-01 No.) | J5: S.No | K5: Type | L5: Size (mm) | M5: Material | N5: Sum of Total Weight (Kg) | O5: Sum of Gross Wt (kg) | P5: MOQ Weight | Q5: Remarks | R5: Cal. Weight | S5: Rate/Kg | T5: Cost
A6: RAW MATERIAL COST | J6: 1 | K6: Plate | L6: 10 | M6: E350 A/BR | N6: ='RM Details'!E174 -> 45.0747 | O6: ='RM Details'!F174 -> 49.58217 | R6: =IF(P6>O6,P6,IF(P6<O6,O6)) -> 49.58217 | S6: 90 | T6: =S6*R6 -> 4462.3953
A7: SPEC | F7: IS 2062: E350 A/BR | J7: 2 | K7: Plate | L7: 12 | M7: E350 A/BR | N7: ='RM Details'!E175 -> 36.854949 | O7: ='RM Details'!F175 -> 43.271712 | R7: =IF(P7>O7,P7,IF(P7<O7,O7)) -> 43.271712 | S7: 90 | T7: =S7*R7 -> 3894.4541
A8: GROSS WT. (KG) | F8: =R9 -> 250.32865 | G8: =SUM(C8:F8) -> 250.32865 | J8: 3 | K8: Plate | L8: 40 | M8: E350 A/BR | N8: ='RM Details'!E176 -> 95.943328 | O8: ='RM Details'!F176 -> 157.47477 | R8: =IF(P8>O8,P8,IF(P8<O8,O8)) -> 157.47477 | S8: 90 | T8: =S8*R8 -> 14172.729
A9: NET WT (KG) | F9: =N9 -> 177.87298 | G9: =SUM(C9:F9) -> 177.87298 | L9: Total | N9: =SUM(N6:N8) -> 177.87298 | O9: =SUM(O6:O8) -> 250.32865 | R9: =SUM(R6:R8) -> 250.32865 | S9: =T9/R9 -> 90 | T9: =SUM(T6:T8) -> 22529.579
A10: SCRAP (KG) | F10: =(F8-F9)*80% -> 57.964538 | G10: =(G8-G9)/G9 -> 0.40734503
A11: RM RATE (RS/KG) | F11: 90 | G11: =SUMPRODUCT(B11:F11,B8:F8) -> 22529.578
A12: SCRAP RATE (RS/KG) | F12: 30
A13: NET RM COST (RS) | F13: =(F8*F11)-(F10*F12) -> 20790.642 | G13: =SUM(B13:F13) -> 20790.642
A14: TOTAL (RS) | B14: =SUM(B13:F13) -> 20790.642 | G14: =G13/G8 -> 83.053387
A15: BOP COST
A16: BOP COST (RS)
A17: TOTAL BOP | F17: =SUM(F16:F16) -> 0
A18: TOTAL OF RM + BOP (RS) | F18: =B14+F17 -> 20790.642
A19: PROCESS COST
A20: SPEC | B20: QTY | C20: RATE | F20: TOTAL COST
A21: LASER /PLASMA/PIPE - Cutting (Min.) | B21: ='BOM R2D CatWalk'!X187 -> 27.447842 | C21: 45 | F21: =B21*C21 -> 1235.1529 | H21: =F21/$G$9 -> 6.9440164
A22: Machining (Hrs) | B22: ='BOM R2D CatWalk'!AB187/60 -> 0.66666667 | C22: 600 | F22: =B22*C22 -> 400 | H22: =F22/$G$9 -> 2.2487958
A23: BENDING BY CNC BENDING (STROKE) | B23: ='BOM R2D CatWalk'!Z187 -> 0 | C23: 100 | F23: =B23*C23 -> 0 | H23: =F23/$G$9 -> 0
A24: MIG WELDING (MTR.) | B24: ='BOM R2D CatWalk'!AF187 -> 13.032 | C24: 250 | F24: =B24*C24 -> 3258 | H24: =F24/$G$9 -> 18.316442
A25: GRINDING/BUFFING & FINISHING (hrs) | B25: =B24/12 -> 1.086 | C25: 250 | F25: =B25*C25 -> 271.5 | H25: =F25/$G$9 -> 1.5263701
A26: INSPECTION & TESTING (HRS) | B26: =G9/95 -> 1.8723471 | C26: 1200 | F26: =B26*C26 -> 2246.8166 | H26: =F26/$G$9 -> 12.631579
A27: STRESS RELIEVING | C27: 250 | F27: =B27*C27 -> 0 | G27: As Actual, If required | H27: =F27/$G$9 -> 0
A28: Shot Blasting | C28: 5 | F28: =C28*G9 -> 889.36489 | H28: =F28/$G$9 -> 5
A29: Hot Dip Galvanization | B29: 0 | C29: 50 | F29: =B29*C29 -> 0 | H29: =F29/$G$9 -> 0
A30: PAINTING (including material & Labor) | B30: ='BOM R2D CatWalk'!AI187 -> 3.329756 | C30: 1250 | F30: =B30*C30 -> 4162.195 | G30: No paint Detail Found | H30: =F30/$G$9 -> 23.399816
A31: Stamping Cost (HRS) | B31: =15/60 -> 0.25 | C31: 250 | F31: =B31*C31 -> 62.5 | H31: =F31/$G$9 -> 0.35137434
A32: FE cost | C32: 4.5 | F32: =C32*G9 -> 800.4284 | H32: =F32/$G$9 -> 4.5
A33: TOTAL PROCESS COST OF PC | F33: =SUM(F21:F32) -> 13325.958 | H33: =F33/$G$9 -> 74.918394
A34: TOTAL RM+BOP+PC | F34: =F18+F33 -> 34116.6
A35: OH + Contingency | D35: 0.1 | F35: =F34*D35 -> 3411.66 | H35: =F35/$G$9 -> 19.180317
A36: Total Product Cost Without Profit | F36: =SUM(F34:F35) -> 37528.26 | H36: =F36/G9 -> 210.98348 | I36: =F36/G8 -> 149.91596
G39: Min.
A40: NOTES:- | F40: OTHER COST | G40: Min.
A41: No BOP found in the Drawing Details
A42: Stress relieveing NOT FOUND ON PRINTS, IF REQUIRED | F42: As Actual
A45: NRC COST BREAKUP
A46: Fixture Details | B46: Approx Wt /Days | C46: Rate | D46: Cost
A47: Tacking Fixture main Frame | C47: 100 | D47: =B47*C47 -> 0
A48: Testing Templates /Guided Rod | C48: 100 | D48: =B48*C48 -> 0
A49: FE COST | C49: 4.5 | D49: =B49*C49 -> 0
A50: SUB TOTAL | D50: =SUM(D47:D49) -> 0
A51: Development and Engg | C51: =75000/30 -> 2500 | D51: =B51*C51 -> 0
A52: OH + Contingency | C52: 0.0255 | D52: =(D50+D51)*C52 -> 0
A53: Total Cost | D53: =SUM(D50:D52) -> 0

Sheet Item-12_AY30160
A1: COSTING SHEET
A2: PRODUCT NAME:- | B2: ='BOM R2D CatWalk'!I171 -> WELDMENT,42D CARRIER REAR, PC4100 | D2: RFQ Ref.
A3: ITEM DRG NO | B3: ='BOM R2D CatWalk'!G171 -> AY30160 | D3: Total Quantity | E3: ='BOM R2D CatWalk'!K171 -> 1
A4: Total Net WT as per Drawing | B4: ='BOM R2D CatWalk'!N171 -> 777 | J4: Assy No | Q4: ='RM Details'!H154 -> AY30160
A5: COSTBREAKUP OF COMPONENT (QTY-01 No.) | J5: S.No | K5: Type | L5: Size (mm) | M5: Material | N5: Sum of Total Weight (Kg) | O5: Sum of Gross Wt (kg) | P5: MOQ Weight | Q5: Remarks | R5: Cal. Weight | S5: Rate/Kg | T5: Cost
A6: RAW MATERIAL COST | J6: 1 | K6: Plate | L6: 6 | M6: E350 A/BR | N6: ='RM Details'!E156 -> 1.2 | O6: ='RM Details'!F156 -> 1.2045825 | R6: =IF(P6>O6,P6,IF(P6<O6,O6)) -> 1.2045825 | S6: 90 | T6: =S6*R6 -> 108.41243
A7: SPEC | B7: IS 2062: E350 A/BR | C7: IS 2062: E250 A/BR | D7: YST 310 | E7: =M13 -> AISI C1045 | F7: Rolled Section E350A/BR | J7: 2 | K7: Plate | L7: 10 | M7: E350 A/BR | N7: ='RM Details'!E157 -> 46 | O7: ='RM Details'!F157 -> 68.055025 | R7: =IF(P7>O7,P7,IF(P7<O7,O7)) -> 68.055025 | S7: 90 | T7: =S7*R7 -> 6124.9523
A8: GROSS WT. (KG) | B8: =SUM(R6:R9) -> 269.88996 | C8: =SUM(R10:R11) -> 99.897452 | D8: =R12 -> 368.52 | E8: =R13 -> 31.96 | F8: =R14 -> 531.9072 | G8: =SUM(C8:F8) -> 1032.2847 | J8: 3 | K8: Plate | L8: 12 | M8: E350 A/BR | N8: ='RM Details'!E158 -> 149.6 | O8: ='RM Details'!F158 -> 199.55098 | R8: =IF(P8>O8,P8,IF(P8<O8,O8)) -> 199.55098 | S8: 90 | T8: =S8*R8 -> 17959.588
A9: NET WT (KG) | B9: =SUM(N6:N9) -> 197.78125 | C9: =SUM(N10:N11) -> 71 | D9: =N12 -> 25 | E9: =N13 -> 1.6 | F9: =N14 -> 482 | G9: =SUM(C9:F9) -> 579.6 | J9: 3 | K9: Plate | L9: 25 | M9: E350 A/BR | N9: ='RM Details'!E159 -> 0.98125 | O9: ='RM Details'!F159 -> 1.079375 | R9: =IF(P9>O9,P9,IF(P9<O9,O9)) -> 1.079375 | S9: 90 | T9: =S9*R9 -> 97.14375
A10: SCRAP (KG) | B10: =(B8-B9)*80% -> 57.686972 | C10: =(C8-C9)*80% -> 23.117961 | D10: =(D8-D9)*80% -> 274.816 | E10: =(E8-E9)*80% -> 24.288 | F10: =(F8-F9)*80% -> 39.92576 | G10: =(G8-G9)/G9 -> 0.78102942 | J10: 4 | K10: Plate | L10: 20 | M10: E250 A/BR | N10: ='RM Details'!E160 -> 47 | O10: ='RM Details'!F160 -> 54.871971 | R10: =IF(P10>O10,P10,IF(P10<O10,O10)) -> 54.871971 | S10: 90 | T10: =S10*R10 -> 4938.4774
A11: RM RATE (RS/KG) | B11: 90 | C11: 90 | D11: 200 | E11: 110 | F11: 110 | G11: =SUMPRODUCT(B11:F11,B8:F8) -> 169010.26 | J11: 5 | K11: Plate | L11: 25 | M11: E250 A/BR | N11: ='RM Details'!E161 -> 24 | O11: ='RM Details'!F161 -> 45.025481 | R11: =IF(P11>O11,P11,IF(P11<O11,O11)) -> 45.025481 | S11: 90 | T11: =S11*R11 -> 4052.2932
A12: SCRAP RATE (RS/KG) | B12: 30 | C12: 30 | D12: 30 | E12: 30 | F12: 30 | J12: 6 | K12: Plate | L12: 200 X 150 X 12thk | M12: YST 310 | N12: ='RM Details'!E162 -> 25 | O12: ='RM Details'!F162 -> 38.84815 | P12: =61.42*6 -> 368.52 | R12: =IF(P12>O12,P12,IF(P12<O12,O12)) -> 368.52 | S12: 200 | T12: =S12*R12 -> 73704
A13: NET RM COST (RS) | B13: =(B8*B11)-(B10*B12) -> 22559.488 | C13: =(C8*C11)-(C10*C12) -> 8297.2318 | D13: =(D8*D11)-(D10*D12) -> 65459.52 | E13: =(E8*E11)-(E10*E12) -> 2786.96 | F13: =(F8*F11)-(F10*F12) -> 57312.019 | G13: =SUM(B13:F13) -> 156415.22 | J13: 7 | K13: Plate | L13: Dia 72 | M13: AISI C1045 | N13: ='RM Details'!E163 -> 1.6 | O13: ='RM Details'!F163 -> 1.76 | P13: =31.96*1 -> 31.96 | R13: =IF(P13>O13,P13,IF(P13<O13,O13)) -> 31.96 | S13: 110 | T13: =S13*R13 -> 3515.6
A14: TOTAL (RS) | B14: =SUM(B13:F13) -> 156415.22 | G14: =G13/G8 -> 151.52334 | J14: 8 | K14: Plate | L14: NPB 450x190x67.16 | M14: IS 2062 E 350 A | N14: ='RM Details'!E164 -> 482 | O14: ='RM Details'!F164 -> 531.9072 | P14: =67.16*6 -> 402.96 | R14: =IF(P14>O14,P14,IF(P14<O14,O14)) -> 531.9072 | S14: 110 | T14: =S14*R14 -> 58509.792
A15: BOP COST | L15: Total | N15: =SUM(N6:N14) -> 777.38125 | O15: =SUM(O6:O14) -> 942.30277 | R15: =SUM(R6:R14) -> 1302.1746 | S15: =T15/R15 -> 129.79078 | T15: =SUM(T6:T14) -> 169010.26
A16: BOP COST (RS)
A17: TOTAL BOP | F17: =SUM(F16:F16) -> 0
A18: TOTAL OF RM + BOP (RS) | F18: =B14+F17 -> 156415.22
A19: PROCESS COST
A20: SPEC | B20: QTY | C20: RATE | F20: TOTAL COST
A21: LASER /PLASMA/PIPE - Cutting (Min.) | B21: ='BOM R2D CatWalk'!X171 -> 94.168469 | C21: 30 | F21: =B21*C21 -> 2825.0541 | H21: =F21/$G$9 -> 4.8741444
A22: Machining (Hrs) | B22: ='BOM R2D CatWalk'!AB171/60 -> 4.3166667 | C22: 1250 | F22: =B22*C22 -> 5395.8333 | H22: =F22/$G$9 -> 9.3095813
A23: BENDING BY CNC BENDING (STROKE) | B23: ='BOM R2D CatWalk'!Z171 -> 3 | C23: 100 | F23: =B23*C23 -> 300 | H23: =F23/$G$9 -> 0.51759834
A24: MIG WELDING (MTR.) | B24: 71.2 | C24: 250 | F24: =B24*C24 -> 17800 | H24: =F24/$G$9 -> 30.710835
A25: GRINDING/BUFFING & FINISHING (hrs) | B25: =B24/12 -> 5.9333333 | C25: 250 | F25: =B25*C25 -> 1483.3333 | H25: =F25/$G$9 -> 2.5592363
A26: INSPECTION & TESTING (HRS) | B26: =G9/95 -> 6.1010526 | C26: 1200 | F26: =B26*C26 -> 7321.2632 | H26: =F26/$G$9 -> 12.631579
A27: STRESS RELIEVING | C27: 250 | F27: =B27*C27 -> 0 | G27: As Actual, If required | H27: =F27/$G$9 -> 0
A28: Shot Blasting | C28: 5 | F28: =C28*G9 -> 2898 | H28: =F28/$G$9 -> 5
A29: Hot Dip Galvanization | B29: 0 | C29: 50 | F29: =B29*C29 -> 0 | H29: =F29/$G$9 -> 0
A30: PAINTING (including material & Labor) | B30: ='BOM R2D CatWalk'!AI171 -> 8.1248013 | C30: 1250 | F30: =B30*C30 -> 10156.002 | G30: No paint Detail Found | H30: =F30/$G$9 -> 17.522432
A31: Stamping Cost (HRS) | B31: =15/60 -> 0.25 | C31: 250 | F31: =B31*C31 -> 62.5 | H31: =F31/$G$9 -> 0.10783299
A32: FE cost | C32: 4.5 | F32: =C32*G9 -> 2608.2 | H32: =F32/$G$9 -> 4.5
A33: TOTAL PROCESS COST OF PC | F33: =SUM(F21:F32) -> 50850.186 | H33: =F33/$G$9 -> 87.733239
A34: TOTAL RM+BOP+PC | F34: =F18+F33 -> 207265.4
A35: OH + Contingency | D35: 0.1 | F35: =F34*D35 -> 20726.54 | H35: =F35/$G$9 -> 35.760077
A36: Total Product Cost Without Profit | F36: =SUM(F34:F35) -> 227991.94 | H36: =F36/G9 -> 393.36084 | I36: =F36/G8 -> 220.86151
G39: Min.
A40: NOTES:- | F40: OTHER COST | G40: Min.
A41: No BOP found in the Drawing Details
A42: Stress relieveing NOT FOUND ON PRINTS, IF REQUIRED | F42: As Actual
A45: NRC COST BREAKUP
A46: Fixture Details | B46: Approx Wt /Days | C46: Rate | D46: Cost
A47: Tacking Fixture main Frame | B47: =B4*1.5 -> 1165.5 | C47: 100 | D47: =B47*C47 -> 116550
A48: Testing Templates /Guided Rod | B48: =B4*0.2 -> 155.4 | C48: 200 | D48: =B48*C48 -> 31080
A49: FE COST | B49: =SUM(B47:B48) -> 1320.9 | C49: 4.5 | D49: =B49*C49 -> 5944.05
A50: SUB TOTAL | D50: =SUM(D47:D49) -> 153574.05
A51: Development and Engg | B51: 5 | C51: =75000/30 -> 2500 | D51: =B51*C51 -> 12500
A52: OH + Contingency | C52: 0.0255 | D52: =(D50+D51)*C52 -> 4234.8883
A53: Total Cost | D53: =SUM(D50:D52) -> 170308.94

Sheet Item-11_AT30150
A1: COSTING SHEET
A2: PRODUCT NAME:- | B2: ='BOM R2D CatWalk'!I162 -> WELDMENT, SPEAR FRAME, PC4100 | D2: RFQ Ref.
A3: ITEM DRG NO | B3: ='BOM R2D CatWalk'!G162 -> AY30150 | D3: Total Quantity | E3: ='BOM R2D CatWalk'!K162 -> 1
A4: Total Net WT as per Drawing | B4: ='BOM R2D CatWalk'!N162 -> 69 | J4: Assy No | Q4: ='RM Details'!H141 -> AY30150
A5: COSTBREAKUP OF COMPONENT (QTY-01 No.) | J5: S.No | K5: Type | L5: Size (mm) | M5: Material | N5: Sum of Total Weight (Kg) | O5: Sum of Gross Wt (kg) | P5: MOQ Weight | Q5: Remarks | R5: Cal. Weight | S5: Rate/Kg | T5: Cost
A6: RAW MATERIAL COST | J6: 1 | K6: Plate | L6: 12 | M6: E350 A/BR | N6: ='RM Details'!E143 -> 4.4 | O6: ='RM Details'!F143 -> 8.4330101 | R6: =IF(P6>O6,P6,IF(P6<O6,O6)) -> 8.4330101 | S6: 90 | T6: =S6*R6 -> 758.97091
A7: SPEC | C7: IS 2062: E350 A/BR | D7: IS 2062: E250 A/BR | E7: YST 310 | F7: ROD E250A/BR | J7: 2 | K7: Pipe | L7: 20 | M7: E250 A/BR | N7: ='RM Details'!E144 -> 6 | O7: ='RM Details'!F144 -> 12.841972 | R7: =IF(P7>O7,P7,IF(P7<O7,O7)) -> 12.841972 | S7: 90 | T7: =S7*R7 -> 1155.7775
A8: GROSS WT. (KG) | C8: =R6 -> 8.4330101 | D8: =R7 -> 12.841972 | E8: =R8 -> 77.04 | F8: =R9 -> 2.67 | G8: =SUM(C8:F8) -> 100.98498 | J8: 3 | K8: Plate | L8: 120x80x 5thk 120x60x 5thk | M8: YST 310 | N8: ='RM Details'!E145 -> 54.73 | O8: ='RM Details'!F145 -> 60.203 | P8: =12.84*6 -> 77.04 | R8: =IF(P8>O8,P8,IF(P8<O8,O8)) -> 77.04 | S8: 110 | T8: =S8*R8 -> 8474.4
A9: NET WT (KG) | C9: =N6 -> 4.4 | D9: =N7 -> 6 | E9: =N8 -> 54.73 | F9: =N9 -> 0.4 | G9: =SUM(C9:F9) -> 65.53 | J9: 4 | K9: Plate | L9: Dia 12 | M9: E250 A/BR | N9: ='RM Details'!E146 -> 0.4 | O9: ='RM Details'!F146 -> 2.509364 | P9: =0.89*3 -> 2.67 | R9: =IF(P9>O9,P9,IF(P9<O9,O9)) -> 2.67 | S9: 110 | T9: =S9*R9 -> 293.7
A10: SCRAP (KG) | C10: =(C8-C9)*80% -> 3.2264081 | D10: =(D8-D9)*80% -> 5.4735776 | E10: =(E8-E9)*80% -> 17.848 | F10: =(F8-F9)*80% -> 1.816 | G10: =(G8-G9)/G9 -> 0.54104963 | L10: Total | N10: =SUM(N6:N9) -> 65.53 | O10: =SUM(O6:O9) -> 83.987346 | R10: =SUM(R6:R9) -> 100.98498 | S10: =T10/R10 -> 105.78651 | T10: =SUM(T6:T9) -> 10682.848
A11: RM RATE (RS/KG) | C11: 90 | D11: 90 | E11: 200 | F11: 110 | G11: =SUMPRODUCT(B11:F11,B8:F8) -> 17616.448
A12: SCRAP RATE (RS/KG) | C12: 30 | D12: 30 | E12: 30 | F12: 30
A13: NET RM COST (RS) | C13: =(C8*C11)-(C10*C12) -> 662.17867 | D13: =(D8*D11)-(D10*D12) -> 991.57015 | E13: =(E8*E11)-(E10*E12) -> 14872.56 | F13: =(F8*F11)-(F10*F12) -> 239.22 | G13: =SUM(B13:F13) -> 16765.529
A14: TOTAL (RS) | B14: =SUM(B13:F13) -> 16765.529 | G14: =G13/G8 -> 166.02002
A15: BOP COST
A16: BOP COST (RS)
A17: TOTAL BOP | F17: =SUM(F16:F16) -> 0
A18: TOTAL OF RM + BOP (RS) | F18: =B14+F17 -> 16765.529
A19: PROCESS COST
A20: SPEC | B20: QTY | C20: RATE | F20: TOTAL COST
A21: LASER /PLASMA/PIPE - Cutting (Min.) | B21: ='BOM R2D CatWalk'!X162 -> 22.320642 | C21: 35 | F21: =B21*C21 -> 781.22248 | H21: =F21/$G$9 -> 11.921601
A22: Machining (Hrs) | B22: ='BOM R2D CatWalk'!AB162/60 -> 0.5 | C22: 1000 | F22: =B22*C22 -> 500 | H22: =F22/$G$9 -> 7.6300931
A23: BENDING BY CNC BENDING (STROKE) | B23: ='BOM R2D CatWalk'!Z162 -> 4 | C23: 50 | F23: =B23*C23 -> 200 | H23: =F23/$G$9 -> 3.0520372
A24: MIG WELDING (MTR.) | B24: ='BOM R2D CatWalk'!AF162 -> 5.6616 | C24: 250 | F24: =B24*C24 -> 1415.4 | H24: =F24/$G$9 -> 21.599268
A25: GRINDING/BUFFING & FINISHING (hrs) | B25: =B24/12 -> 0.4718 | C25: 250 | F25: =B25*C25 -> 117.95 | H25: =F25/$G$9 -> 1.799939
A26: INSPECTION & TESTING (HRS) | B26: =G9/95 -> 0.68978947 | C26: 1200 | F26: =B26*C26 -> 827.74737 | H26: =F26/$G$9 -> 12.631579
A27: STRESS RELIEVING | C27: 250 | F27: =B27*C27 -> 0 | G27: As Actual, If required | H27: =F27/$G$9 -> 0
A28: Shot Blasting | C28: 5 | F28: =C28*G9 -> 327.65 | H28: =F28/$G$9 -> 5
A29: Hot Dip Galvanization | B29: 0 | C29: 50 | F29: =B29*C29 -> 0 | H29: =F29/$G$9 -> 0
A30: PAINTING (including material & Labor) | B30: ='BOM R2D CatWalk'!AI162 -> 2.2032753 | C30: 1250 | F30: =B30*C30 -> 2754.0941 | G30: No paint Detail Found | H30: =F30/$G$9 -> 42.027988
A31: Stamping Cost (HRS) | B31: =15/60 -> 0.25 | C31: 250 | F31: =B31*C31 -> 62.5 | H31: =F31/$G$9 -> 0.95376164
A32: FE cost | C32: 4.5 | F32: =C32*G9 -> 294.885 | H32: =F32/$G$9 -> 4.5
A33: TOTAL PROCESS COST OF PC | F33: =SUM(F21:F32) -> 7281.4489 | H33: =F33/$G$9 -> 111.11627
A34: TOTAL RM+BOP+PC | F34: =F18+F33 -> 24046.978
A35: OH + Contingency | D35: 0.1 | F35: =F34*D35 -> 2404.6978 | H35: =F35/$G$9 -> 36.696136
A36: Total Product Cost Without Profit | F36: =SUM(F34:F35) -> 26451.676 | H36: =F36/G9 -> 403.65749 | I36: =F36/G8 -> 261.93673
G39: Min.
A40: NOTES:- | F40: OTHER COST | G40: Min.
A41: No BOP found in the Drawing Details
A42: Stress relieveing NOT FOUND ON PRINTS, IF REQUIRED | F42: As Actual
A45: NRC COST BREAKUP
A46: Fixture Details | B46: Approx Wt /Days | C46: Rate | D46: Cost
A47: Tacking Fixture main Frame | B47: =B4*0.5 -> 34.5 | C47: 100 | D47: =B47*C47 -> 3450
A48: Testing Templates /Guided Rod | B48: =B4*0.25 -> 17.25 | C48: 200 | D48: =B48*C48 -> 3450
A49: FE COST | B49: =SUM(B47:B48) -> 51.75 | C49: 4.5 | D49: =B49*C49 -> 232.875
A50: SUB TOTAL | D50: =SUM(D47:D49) -> 7132.875
A51: Development and Engg | B51: 2 | C51: =75000/30 -> 2500 | D51: =B51*C51 -> 5000
A52: OH + Contingency | C52: 0.0255 | D52: =(D50+D51)*C52 -> 309.38831
A53: Total Cost | D53: =SUM(D50:D52) -> 12442.263

Sheet Item-10_AT30144
A1: COSTING SHEET
A2: PRODUCT NAME:- | B2: ='BOM R2D CatWalk'!I145 -> WELDMENT, 30 FT LIFT ARM, PC4100 | D2: RFQ Ref.
A3: ITEM DRG NO | B3: ='BOM R2D CatWalk'!G145 -> AY30144 | D3: Total Quantity | E3: ='BOM R2D CatWalk'!K145 -> 1
A4: Total Net WT as per Drawing | B4: ='BOM R2D CatWalk'!N145 -> 1095 | J4: Assy No | Q4: ='RM Details'!H123 -> AY30144
A5: COSTBREAKUP OF COMPONENT (QTY-01 No.) | J5: S.No | K5: Type | L5: Size (mm) | M5: Material | N5: Sum of Total Weight (Kg) | O5: Sum of Gross Wt (kg) | P5: MOQ Weight | Q5: Remarks | R5: Cal. Weight | S5: Rate/Kg | T5: Cost
A6: RAW MATERIAL COST | J6: 1 | K6: Plate | L6: 6 | M6: E250 A/BR | N6: ='RM Details'!E125 -> 1.173732 | O6: ='RM Details'!F125 -> 1.2911052 | R6: =IF(P6>O6,P6,IF(P6<O6,O6)) -> 1.2911052 | S6: 100 | T6: =S6*R6 -> 129.11052
A7: SPEC | B7: IS 2062: E250 A/BR | C7: IS 2062: E350 A/BR | D7: YST 310 | E7: ASTM A106 GR.B | F7: BROWNING SCS-2 | J7: 5 | K7: Pipe | L7: 25 | M7: E250 A/BR | N7: ='RM Details'!E126 -> 104 | O7: ='RM Details'!F126 -> 154.3938 | R7: =IF(P7>O7,P7,IF(P7<O7,O7)) -> 154.3938 | S7: 90 | T7: =S7*R7 -> 13895.442
A8: GROSS WT. (KG) | B8: =R6+R7 -> 155.68491 | C8: =R8+R9+R10 -> 149.76233 | D8: =R11+R12 -> 935.6867 | E8: =R13 -> 110.8866 | F8: =R14 -> 35.61 | G8: =SUM(C8:F8) -> 1231.9456 | J8: 2 | K8: Plate | L8: 10 | M8: E350 A/BR | N8: ='RM Details'!E127 -> 85.73485 | O8: ='RM Details'!F127 -> 138.76549 | R8: =IF(P8>O8,P8,IF(P8<O8,O8)) -> 138.76549 | S8: 90 | T8: =S8*R8 -> 12488.894
A9: NET WT (KG) | B9: =N6+N7 -> 105.17373 | C9: =N8+N9+N10 -> 90.64205 | D9: =N11+N12 -> 850.62427 | E9: =N13 -> 100.806 | F9: =N14 -> 2.4 | G9: =SUM(C9:F9) -> 1044.4723 | J9: 3 | K9: Plate | L9: 12 | M9: E350 A/BR | N9: ='RM Details'!E128 -> 4 | O9: ='RM Details'!F128 -> 4.787244 | R9: =IF(P9>O9,P9,IF(P9<O9,O9)) -> 4.787244 | S9: 100 | T9: =S9*R9 -> 478.7244
A10: SCRAP (KG) | B10: =(B8-B9)*80% -> 40.408939 | C10: =(C8-C9)*80% -> 47.296225 | D10: =(D8-D9)*80% -> 68.049942 | E10: =(E8-E9)*80% -> 8.06448 | F10: =(F8-F9)*80% -> 26.568 | G10: =(G8-G9)/G9 -> 0.17949093 | J10: 4 | K10: Plate | L10: 20 | M10: E350 A/BR | N10: ='RM Details'!E129 -> 0.9072 | O10: ='RM Details'!F129 -> 6.2096012 | R10: =IF(P10>O10,P10,IF(P10<O10,O10)) -> 6.2096012 | S10: 100 | T10: =S10*R10 -> 620.96012
A11: RM RATE (RS/KG) | B11: 90 | C11: 90 | D11: 200 | E11: 130 | F11: 150 | G11: =SUMPRODUCT(B11:F11,B8:F8) -> 234384.35 | J11: 6 | K11: Rec Tube | L11: 150 X 100 X 12thk 150x100x 8thk | M11: YST 310 | N11: ='RM Details'!E130 -> 739.35912 | O11: ='RM Details'!F130 -> 813.29503 | P11: =28.1*6 -> 168.6 | Q11: Apollo | R11: =IF(P11>O11,P11,IF(P11<O11,O11)) -> 813.29503 | S11: 110 | T11: =S11*R11 -> 89462.454
A12: SCRAP RATE (RS/KG) | B12: 30 | C12: 30 | D12: 30 | E12: 30 | F12: 30 | J12: 7 | K12: Rec Tube | L12: 150x80x 10thk 150x100x 8thk | M12: YST 310 | N12: ='RM Details'!E131 -> 111.26515 | O12: ='RM Details'!F131 -> 122.39167 | P12: =28.1*6 -> 168.6 | Q12: Apollo | R12: =O12 -> 122.39167 | S12: 110 | T12: =S12*R12 -> 13463.083
A13: NET RM COST (RS) | B13: =(B8*B11)-(B10*B12) -> 12799.373 | C13: =(C8*C11)-(C10*C12) -> 12059.723 | D13: =(D8*D11)-(D10*D12) -> 185095.84 | E13: =(E8*E11)-(E10*E12) -> 14173.324 | F13: =(F8*F11)-(F10*F12) -> 4544.46 | G13: =SUM(B13:F13) -> 228672.72 | J13: 8 | K13: Pipe | L13: Dia 33.4x 6.35 | M13: ASTM A106 GR.B | N13: ='RM Details'!E132 -> 100.806 | O13: ='RM Details'!F132 -> 110.8866 | P13: =4.24*6 -> 25.44 | Q13: Yash | R13: =IF(P13<O13,O13,IF(P13>O13,P13)) -> 110.8866 | S13: 130 | T13: =S13*R13 -> 14415.258
A14: TOTAL (RS) | B14: =SUM(B13:F13) -> 228672.72 | G14: =G13/G8 -> 185.61917 | J14: 9 | K14: Rod | L14: Dia 76 | M14: BROWNING SCS-2 | N14: ='RM Details'!E133 -> 2.4 | O14: ='RM Details'!F133 -> 2.64 | P14: =35.61*1 -> 35.61 | R14: =IF(P14<O14,O14,IF(P14>O14,P14)) -> 35.61 | S14: 250 | T14: =S14*R14 -> 8902.5
A15: BOP COST | L15: Total | N15: =SUM(N6:N14) -> 1149.6461 | O15: =SUM(O6:O14) -> 1354.6605 | R15: =SUM(R6:R14) -> 1387.6305 | S15: =T15/R15 -> 110.87708 | T15: =SUM(T6:T14) -> 153856.43
A16: BOP COST (RS)
A17: TOTAL BOP | F17: =SUM(F16:F16) -> 0
A18: TOTAL OF RM + BOP (RS) | F18: =B14+F17 -> 228672.72
A19: PROCESS COST
A20: SPEC | B20: QTY | C20: RATE | F20: TOTAL COST
A21: LASER /PLASMA/PIPE - Cutting (Min.) | B21: ='BOM R2D CatWalk'!X145 -> 85.7114 | C21: 35 | F21: =B21*C21 -> 2999.899 | H21: =F21/$G$9 -> 2.8721671
A22: Machining (Hrs) | B22: ='BOM R2D CatWalk'!AB145/60 -> 4.1666667 | C22: 1000 | F22: =B22*C22 -> 4166.6667 | H22: =F22/$G$9 -> 3.9892552
A23: BENDING BY CNC BENDING (STROKE) | B23: ='BOM R2D CatWalk'!Z145 -> 0 | C23: 100 | F23: =B23*C23 -> 0 | H23: =F23/$G$9 -> 0
A24: MIG WELDING (MTR.) | B24: 132 | C24: 250 | F24: =B24*C24 -> 33000 | H24: =F24/$G$9 -> 31.594901
A25: GRINDING/BUFFING & FINISHING (hrs) | B25: =B24/12 -> 11 | C25: 250 | F25: =B25*C25 -> 2750 | H25: =F25/$G$9 -> 2.6329085
A26: INSPECTION & TESTING (HRS) | B26: =G9/95 -> 10.994445 | C26: 1200 | F26: =B26*C26 -> 13193.335 | H26: =F26/$G$9 -> 12.631579
A27: STRESS RELIEVING | C27: 250 | F27: =B27*C27 -> 0 | G27: As Actual, If required | H27: =F27/$G$9 -> 0
A28: Shot Blasting | C28: 5 | F28: =C28*G9 -> 5222.3616 | H28: =F28/$G$9 -> 5
A29: Hot Dip Galvanization | B29: 0 | C29: 50 | F29: =B29*C29 -> 0 | H29: =F29/$G$9 -> 0
A30: PAINTING (including material & Labor) | B30: ='BOM R2D CatWalk'!AI145 -> 21.38217 | C30: 1250 | F30: =B30*C30 -> 26727.712 | G30: No paint Detail Found | H30: =F30/$G$9 -> 25.58968
A31: Stamping Cost (HRS)/Straightning | B31: 4 | C31: 250 | F31: =B31*C31 -> 1000 | H31: =F31/$G$9 -> 0.95742126
A32: FE cost | C32: 4.5 | F32: =C32*G9 -> 4700.1254 | H32: =F32/$G$9 -> 4.5
A33: TOTAL PROCESS COST OF PC | F33: =SUM(F21:F32) -> 93760.099 | H33: =F33/$G$9 -> 89.767912
A34: TOTAL RM+BOP+PC | F34: =F18+F33 -> 322432.82
A35: OH + Contingency | D35: 0.1 | F35: =F34*D35 -> 32243.282 | H35: =F35/$G$9 -> 30.870404
A36: Total Product Cost Without Profit | F36: =SUM(F34:F35) -> 354676.1 | H36: =F36/G9 -> 339.57444 | I36: =F36/G8 -> 287.89915
G39: Min.
A40: NOTES:- Joint need to make while welding | F40: OTHER COST | G40: Min.
A41: No BOP found in the Drawing Details
A42: Stress relieveing NOT FOUND ON PRINTS, IF REQUIRED | F42: As Actual
A45: NRC COST BREAKUP
A46: Fixture Details | B46: Approx Wt /Days | C46: Rate | D46: Cost
A47: Tacking Fixture main Frame | B47: =B4*1.6 -> 1752 | C47: 100 | D47: =B47*C47 -> 175200
A48: Testing Templates /Guided Rod | B48: =B4*0.25 -> 273.75 | C48: 200 | D48: =B48*C48 -> 54750
A49: FE COST | B49: =SUM(B47:B48) -> 2025.75 | C49: 4.5 | D49: =B49*C49 -> 9115.875
A50: SUB TOTAL | D50: =SUM(D47:D49) -> 239065.88
A51: Development and Engg | B51: 8 | C51: =75000/30 -> 2500 | D51: =B51*C51 -> 20000
A52: OH + Contingency | C52: 0.0255 | D52: =(D50+D51)*C52 -> 6606.1798
A53: Total Cost | D53: =SUM(D50:D52) -> 265672.05

Sheet Item-9_AT30134
A1: COSTING SHEET
A2: PRODUCT NAME:- | B2: ='BOM R2D CatWalk'!I128 -> WELDMENT, RAMP, SHEAVE SUB B, PC4100 | D2: RFQ Ref.
A3: ITEM DRG NO | B3: ='BOM R2D CatWalk'!G128 -> AY30134 | D3: Total Quantity | E3: ='BOM R2D CatWalk'!K128 -> 1
A4: Total Net WT as per Drawing | B4: ='BOM R2D CatWalk'!N128 -> 363 | I4: Assy No | P4: ='RM Details'!H108 -> AY30134
A5: COSTBREAKUP OF COMPONENT (QTY-01 No.) | I5: S.No | J5: Type | K5: Size (mm) | L5: Material | M5: Sum of Total Weight (Kg) | N5: Sum of Gross Wt (kg) | O5: MOQ Weight | P5: Remarks | Q5: Cal. Weight | R5: Rate/Kg | S5: Cost
A6: RAW MATERIAL COST | I6: 1 | J6: Plate | K6: 12 | L6: E350 A/BR | M6: ='RM Details'!E110 -> 96.257444 | N6: ='RM Details'!F110 -> 153.65012 | Q6: =IF(O6>N6,O6,IF(O6<N6,N6)) -> 153.65012 | R6: 90 | S6: =R6*Q6 -> 13828.511
A7: SPEC | C7: IS 2062: E350 A/BR | D7: IS 2062: E250 A/BR | E7: ASTM A106 GR.B | I7: 2 | J7: Plate | K7: 20 | L7: E350 A/BR | M7: ='RM Details'!E111 -> 168.89231 | N7: ='RM Details'!F111 -> 387.04488 | Q7: =IF(O7>N7,O7,IF(O7<N7,N7)) -> 387.04488 | R7: 90 | S7: =R7*Q7 -> 34834.039
A8: GROSS WT. (KG) | C8: =Q6+Q7 -> 540.695 | D8: =Q8+Q9 -> 71.611782 | E8: =Q10+Q11 -> 288 | F8: =SUM(C8:E8) -> 900.30678 | I8: 3 | J8: Plate | K8: 20 | L8: E250 A/BR | M8: ='RM Details'!E112 -> 42 | N8: ='RM Details'!F112 -> 63.824739 | Q8: =IF(O8>N8,O8,IF(O8<N8,N8)) -> 63.824739 | R8: 90 | S8: =R8*Q8 -> 5744.2265
A9: NET WT (KG) | C9: =M6+M7 -> 265.14975 | D9: =M8+M9 -> 46.6 | E9: =M10+M11 -> 58.676352 | F9: =SUM(C9:E9) -> 370.42611 | I9: 4 | J9: Plate | K9: 25 | L9: E250 A/BR | M9: ='RM Details'!E113 -> 4.6 | N9: ='RM Details'!F113 -> 7.787043 | Q9: =IF(O9>N9,O9,IF(O9<N9,N9)) -> 7.787043 | R9: 90 | S9: =R9*Q9 -> 700.83387
A10: SCRAP (KG) | C10: =(C8-C9)*80% -> 220.43619 | D10: =(D8-D9)*80% -> 20.009426 | E10: =(E8-E9)*80% -> 183.45892 | F10: =(F8-F9)/F9 -> 1.4304626 | I10: 5 | J10: Pipe | K10: Dia 168.28 x 10.97thk | L10: ASTM A106 GR.B | M10: ='RM Details'!E114 -> 58.4 | N10: ='RM Details'!F114 -> 64.24 | O10: =42.56*6 -> 255.36 | Q10: =IF(O10>N10,O10,IF(O10<N10,N10)) -> 255.36 | R10: 110 | S10: =R10*Q10 -> 28089.6
A11: RM RATE (RS/KG) | C11: 90 | D11: 90 | E11: 110 | F11: =SUMPRODUCT(B11:E11,B8:E8) -> 86787.61 | I11: 6 | J11: Pipe | K11: Dia 60.3 x 3.91 thk | L11: ASTM A106 GR.B | M11: ='RM Details'!E115 -> 0.276352 | N11: ='RM Details'!F115 -> 0.3039872 | O11: =5.44*6 -> 32.64 | Q11: =IF(O11>N11,O11,IF(O11<N11,N11)) -> 32.64 | R11: 110 | S11: =R11*Q11 -> 3590.4
A12: SCRAP RATE (RS/KG) | C12: 30 | D12: 30 | E12: 30 | K12: Total | M12: =SUM(M6:M11) -> 370.42611 | N12: =SUM(N6:N11) -> 676.85077 | Q12: =SUM(Q6:Q11) -> 900.30678 | R12: =S12/Q12 -> 96.397819 | S12: =SUM(S6:S11) -> 86787.61
A13: NET RM COST (RS) | C13: =(C8*C11)-(C10*C12) -> 42049.464 | D13: =(D8*D11)-(D10*D12) -> 5844.7776 | E13: =(E8*E11)-(E10*E12) -> 26176.232 | F13: =SUM(B13:E13) -> 74070.474
A14: TOTAL (RS) | B14: =SUM(B13:E13) -> 74070.474 | F14: =F13/F8 -> 82.272483
A15: BOP COST
A16: BOP COST (RS)
A17: TOTAL BOP | E17: =SUM(E16:E16) -> 0
A18: TOTAL OF RM + BOP (RS) | E18: =B14+E17 -> 74070.474
A19: PROCESS COST
A20: SPEC | B20: QTY | C20: RATE | E20: TOTAL COST
A21: LASER /PLASMA/PIPE - Cutting (Min.) | B21: ='BOM R2D CatWalk'!X128 -> 37.583277 | C21: 35 | E21: =B21*C21 -> 1315.4147 | G21: =E21/$F$9 -> 3.5510853
A22: Machining (Hrs) | B22: ='BOM R2D CatWalk'!AB128/60 -> 3 | C22: 2000 | E22: =B22*C22 -> 6000 | G22: =E22/$F$9 -> 16.197562
A23: BENDING BY CNC BENDING (STROKE) | B23: ='BOM R2D CatWalk'!Z128 -> 0 | C23: 100 | E23: =B23*C23 -> 0 | G23: =E23/$F$9 -> 0
A24: MIG WELDING (MTR.) | B24: 45 | C24: 300 | E24: =B24*C24 -> 13500 | G24: =E24/$F$9 -> 36.444516
A25: GRINDING/BUFFING & FINISHING (hrs) | B25: =B24/12 -> 3.75 | C25: 250 | E25: =B25*C25 -> 937.5 | G25: =E25/$F$9 -> 2.5308691
A26: INSPECTION & TESTING (HRS) | B26: =F9/95 -> 3.8992222 | C26: 1200 | E26: =B26*C26 -> 4679.0666 | G26: =E26/$F$9 -> 12.631579
A27: STRESS RELIEVING | C27: 250 | E27: =B27*C27 -> 0 | F27: As Actual, If required | G27: =E27/$F$9 -> 0
A28: Shot Blasting | C28: 5 | E28: =C28*F9 -> 1852.1305 | G28: =E28/$F$9 -> 5
A29: Hot Dip Galvanization | B29: 0 | C29: 50 | E29: =B29*C29 -> 0 | G29: =E29/$F$9 -> 0
A30: PAINTING (including material & Labor) | B30: ='BOM R2D CatWalk'!AI128 -> 10.366096 | C30: 1250 | E30: =B30*C30 -> 12957.62 | F30: No paint Detail Found | G30: =E30/$F$9 -> 34.980309
A31: Stamping Cost (HRS) | B31: =15/60 -> 0.25 | C31: 250 | E31: =B31*C31 -> 62.5 | G31: =E31/$F$9 -> 0.16872461
A32: FE cost | C32: 4.5 | E32: =C32*F9 -> 1666.9175 | G32: =E32/$F$9 -> 4.5
A33: TOTAL PROCESS COST OF PC | E33: =SUM(E21:E32) -> 42971.149 | G33: =E33/$F$9 -> 116.00465
A34: TOTAL RM+BOP+PC | E34: =E18+E33 -> 117041.62
A35: OH + Contingency | D35: 0.1 | E35: =E34*D35 -> 11704.162 | G35: =E35/$F$9 -> 31.596483
A36: Total Product Cost Without Profit | E36: =SUM(E34:E35) -> 128745.79 | G36: =E36/F9 -> 347.56132 | H36: =E36/F8 -> 143.00213
F39: Min.
A40: NOTES:- | E40: OTHER COST | F40: Min.
A41: No BOP found in the Drawing Details
A42: Stress relieveing NOT FOUND ON PRINTS, IF REQUIRED | E42: As Actual
A45: NRC COST BREAKUP
A46: Fixture Details | B46: Approx Wt /Days | C46: Rate | D46: Cost
A47: Tacking Fixture main Frame | B47: =B4*1 -> 363 | C47: 100 | D47: =B47*C47 -> 36300
A48: Testing Templates /Guided Rod | B48: =B4*0.25 -> 90.75 | C48: 200 | D48: =B48*C48 -> 18150
A49: FE COST | B49: =SUM(B47:B48) -> 453.75 | C49: 4.5 | D49: =B49*C49 -> 2041.875
A50: SUB TOTAL | D50: =SUM(D47:D49) -> 56491.875
A51: Development and Engg | B51: 4 | C51: =75000/30 -> 2500 | D51: =B51*C51 -> 10000
A52: OH + Contingency | C52: 0.0255 | D52: =(D50+D51)*C52 -> 1695.5428
A53: Total Cost | D53: =SUM(D50:D52) -> 68187.418

Sheet Item-8_AT30133
A1: COSTING SHEET
A2: PRODUCT NAME:- | B2: ='BOM R2D CatWalk'!I119 -> WELDMENT,RAMPRAIL, PC4100 | D2: RFQ Ref.
A3: ITEM DRG NO | B3: ='BOM R2D CatWalk'!G119 -> AY30133 | D3: Total Quantity | E3: ='BOM R2D CatWalk'!K119 -> 1
A4: Total Net WT as per Drawing | B4: ='BOM R2D CatWalk'!N119 -> 113.7 | I4: Assy No | P4: ='RM Details'!H98 -> AY30133
A5: COSTBREAKUP OF COMPONENT (QTY-01 No.) | I5: S.No | J5: Type | K5: Size (mm) | L5: Material | M5: Sum of Total Weight (Kg) | N5: Sum of Gross Wt (kg) | O5: MOQ Weight | P5: Remarks | Q5: Cal. Weight | R5: Rate/Kg | S5: Cost
A6: RAW MATERIAL COST | I6: 1 | J6: Sq. Tube | K6: 50x50x 5thk | L6: YST 310 | M6: ='RM Details'!E100 -> 124.5734 | N6: ='RM Details'!F100 -> 137.03074 | O6: =6.56*6 -> 39.36 | Q6: =IF(O6>N6,O6,IF(O6<N6,N6)) -> 137.03074 | R6: 110 | S6: =R6*Q6 -> 15073.381
A7: SPEC | E7: YST 310 | K7: Total | M7: =SUM(M6:M6) -> 124.5734 | N7: =SUM(N6:N6) -> 137.03074 | Q7: =SUM(Q6:Q6) -> 137.03074 | R7: =S7/Q7 -> 110 | S7: =SUM(S6:S6) -> 15073.381
A8: GROSS WT. (KG) | E8: =Q6 -> 137.03074 | F8: =SUM(C8:E8) -> 137.03074
A9: NET WT (KG) | E9: =M6 -> 124.5734 | F9: =SUM(C9:E9) -> 124.5734
A10: SCRAP (KG) | E10: =(E8-E9)*80% -> 9.965872 | F10: =(F8-F9)/F9 -> 0.1
A11: RM RATE (RS/KG) | E11: 200 | F11: =SUMPRODUCT(B11:E11,B8:E8) -> 27406.148
A12: SCRAP RATE (RS/KG) | E12: 30
A13: NET RM COST (RS) | D13: =(D8*D11)-(D10*D12) -> 0 | E13: =(E8*E11)-(E10*E12) -> 27107.172 | F13: =SUM(B13:E13) -> 27107.172
A14: TOTAL (RS) | B14: =SUM(B13:E13) -> 27107.172 | F14: =F13/F8 -> 197.81818
A15: BOP COST
A16: BOP COST (RS)
A17: TOTAL BOP | E17: =SUM(E16:E16) -> 0
A18: TOTAL OF RM + BOP (RS) | E18: =B14+E17 -> 27107.172
A19: PROCESS COST
A20: SPEC | B20: QTY | C20: RATE | E20: TOTAL COST
A21: LASER /PLASMA/PIPE - Cutting (Min.) | B21: ='BOM R2D CatWalk'!X119 -> 54 | C21: 35 | E21: =B21*C21 -> 1890 | G21: =E21/$F$9 -> 15.171778
A22: Machining (Hrs) | B22: ='BOM R2D CatWalk'!AB119/60 -> 0.23333333 | C22: 1000 | E22: =B22*C22 -> 233.33333 | G22: =E22/$F$9 -> 1.873059
A23: BENDING BY CNC BENDING (STROKE) | B23: ='BOM R2D CatWalk'!Z119 -> 0 | C23: 100 | E23: =B23*C23 -> 0 | G23: =E23/$F$9 -> 0
A24: MIG WELDING (MTR.) | B24: ='BOM R2D CatWalk'!AF119 -> 6 | C24: 250 | E24: =B24*C24 -> 1500 | G24: =E24/$F$9 -> 12.041094
A25: GRINDING/BUFFING & FINISHING (hrs) | B25: =B24/12 -> 0.5 | C25: 250 | E25: =B25*C25 -> 125 | G25: =E25/$F$9 -> 1.0034245
A26: INSPECTION & TESTING (HRS) | B26: =F9/95 -> 1.3112989 | C26: 1200 | E26: =B26*C26 -> 1573.5587 | G26: =E26/$F$9 -> 12.631579
A27: STRESS RELIEVING | C27: 250 | E27: =B27*C27 -> 0 | F27: As Actual, If required | G27: =E27/$F$9 -> 0
A28: Shot Blasting | C28: 5 | E28: =C28*F9 -> 622.867 | G28: =E28/$F$9 -> 5
A29: Hot Dip Galvanization | B29: 0 | C29: 50 | E29: =B29*C29 -> 0 | G29: =E29/$F$9 -> 0
A30: PAINTING (including material & Labor) | B30: ='BOM R2D CatWalk'!AI119 -> 4.153915 | C30: 1250 | E30: =B30*C30 -> 5192.3937 | F30: No paint Detail Found | G30: =E30/$F$9 -> 41.6814
A31: Stamping Cost (HRS)/Straightning | B31: 4 | C31: 250 | E31: =B31*C31 -> 1000 | G31: =E31/$F$9 -> 8.0273959
A32: FE cost | C32: 4.5 | E32: =C32*F9 -> 560.5803 | G32: =E32/$F$9 -> 4.5
A33: TOTAL PROCESS COST OF PC | E33: =SUM(E21:E32) -> 12697.733 | G33: =E33/$F$9 -> 101.92973
A34: TOTAL RM+BOP+PC | E34: =E18+E33 -> 39804.905
A35: OH + Contingency | D35: 0.1 | E35: =E34*D35 -> 3980.4905 | G35: =E35/$F$9 -> 31.952973
A36: Total Product Cost Without Profit | E36: =SUM(E34:E35) -> 43785.395 | G36: =E36/F9 -> 351.4827 | H36: =E36/F8 -> 319.52973
F39: Min.
A40: NOTES:- Joint need to make while welding | E40: OTHER COST | F40: Min.
A41: No BOP found in the Drawing Details
A42: Stress relieveing NOT FOUND ON PRINTS, IF REQUIRED | E42: As Actual
A45: NRC COST BREAKUP
A46: Fixture Details | B46: Approx Wt /Days | C46: Rate | D46: Cost
A47: Tacking Fixture main Frame | C47: 100 | D47: =B47*C47 -> 0
A48: Testing Templates | C48: 100 | D48: =B48*C48 -> 0
A49: FE COST | C49: 4.5 | D49: =B49*C49 -> 0
A50: SUB TOTAL | D50: =SUM(D47:D49) -> 0
A51: Development and Engg | C51: =75000/30 -> 2500 | D51: =B51*C51 -> 0
A52: OH + Contingency | C52: 0.07 | D52: =(D50+D51)*C52 -> 0
A53: Total Cost | D53: =SUM(D50:D52) -> 0

Sheet Item-7_AT30107
A1: COSTING SHEET
A2: PRODUCT NAME:- | B2: ='BOM R2D CatWalk'!I114 -> WELDMENT,SKATE BODY, REVERSE VEE, PC4100 | D2: RFQ Ref.
A3: ITEM DRG NO | B3: ='BOM R2D CatWalk'!G114 -> AY30107 | D3: Total Quantity | E3: ='BOM R2D CatWalk'!K114 -> 1
A4: Total Net WT as per Drawing | B4: ='BOM R2D CatWalk'!N114 -> 80 | I4: Assy No | P4: ='RM Details'!H87 -> AY30107
A5: COSTBREAKUP OF COMPONENT (QTY-01 No.) | I5: S.No | J5: Type | K5: Size (mm) | L5: Material | M5: Sum of Total Weight (Kg) | N5: Sum of Gross Wt (kg) | O5: MOQ Weight | P5: Remarks | Q5: Cal. Weight | R5: Rate/Kg | S5: Cost
A6: RAW MATERIAL COST | I6: 1 | J6: Plate | K6: 10 | L6: E350 A/BR | M6: ='RM Details'!E89 -> 2 | N6: ='RM Details'!F89 -> 4.1130232 | Q6: =IF(O6>N6,O6,IF(O6<N6,N6)) -> 4.1130232 | R6: 90 | S6: =R6*Q6 -> 370.17209
A7: SPEC | D7: IS 2062 E350 A/BR | E7: IS 2062 E250 A/BR | I7: 2 | J7: Plate | K7: 20 | L7: E250 A/BR | M7: ='RM Details'!E90 -> 28 | N7: ='RM Details'!F90 -> 38.74559 | Q7: =IF(O7>N7,O7,IF(O7<N7,N7)) -> 38.74559 | R7: 90 | S7: =R7*Q7 -> 3487.1031
A8: GROSS WT. (KG) | D8: =Q6 -> 4.1130232 | E8: =Q7+Q8 -> 133.32971 | F8: =SUM(C8:E8) -> 137.44273 | I8: 3 | J8: Plate | K8: 25 | L8: E250 A/BR | M8: ='RM Details'!E91 -> 50.5 | N8: ='RM Details'!F91 -> 94.58412 | Q8: =IF(O8>N8,O8,IF(O8<N8,N8)) -> 94.58412 | R8: 90 | S8: =R8*Q8 -> 8512.5708
A9: NET WT (KG) | D9: =M6 -> 2 | E9: =M7+M8 -> 78.5 | F9: =SUM(C9:E9) -> 80.5 | K9: Total | M9: =SUM(M6:M8) -> 80.5 | N9: =SUM(N6:N8) -> 137.44273 | Q9: =SUM(Q6:Q8) -> 137.44273 | R9: =S9/Q9 -> 90 | S9: =SUM(S6:S8) -> 12369.846
A10: SCRAP (KG) | D10: =(D8-D9)*80% -> 1.6904186 | E10: =(E8-E9)*80% -> 43.863768 | F10: =(F8-F9)/F9 -> 0.70736315
A11: RM RATE (RS/KG) | D11: =R6 -> 90 | E11: =R7 -> 90 | F11: =SUMPRODUCT(B11:E11,B8:E8) -> 12369.846
A12: SCRAP RATE (RS/KG) | D12: 30 | E12: 30
A13: NET RM COST (RS) | D13: =(D8*D11)-(D10*D12) -> 319.45953 | E13: =(E8*E11)-(E10*E12) -> 10683.761 | F13: =SUM(B13:E13) -> 11003.22
A14: TOTAL (RS) | B14: =SUM(B13:E13) -> 11003.22 | F14: =F13/F8 -> 80.056763
A15: BOP COST
A16: BOP COST (RS)
A17: TOTAL BOP | E17: =SUM(E16:E16) -> 0
A18: TOTAL OF RM + BOP (RS) | E18: =B14+E17 -> 11003.22
A19: PROCESS COST
A20: SPEC | B20: QTY | C20: RATE | E20: TOTAL COST
A21: LASER /PLASMA/PIPE - Cutting (Min.) | B21: ='BOM R2D CatWalk'!X114 -> 9.3070165 | C21: 35 | E21: =B21*C21 -> 325.74558 | G21: =E21/$F$9 -> 4.0465289
A22: Machining (Hrs) | B22: 2 | C22: 750 | E22: =B22*C22 -> 1500 | G22: =E22/$F$9 -> 18.63354
A23: BENDING BY CNC BENDING (STROKE) | B23: ='BOM R2D CatWalk'!Z114 -> 0 | C23: 100 | E23: =B23*C23 -> 0 | G23: =E23/$F$9 -> 0
A24: MIG WELDING (MTR.) | B24: ='BOM R2D CatWalk'!AF114 -> 12.5712 | C24: 250 | E24: =B24*C24 -> 3142.8 | G24: =E24/$F$9 -> 39.040994
A25: GRINDING/BUFFING & FINISHING (hrs) | B25: =B24/12 -> 1.0476 | C25: 250 | E25: =B25*C25 -> 261.9 | G25: =E25/$F$9 -> 3.2534161
A26: INSPECTION & TESTING (HRS) | B26: =F9/95 -> 0.84736842 | C26: 1200 | E26: =B26*C26 -> 1016.8421 | G26: =E26/$F$9 -> 12.631579
A27: STRESS RELIEVING | C27: 250 | E27: =B27*C27 -> 0 | F27: As Actual, If required | G27: =E27/$F$9 -> 0
A28: Shot Blasting | C28: 5 | E28: =C28*F9 -> 402.5 | G28: =E28/$F$9 -> 5
A29: Hot Dip Galvanization | B29: 0 | C29: 50 | E29: =B29*C29 -> 0 | G29: =E29/$F$9 -> 0
A30: PAINTING (including material & Labor) | B30: ='BOM R2D CatWalk'!AI114 -> 1.6332921 | C30: 1250 | E30: =B30*C30 -> 2041.6151 | F30: No paint Detail Found | G30: =E30/$F$9 -> 25.361679
A31: Stamping Cost (HRS) | B31: =15/60 -> 0.25 | C31: 250 | E31: =B31*C31 -> 62.5 | G31: =E31/$F$9 -> 0.77639752
A32: FE cost | C32: 4.5 | E32: =C32*F9 -> 362.25 | G32: =E32/$F$9 -> 4.5
A33: TOTAL PROCESS COST OF PC | E33: =SUM(E21:E32) -> 9116.1528 | G33: =E33/$F$9 -> 113.24413
A34: TOTAL RM+BOP+PC | E34: =E18+E33 -> 20119.373
A35: OH + Contingency | D35: 0.1 | E35: =E34*D35 -> 2011.9373 | G35: =E35/$F$9 -> 24.99301
A36: Total Product Cost Without Profit | E36: =SUM(E34:E35) -> 22131.311 | G36: =E36/F9 -> 274.92311 | I36: =E36/F8 -> 161.02205
F39: Min.
A40: NOTES:- | E40: OTHER COST | F40: Min.
A41: No BOP found in the Drawing Details
A42: Stress relieveing NOT FOUND ON PRINTS, IF REQUIRED | E42: As Actual
A45: NRC COST BREAKUP
A46: Fixture Details | B46: Approx Wt /Days | C46: Rate | D46: Cost
A47: Tacking Fixture main Frame | B47: =B4*1.5 -> 120 | C47: 100 | D47: =B47*C47 -> 12000
A48: Testing Templates | B48: =B4*0.2 -> 16 | C48: 100 | D48: =B48*C48 -> 1600
A49: FE COST | B49: =SUM(B47:B48) -> 136 | C49: 4.5 | D49: =B49*C49 -> 612
A50: SUB TOTAL | D50: =SUM(D47:D49) -> 14212
A51: Development and Engg | B51: 2 | C51: =75000/30 -> 2500 | D51: =B51*C51 -> 5000
A52: OH + Contingency | C52: 0.0255 | D52: =(D50+D51)*C52 -> 489.906
A53: Total Cost | D53: =SUM(D50:D52) -> 19701.906

Sheet Item-6_AY30084
A1: COSTING SHEET
A2: PRODUCT NAME:- | B2: ='BOM R2D CatWalk'!I109 -> HAND RAIL,WELDMENT,42" CATWALK, PC4100 | D2: RFQ Ref.
A3: ITEM DRG NO | B3: ='BOM R2D CatWalk'!G109 -> AY30084 | D3: Total Quantity | E3: ='BOM R2D CatWalk'!K109 -> 4
A4: Total Net WT as per Drawing | B4: ='BOM R2D CatWalk'!N109 -> 76 | I4: Assy No | P4: ='RM Details'!H77 -> AY30084
A5: COSTBREAKUP OF COMPONENT (QTY-01 No.) | I5: S.No | J5: Type | K5: Size (mm) | L5: Material | M5: Sum of Total Weight (Kg) | N5: Sum of Gross Wt (kg) | O5: MOQ Weight | P5: Remarks | Q5: Cal. Weight | R5: Rate/Kg | S5: Cost
A6: RAW MATERIAL COST | I6: 1 | J6: Sq. Tube | K6: 40x40x 5thk | L6: YST 310 | M6: ='RM Details'!E79 -> 88.946 | N6: ='RM Details'!F79 -> 97.8406 | O6: =5.5*6 -> 33 | Q6: =IF(O6>N6,O6,IF(O6<N6,N6)) -> 97.8406 | R6: 110 | S6: =R6*Q6 -> 10762.466
A7: SPEC | D7: YST 310 | K7: Total | M7: =SUM(M6:M6) -> 88.946 | N7: =SUM(N6:N6) -> 97.8406 | Q7: =SUM(Q6:Q6) -> 97.8406 | R7: =S7/Q7 -> 110 | S7: =SUM(S6:S6) -> 10762.466
A8: GROSS WT. (KG) | D8: =Q6 -> 97.8406 | F8: =SUM(C8:E8) -> 97.8406
A9: NET WT (KG) | D9: =M6 -> 88.946 | F9: =SUM(C9:E9) -> 88.946
A10: SCRAP (KG) | D10: =(D8-D9)*80% -> 7.11568 | F10: =(F8-F9)/F9 -> 0.1
A11: RM RATE (RS/KG) | D11: 200 | F11: =SUMPRODUCT(B11:E11,B8:E8) -> 19568.12
A12: SCRAP RATE (RS/KG) | D12: 30
A13: NET RM COST (RS) | D13: =(D8*D11)-(D10*D12) -> 19354.65 | F13: =SUM(B13:E13) -> 19354.65
A14: TOTAL (RS) | B14: =SUM(B13:E13) -> 19354.65 | F14: =F13/F8 -> 197.81818
A15: BOP COST
A16: BOP COST (RS)
A17: TOTAL BOP | E17: =SUM(E16:E16) -> 0
A18: TOTAL OF RM + BOP (RS) | E18: =B14+E17 -> 19354.65
A19: PROCESS COST
A20: SPEC | B20: QTY | C20: RATE | E20: TOTAL COST
A21: LASER /PLASMA/PIPE - Cutting (Min.) | B21: ='BOM R2D CatWalk'!X109 -> 16 | C21: 35 | E21: =B21*C21 -> 560 | G21: =E21/$F$9 -> 6.2959548
A22: Machining (Hrs) | B22: ='BOM R2D CatWalk'!AB109/60 -> 0.66666667 | C22: 550 | E22: =B22*C22 -> 366.66667 | G22: =E22/$F$9 -> 4.1223514
A23: BENDING BY CNC BENDING (STROKE) | B23: ='BOM R2D CatWalk'!Z109 -> 0 | C23: 100 | E23: =B23*C23 -> 0 | G23: =E23/$F$9 -> 0
A24: MIG WELDING (MTR.) | B24: ='BOM R2D CatWalk'!AF109 -> 3.456 | C24: 250 | E24: =B24*C24 -> 864 | G24: =E24/$F$9 -> 9.7137589
A25: GRINDING/BUFFING & FINISHING (hrs) | B25: =B24/12 -> 0.288 | C25: 250 | E25: =B25*C25 -> 72 | G25: =E25/$F$9 -> 0.80947991
A26: INSPECTION & TESTING (HRS) | B26: =F9/95 -> 0.93627368 | C26: 1200 | E26: =B26*C26 -> 1123.5284 | G26: =E26/$F$9 -> 12.631579
A27: STRESS RELIEVING | C27: 250 | E27: =B27*C27 -> 0 | F27: As Actual, If required | G27: =E27/$F$9 -> 0
A28: Shot Blasting | C28: 5 | E28: =C28*F9 -> 444.73 | G28: =E28/$F$9 -> 5
A29: Hot Dip Galvanization | B29: 0 | C29: 50 | E29: =B29*C29 -> 0 | G29: =E29/$F$9 -> 0
A30: PAINTING (including material & Labor) | B30: ='BOM R2D CatWalk'!AI109 -> 3.4219952 | C30: 1250 | E30: =B30*C30 -> 4277.494 | F30: No paint Detail Found | G30: =E30/$F$9 -> 48.090909
A31: Stamping Cost (HRS) | B31: =15/60 -> 0.25 | C31: 250 | E31: =B31*C31 -> 62.5 | G31: =E31/$F$9 -> 0.70267353
A32: FE cost | C32: 5 | E32: =C32*F9 -> 444.73 | G32: =E32/$F$9 -> 5
A33: TOTAL PROCESS COST OF PC | E33: =SUM(E21:E32) -> 8215.6491 | G33: =E33/$F$9 -> 92.366707
A34: TOTAL RM+BOP+PC | E34: =E18+E33 -> 27570.299
A35: OH + Contingency | D35: 0.1 | E35: =E34*D35 -> 2757.0299 | G35: =E35/$F$9 -> 30.996671
A36: Total Product Cost Without Profit | E36: =SUM(E34:E35) -> 30327.329 | G36: =E36/F9 -> 340.96338 | I36: =E36/F8 -> 309.96671
F39: Min.
A40: NOTES:- | E40: OTHER COST | F40: Min.
A41: No BOP found in the Drawing Details
A42: Stress relieveing NOT FOUND ON PRINTS, IF REQUIRED | E42: As Actual
A45: NRC COST BREAKUP
A46: Fixture Details | B46: Approx Wt /Days | C46: Rate | D46: Cost
A47: Tacking Fixture main Frame | C47: 100 | D47: =B47*C47 -> 0
A48: Testing Templates | C48: 100 | D48: =B48*C48 -> 0
A49: FE COST | C49: 4.5 | D49: =B49*C49 -> 0
A50: SUB TOTAL | D50: =SUM(D47:D49) -> 0
A51: Development and Engg | C51: =75000/30 -> 2500 | D51: =B51*C51 -> 0
A52: OH + Contingency | C52: 0.07 | D52: =(D50+D51)*C52 -> 0
A53: Total Cost | D53: =SUM(D50:D52) -> 0

Sheet Item-5_AY30062
A1: COSTING SHEET
A2: PRODUCT NAME:- | B2: ='BOM R2D CatWalk'!I105 -> WELDMENT, SAFETY BAR, PC4100 | D2: RFQ Ref.
A3: ITEM DRG NO | B3: ='BOM R2D CatWalk'!G105 -> AY30062 | D3: Total Quantity | E3: ='BOM R2D CatWalk'!K105 -> 1
A4: Total Net WT as per Drawing | B4: ='BOM R2D CatWalk'!N105 -> 21 | I4: Assy No | P4: ='RM Details'!H65 -> AY30062
A5: COSTBREAKUP OF COMPONENT (QTY-01 No.) | I5: S.No | J5: Type | K5: Size (mm) | L5: Material | M5: Sum of Total Weight (Kg) | N5: Sum of Gross Wt (kg) | O5: MOQ Weight | P5: Remarks | Q5: Cal. Weight | R5: Rate/Kg | S5: Cost
A6: RAW MATERIAL COST | I6: 1 | J6: Plate | K6: 10 | L6: E350 A/BR | M6: ='RM Details'!E67 -> 2.4 | N6: ='RM Details'!F67 -> 3.38492 | O6: 0 | Q6: =IF(O6>N6,O6,IF(O6<N6,N6)) -> 3.38492 | R6: 90 | S6: =R6*Q6 -> 304.6428
A7: SPEC | C7: IS 2062 E350 A/BR | D7: =L7 -> ASTM A106 GR.B | E7: Rod IS 2062 E250 A/BR | I7: 2 | J7: Pipe | K7: Dia 101.6 x 8.08 thk | L7: ASTM A106 GR.B | M7: ='RM Details'!E68 -> 17.9876 | N7: ='RM Details'!F68 -> 19.78636 | O7: =18.64*6/2 -> 55.92 | Q7: =IF(O7>N7,O7,IF(O7<N7,N7)) -> 55.92 | R7: 110 | S7: =R7*Q7 -> 6151.2
A8: GROSS WT. (KG) | C8: =Q6 -> 3.38492 | D8: =Q7 -> 55.92 | E8: =Q8 -> 2.67 | F8: =SUM(C8:E8) -> 61.97492 | I8: 3 | J8: Rod | K8: Dia 12 | L8: E250 A/BR | M8: ='RM Details'!E69 -> 0.3 | N8: ='RM Details'!F69 -> 2.011009 | O8: =0.89*3 -> 2.67 | Q8: =IF(O8>N8,O8,IF(O8<N8,N8)) -> 2.67 | R8: 110 | S8: =R8*Q8 -> 293.7
A9: NET WT (KG) | C9: =M6 -> 2.4 | D9: =M7 -> 17.9876 | E9: =M8 -> 0.3 | F9: =SUM(C9:E9) -> 20.6876 | K9: Total | M9: =SUM(M6:M8) -> 20.6876 | N9: =SUM(N6:N8) -> 25.182289 | Q9: =SUM(Q6:Q8) -> 61.97492 | R9: =S9/Q9 -> 108.90765 | S9: =SUM(S6:S8) -> 6749.5428
A10: SCRAP (KG) | C10: =(C8-C9)*80% -> 0.787936 | D10: =(D8-D9)*80% -> 30.34592 | E10: =(E8-E9)*80% -> 1.896 | F10: =(F8-F9)/F9 -> 1.995752
A11: RM RATE (RS/KG) | C11: =R6 -> 90 | D11: =R7 -> 110 | E11: =R8 -> 110 | F11: =SUMPRODUCT(B11:E11,B8:E8) -> 6749.5428
A12: SCRAP RATE (RS/KG) | C12: 30 | D12: 30 | E12: 30
A13: NET RM COST (RS) | C13: =(C8*C11)-(C10*C12) -> 281.00472 | D13: =(D8*D11)-(D10*D12) -> 5240.8224 | E13: =(E8*E11)-(E10*E12) -> 236.82 | F13: =SUM(B13:E13) -> 5758.6471
A14: TOTAL (RS) | B14: =SUM(B13:E13) -> 5758.6471 | F14: =F13/F8 -> 92.918992
A15: BOP COST
A16: BOP COST (RS)
A17: TOTAL BOP | E17: =SUM(E16:E16) -> 0
A18: TOTAL OF RM + BOP (RS) | E18: =B14+E17 -> 5758.6471
A19: PROCESS COST
A20: SPEC | B20: QTY | C20: RATE | E20: TOTAL COST
A21: LASER /PLASMA/PIPE - Cutting (Min.) | B21: ='BOM R2D CatWalk'!X105 -> 4.1709091 | C21: 35 | E21: =B21*C21 -> 145.98182 | G21: =E21/$F$9 -> 7.0564888
A22: Machining (Hrs) | B22: ='BOM R2D CatWalk'!AB105 -> 0 | C22: 550 | E22: =B22*C22 -> 0 | G22: =E22/$F$9 -> 0
A23: BENDING BY CNC BENDING (STROKE) | B23: 2 | C23: 100 | E23: =B23*C23 -> 200 | G23: =E23/$F$9 -> 9.667627
A24: MIG WELDING (MTR.) | B24: ='BOM R2D CatWalk'!AF105 -> 0.859104 | C24: 250 | E24: =B24*C24 -> 214.776 | G24: =E24/$F$9 -> 10.381871
A25: GRINDING/BUFFING & FINISHING (hrs) | B25: =B24/12 -> 0.071592 | C25: 250 | E25: =B25*C25 -> 17.898 | G25: =E25/$F$9 -> 0.86515594
A26: INSPECTION & TESTING (HRS) | B26: =F9/95 -> 0.21776421 | C26: 1200 | E26: =B26*C26 -> 261.31705 | G26: =E26/$F$9 -> 12.631579
A27: STRESS RELIEVING | C27: 250 | E27: =B27*C27 -> 0 | F27: As Actual, If required | G27: =E27/$F$9 -> 0
A28: Shot Blasting | C28: 5 | E28: =C28*F9 -> 103.438 | G28: =E28/$F$9 -> 5
A29: Hot Dip Galvanization | B29: 0 | C29: 50 | E29: =B29*C29 -> 0 | G29: =E29/$F$9 -> 0
A30: PAINTING (including material & Labor) | B30: ='BOM R2D CatWalk'!AI105 -> 0.44613552 | C30: 1250 | E30: =B30*C30 -> 557.6694 | F30: No paint Detail Found | G30: =E30/$F$9 -> 26.956699
A31: Stamping Cost (HRS) | B31: =15/60 -> 0.25 | C31: 250 | E31: =B31*C31 -> 62.5 | G31: =E31/$F$9 -> 3.0211334
A32: FE cost | C32: 5 | E32: =C32*F9 -> 103.438 | G32: =E32/$F$9 -> 5
A33: TOTAL PROCESS COST OF PC | E33: =SUM(E21:E32) -> 1667.0183 | G33: =E33/$F$9 -> 80.580554
A34: TOTAL RM+BOP+PC | E34: =E18+E33 -> 7425.6654
A35: OH + Contingency | D35: 0.1 | E35: =E34*D35 -> 742.56654 | G35: =E35/$F$9 -> 35.894282
A36: Total Product Cost Without Profit | E36: =SUM(E34:E35) -> 8168.2319 | G36: =E36/F9 -> 394.8371 | I36: =E36/F8 -> 131.79899
F39: Min.
A40: NOTES:- | E40: OTHER COST | F40: Min.
A41: No BOP found in the Drawing Details
A42: Stress relieveing NOT FOUND ON PRINTS, IF REQUIRED | E42: As Actual
A45: NRC COST BREAKUP
A46: Fixture Details | B46: Approx Wt /Days | C46: Rate | D46: Cost
A47: Tacking Fixture main Frame | C47: 100 | D47: =B47*C47 -> 0
A48: Rotation arrangement | C48: 200 | D48: =B48*C48 -> 0
A49: FE COST | C49: 4.5 | D49: =B49*C49 -> 0
A50: SUB TOTAL | D50: =SUM(D47:D49) -> 0
A51: Development and Engg | C51: =75000/30 -> 2500 | D51: =B51*C51 -> 0
A52: OH + Contingency | C52: 0.07 | D52: =(D50+D51)*C52 -> 0
A53: Total Cost | D53: =SUM(D50:D52) -> 0

Sheet Item-4_AY30027
A1: COSTING SHEET
A2: PRODUCT NAME:- | B2: ='BOM R2D CatWalk'!I100 -> WELDMENT, HINGED FLOOR, PC4100 | D2: RFQ Ref.
A3: ITEM DRG NO | B3: ='BOM R2D CatWalk'!G100 -> AY30027 | D3: Total Quantity | E3: ='BOM R2D CatWalk'!K100 -> 23
A4: Total Net WT as per Drawing | B4: ='BOM R2D CatWalk'!N100 -> 455.4 | I4: S.No | J4: Type | K4: Size (mm) | L4: Material | M4: Sum of Total Weight (Kg) | N4: Sum of Gross Wt (kg) | O4: MOQ Weight | P4: Remarks | Q4: Cal. Weight | R4: Rate/Kg | S4: Cost
A5: COSTBREAKUP OF COMPONENT (QTY-01 No.) | I5: 1 | J5: Plate | K5: 6 | L5: E350 A/BR | M5: ='RM Details'!E56 -> 391 | N5: ='RM Details'!F56 -> 428.97608 | O5: 0 | Q5: =IF(O5>N5,O5,IF(O5<N5,N5)) -> 428.97608 | R5: 90 | S5: =R5*Q5 -> 38607.847
A6: RAW MATERIAL COST | I6: 2 | J6: Plate | K6: 10 | L6: E350 A/BR | M6: ='RM Details'!E57 -> 52.058131 | N6: ='RM Details'!F57 -> 61.561989 | O6: 0 | Q6: =IF(O6>N6,O6,IF(O6<N6,N6)) -> 61.561989 | R6: 90 | S6: =R6*Q6 -> 5540.579
A7: SPEC | D7: IS 2062 E350 A/BR | K7: Total | M7: =SUM(M5:M6) -> 443.05813 | N7: =SUM(N5:N6) -> 490.53806 | Q7: =SUM(Q5:Q6) -> 490.53806 | R7: =S7/Q7 -> 90 | S7: =SUM(S5:S6) -> 44148.426
A8: GROSS WT. (KG) | D8: =Q5+Q6 -> 490.53806 | F8: =SUM(C8:E8) -> 490.53806
A9: NET WT (KG) | D9: =M5+M6 -> 443.05813 | F9: =SUM(C9:E9) -> 443.05813
A10: SCRAP (KG) | D10: =(D8-D9)*80% -> 37.983947 | F10: =(F8-F9)/F9 -> 0.10716412
A11: RM RATE (RS/KG) | D11: =R5 -> 90 | F11: =SUMPRODUCT(B11:E11,B8:E8) -> 44148.426
A12: SCRAP RATE (RS/KG) | D12: 30
A13: NET RM COST (RS) | D13: =(D8*D11)-(D10*D12) -> 43008.907 | F13: =SUM(B13:E13) -> 43008.907
A14: TOTAL (RS) | B14: =SUM(B13:E13) -> 43008.907 | F14: =F13/F8 -> 87.677003
A15: BOP COST
A16: BOP COST (RS)
A17: TOTAL BOP | E17: =SUM(E16:E16) -> 0
A18: TOTAL OF RM + BOP (RS) | E18: =B14+E17 -> 43008.907
A19: PROCESS COST
A20: SPEC | B20: QTY | C20: RATE | E20: TOTAL COST
A21: LASER /PLASMA/PIPE - Cutting (Min.) | B21: ='BOM R2D CatWalk'!X100 -> 3.199351 | C21: 50 | E21: =B21*C21 -> 159.96755 | G21: =E21/$F$9 -> 0.36105319
A22: Machining (Hrs) | B22: ='BOM R2D CatWalk'!AB100 -> 0 | C22: 550 | E22: =B22*C22 -> 0 | G22: =E22/$F$9 -> 0
A23: BENDING BY CNC BENDING (STROKE) | B23: ='BOM R2D CatWalk'!Z100 -> 92 | C23: 100 | E23: =B23*C23 -> 9200 | G23: =E23/$F$9 -> 20.76477
A24: MIG WELDING (MTR.) | B24: ='BOM R2D CatWalk'!AF100 -> 39.9372 | C24: 250 | E24: =B24*C24 -> 9984.3 | G24: =E24/$F$9 -> 22.534966
A25: GRINDING/BUFFING & FINISHING (hrs) | B25: =B24/12 -> 3.3281 | C25: 250 | E25: =B25*C25 -> 832.025 | G25: =E25/$F$9 -> 1.8779138
A26: INSPECTION & TESTING (HRS) | B26: =F9/95 -> 4.6637698 | C26: 1200 | E26: =B26*C26 -> 5596.5238 | G26: =E26/$F$9 -> 12.631579
A27: STRESS RELIEVING | C27: 250 | E27: =B27*C27 -> 0 | F27: As Actual, If required | G27: =E27/$F$9 -> 0
A28: Shot Blasting | C28: 5 | E28: =C28*F9 -> 2215.2907 | G28: =E28/$F$9 -> 5
A29: Hot Dip Galvanization | B29: 0 | C29: 50 | E29: =B29*C29 -> 0 | G29: =E29/$F$9 -> 0
A30: PAINTING (including material & Labor) | B30: ='BOM R2D CatWalk'!AI100 -> 20.683276 | C30: 1250 | E30: =B30*C30 -> 25854.095 | F30: No paint Detail Found | G30: =E30/$F$9 -> 58.35373
A31: Stamping Cost (HRS) | B31: =15/60 -> 0.25 | C31: 250 | E31: =B31*C31 -> 62.5 | G31: =E31/$F$9 -> 0.14106501
A32: FE cost | C32: 4.5 | E32: =C32*F9 -> 1993.7616 | G32: =E32/$F$9 -> 4.5
A33: TOTAL PROCESS COST OF PC | E33: =SUM(E21:E32) -> 55898.463 | G33: =E33/$F$9 -> 126.16508
A34: TOTAL RM+BOP+PC | E34: =E18+E33 -> 98907.371
A35: OH + Contingency | D35: 0.1 | E35: =E34*D35 -> 9890.7371 | G35: =E35/$F$9 -> 22.323791
A36: Total Product Cost Without Profit | E36: =SUM(E34:E35) -> 108798.11 | G36: =E36/F9 -> 245.5617 | I36: =E36/F8 -> 221.79341
F39: Min.
A40: NOTES:- | E40: OTHER COST | F40: Min.
A41: No BOP found in the Drawing Details
A42: Stress relieveing NOT FOUND ON PRINTS, IF REQUIRED | E42: As Actual
A45: NRC COST BREAKUP
A46: Fixture Details | B46: Approx Wt /Days | C46: Rate | D46: Cost
A47: Tacking Fixture main Frame | C47: 100 | D47: =B47*C47 -> 0
A48: Testing Templates | C48: 100 | D48: =B48*C48 -> 0
A49: FE COST | C49: 4.5 | D49: =B49*C49 -> 0
A50: SUB TOTAL | D50: =SUM(D47:D49) -> 0
A51: Development and Engg | C51: =75000/30 -> 2500 | D51: =B51*C51 -> 0
A52: OH + Contingency | C52: 0.07 | D52: =(D50+D51)*C52 -> 0
A53: Total Cost | D53: =SUM(D50:D52) -> 0

Sheet Item-3_AY30018
A1: COSTING SHEET
A2: PRODUCT NAME:- | B2: ='BOM R2D CatWalk'!I97 -> WELDMENT, HINGED FLOOR, PC4100 | D2: RFQ Ref.
A3: ITEM DRG NO | B3: ='BOM R2D CatWalk'!G97 -> AY30018 | D3: Total Quantity | E3: ='BOM R2D CatWalk'!K97 -> 1
A4: Total Net WT as per Drawing | B4: ='BOM R2D CatWalk'!N97 -> 27 | I4: S.No | J4: Type | K4: Size (mm) | L4: Material | M4: Sum of Total Weight (Kg) | N4: Sum of Gross Wt (kg) | O4: MOQ Weight | P4: Remarks | Q4: Cal. Weight | R4: Rate/Kg | S4: Cost
A5: COSTBREAKUP OF COMPONENT (QTY-01 No.) | I5: 1 | J5: Plate | K5: 6 | L5: E350 A/BR | M5: ='RM Details'!E44 -> 26 | N5: ='RM Details'!F44 -> 28.6 | O5: 0 | Q5: =IF(O5>N5,O5,IF(O5<N5,N5)) -> 28.6 | R5: 90 | S5: =R5*Q5 -> 2574
A6: RAW MATERIAL COST | I6: 2 | J6: Plate | K6: 10 | L6: E350 A/BR | M6: ='RM Details'!E45 -> 0.8 | N6: ='RM Details'!F45 -> 1.0668715 | O6: 0 | Q6: =IF(O6>N6,O6,IF(O6<N6,N6)) -> 1.0668715 | R6: 90 | S6: =R6*Q6 -> 96.018437
A7: SPEC | D7: IS 2062 E350 A/BR | K7: Total | M7: =SUM(M5:M6) -> 26.8 | N7: =SUM(N5:N6) -> 29.666872 | Q7: =SUM(Q5:Q6) -> 29.666872 | R7: =S7/Q7 -> 90 | S7: =SUM(S5:S6) -> 2670.0184
A8: GROSS WT. (KG) | D8: =Q5+Q6 -> 29.666872 | F8: =SUM(C8:E8) -> 29.666872
A9: NET WT (KG) | D9: =M5+M6 -> 26.8 | F9: =SUM(C9:E9) -> 26.8
A10: SCRAP (KG) | D10: =(D8-D9)*80% -> 2.2934972 | F10: =(F8-F9)/F9 -> 0.10697282
A11: RM RATE (RS/KG) | D11: =R5 -> 90 | F11: =SUMPRODUCT(B11:E11,B8:E8) -> 2670.0184
A12: SCRAP RATE (RS/KG) | D12: 30
A13: NET RM COST (RS) | D13: =(D8*D11)-(D10*D12) -> 2601.2135 | F13: =SUM(B13:E13) -> 2601.2135
A14: TOTAL (RS) | B14: =SUM(B13:E13) -> 2601.2135 | F14: =F13/F8 -> 87.680749
A15: BOP COST
A16: BOP COST (RS)
A17: TOTAL BOP | E17: =SUM(E16:E16) -> 0
A18: TOTAL OF RM + BOP (RS) | E18: =B14+E17 -> 2601.2135
A19: PROCESS COST
A20: SPEC | B20: QTY | C20: RATE | E20: TOTAL COST
A21: LASER /PLASMA/PIPE - Cutting (Min.) | B21: ='BOM R2D CatWalk'!X97 -> 1.1326886 | C21: 50 | E21: =B21*C21 -> 56.63443 | G21: =E21/$F$9 -> 2.113225
A22: Machining (Hrs) | B22: ='BOM R2D CatWalk'!AB97 -> 0 | C22: 550 | E22: =B22*C22 -> 0 | G22: =E22/$F$9 -> 0
A23: BENDING BY CNC BENDING (STROKE) | B23: ='BOM R2D CatWalk'!Z97 -> 4 | C23: 100 | E23: =B23*C23 -> 400 | G23: =E23/$F$9 -> 14.925373
A24: MIG WELDING (MTR.) | B24: ='BOM R2D CatWalk'!AF97 -> 0.4416 | C24: 250 | E24: =B24*C24 -> 110.4 | G24: =E24/$F$9 -> 4.119403
A25: GRINDING/BUFFING & FINISHING (hrs) | B25: =B24/12 -> 0.0368 | C25: 250 | E25: =B25*C25 -> 9.2 | G25: =E25/$F$9 -> 0.34328358
A26: INSPECTION & TESTING (HRS) | B26: =F9/95 -> 0.28210526 | C26: 1200 | E26: =B26*C26 -> 338.52632 | G26: =E26/$F$9 -> 12.631579
A27: STRESS RELIEVING | C27: 250 | E27: =B27*C27 -> 0 | F27: As Actual, If required | G27: =E27/$F$9 -> 0
A28: Shot Blasting | C28: 5 | E28: =C28*F9 -> 134 | G28: =E28/$F$9 -> 5
A29: Hot Dip Galvanization | B29: 0 | C29: 50 | E29: =B29*C29 -> 0 | G29: =E29/$F$9 -> 0
A30: PAINTING (including material & Labor) | B30: ='BOM R2D CatWalk'!AI97 -> 1.2501494 | C30: 1250 | E30: =B30*C30 -> 1562.6867 | F30: No paint Detail Found | G30: =E30/$F$9 -> 58.309205
A31: Stamping Cost (HRS) | B31: =15/60 -> 0.25 | C31: 250 | E31: =B31*C31 -> 62.5 | G31: =E31/$F$9 -> 2.3320896
A32: FE cost | C32: 5 | E32: =C32*F9 -> 134 | G32: =E32/$F$9 -> 5
A33: TOTAL PROCESS COST OF PC | E33: =SUM(E21:E32) -> 2807.9474 | G33: =E33/$F$9 -> 104.77416
A34: TOTAL RM+BOP+PC | E34: =E18+E33 -> 5409.161
A35: OH + Contingency | D35: 0.1 | E35: =E34*D35 -> 540.9161 | G35: =E35/$F$9 -> 20.183436
A36: Total Product Cost Without Profit | E36: =SUM(E34:E35) -> 5950.0771 | G36: =E36/F9 -> 222.0178 | I36: =E36/F8 -> 200.56301
F39: Min.
A40: NOTES:- | E40: OTHER COST | F40: Min.
A41: No BOP found in the Drawing Details
A42: Stress relieveing NOT FOUND ON PRINTS, IF REQUIRED | E42: As Actual
A45: NRC COST BREAKUP
A46: Fixture Details | B46: Approx Wt /Days | C46: Rate | D46: Cost
A47: Tacking Fixture main Frame | B47: 0 | C47: 100 | D47: =B47*C47 -> 0
A48: Testing Templates | B48: 0 | C48: 100 | D48: =B48*C48 -> 0
A49: FE COST | B49: =SUM(B47:B48) -> 0 | C49: 4.5 | D49: =B49*C49 -> 0
A50: SUB TOTAL | D50: =SUM(D47:D49) -> 0
A51: Development and Engg | B51: 0 | C51: =75000/30 -> 2500 | D51: =B51*C51 -> 0
A52: OH + Contingency | C52: 0.07 | D52: =(D50+D51)*C52 -> 0
A53: Total Cost | D53: =SUM(D50:D52) -> 0

Sheet Item-2_AY30017
A1: COSTING SHEET
A2: PRODUCT NAME:- | B2: ='BOM R2D CatWalk'!I93 -> WELDMENT, FALSE FLOOR, PC4100 | D2: RFQ Ref.
A3: ITEM DRG NO | B3: ='BOM R2D CatWalk'!G93 -> AY30017 | D3: Total Quantity | E3: ='BOM R2D CatWalk'!K93 -> 2
A4: Total Net WT as per Drawing | B4: ='BOM R2D CatWalk'!N93 -> 130 | I4: S.No | J4: Type | K4: Size (mm) | L4: Material | M4: Sum of Total Weight (Kg) | N4: Sum of Gross Wt (kg) | O4: MOQ Weight | P4: Remarks | Q4: Cal. Weight | R4: Rate/Kg | S4: Cost
A5: COSTBREAKUP OF COMPONENT (QTY-01 No.) | I5: 2 | J5: Plate | K5: 10 | L5: E250 A/BR | M5: ='RM Details'!E32 -> 6 | N5: ='RM Details'!F32 -> 8.20325 | O5: 0 | Q5: =IF(O5>N5,O5,IF(O5<N5,N5)) -> 8.20325 | R5: 90 | S5: =R5*Q5 -> 738.2925
A6: RAW MATERIAL COST | I6: 3 | J6: Plate | K6: 16 | L6: E250 A/BR | M6: ='RM Details'!E33 -> 12 | N6: ='RM Details'!F33 -> 17.728139 | O6: 0 | Q6: =IF(O6>N6,O6,IF(O6<N6,N6)) -> 17.728139 | R6: 90 | S6: =R6*Q6 -> 1595.5325
A7: SPEC | D7: IS 2062 E250 A/BR | E7: Rolled Section E350A | I7: 4 | J7: Plate | K7: ISMC 200x 75 | L7: E350 A | M7: ='RM Details'!E34 -> 112.332 | N7: ='RM Details'!F34 -> 123.5652 | O7: =22.3*6 -> 133.8 | P7: JSPL | Q7: =IF(O7>N7,O7,IF(O7<N7,N7)) -> 133.8 | R7: 110 | S7: =R7*Q7 -> 14718
A8: GROSS WT. (KG) | D8: =Q5+Q6 -> 25.931389 | E8: =Q7 -> 133.8 | F8: =SUM(C8:E8) -> 159.73139 | K8: Total | M8: =SUM(M5:M7) -> 130.332 | N8: =SUM(N5:N7) -> 149.49659 | Q8: =SUM(Q5:Q7) -> 159.73139 | R8: =S8/Q8 -> 106.75313 | S8: =SUM(S5:S7) -> 17051.825
A9: NET WT (KG) | D9: =M5+M6 -> 18 | E9: =M7 -> 112.332 | F9: =SUM(C9:E9) -> 130.332
A10: SCRAP (KG) | D10: =(D8-D9)*80% -> 6.3451108 | E10: =(E8-E9)*80% -> 17.1744 | F10: =(F8-F9)/F9 -> 0.22557306
A11: RM RATE (RS/KG) | D11: =R5 -> 90 | E11: =R7 -> 110 | F11: =SUMPRODUCT(B11:E11,B8:E8) -> 17051.825
A12: SCRAP RATE (RS/KG) | D12: 30 | E12: 30
A13: NET RM COST (RS) | D13: =(D8*D11)-(D10*D12) -> 2143.4716 | E13: =(E8*E11)-(E10*E12) -> 14202.768 | F13: =SUM(B13:E13) -> 16346.24
A14: TOTAL (RS) | B14: =SUM(B13:E13) -> 16346.24 | F14: =F13/F8 -> 102.3358
A15: BOP COST
A16: BOP COST (RS)
A17: TOTAL BOP | E17: =SUM(E16:E16) -> 0
A18: TOTAL OF RM + BOP (RS) | E18: =B14+E17 -> 16346.24
A19: PROCESS COST
A20: SPEC | B20: QTY | C20: RATE | E20: TOTAL COST
A21: LASER /PLASMA/PIPE - Cutting (Min.) | B21: ='BOM R2D CatWalk'!X93 -> 25.102121 | C21: 35 | E21: =B21*C21 -> 878.57424 | G21: =E21/$F$9 -> 6.7410478
A22: Machining (Hrs) | B22: 1 | C22: 1000 | E22: =B22*C22 -> 1000 | G22: =E22/$F$9 -> 7.6727128
A23: BENDING BY CNC BENDING (STROKE) | B23: ='BOM R2D CatWalk'!Z93 -> 0 | C23: 100 | E23: =B23*C23 -> 0 | G23: =E23/$F$9 -> 0
A24: MIG WELDING (MTR.) | B24: ='BOM R2D CatWalk'!AF93 -> 11.04 | C24: 250 | E24: =B24*C24 -> 2760 | G24: =E24/$F$9 -> 21.176687
A25: GRINDING/BUFFING & FINISHING (hrs) | B25: =B24/12 -> 0.92 | C25: 250 | E25: =B25*C25 -> 230 | G25: =E25/$F$9 -> 1.7647239
A26: INSPECTION & TESTING (HRS) | B26: =F9/95 -> 1.3719158 | C26: 1200 | E26: =B26*C26 -> 1646.2989 | G26: =E26/$F$9 -> 12.631579
A27: STRESS RELIEVING | C27: 250 | E27: =B27*C27 -> 0 | F27: As Actual, If required | G27: =E27/$F$9 -> 0
A28: Shot Blasting | C28: 5 | E28: =C28*F9 -> 651.66 | G28: =E28/$F$9 -> 5
A29: Hot Dip Galvanization | B29: 0 | C29: 50 | E29: =B29*C29 -> 0 | G29: =E29/$F$9 -> 0
A30: PAINTING (including material & Labor) | B30: ='BOM R2D CatWalk'!AI93 -> 2.3088964 | C30: 1250 | E30: =B30*C30 -> 2886.1205 | F30: No paint Detail Found | G30: =E30/$F$9 -> 22.144374
A31: Stamping Cost (HRS) | B31: =15/60 -> 0.25 | C31: 250 | E31: =B31*C31 -> 62.5 | G31: =E31/$F$9 -> 0.47954455
A32: FE cost | C32: 5 | E32: =C32*F9 -> 651.66 | G32: =E32/$F$9 -> 5
A33: TOTAL PROCESS COST OF PC | E33: =SUM(E21:E32) -> 10766.814 | G33: =E33/$F$9 -> 82.610669
A34: TOTAL RM+BOP+PC | E34: =E18+E33 -> 27113.053
A35: OH + Contingency | D35: 0.1 | E35: =E34*D35 -> 2711.3053 | G35: =E35/$F$9 -> 20.803067
A36: Total Product Cost Without Profit | E36: =SUM(E34:E35) -> 29824.359 | G36: =E36/F9 -> 228.83374 | I36: =E36/F8 -> 186.7157
F39: Min.
A40: NOTES:- | E40: OTHER COST | F40: Min.
A41: No BOP found in the Drawing Details
A42: Stress relieveing NOT FOUND ON PRINTS, IF REQUIRED | E42: As Actual
A45: NRC COST BREAKUP
A46: Fixture Details | B46: Approx Wt /Days | C46: Rate | D46: Cost
A47: Tacking Fixture main Frame | B47: =B4*0.8 -> 104 | C47: 100 | D47: =B47*C47 -> 10400
A48: Templates | B48: =B4*0.2 -> 26 | C48: 100 | D48: =B48*C48 -> 2600
A49: FE COST | B49: =SUM(B47:B48) -> 130 | C49: 4.5 | D49: =B49*C49 -> 585
A50: SUB TOTAL | D50: =SUM(D47:D49) -> 13585
A51: Development and Engg | B51: 2 | C51: =75000/30 -> 2500 | D51: =B51*C51 -> 5000
A52: OH + Contingency | C52: 0.0255 | D52: =(D50+D51)*C52 -> 473.9175
A53: Total Cost | D53: =SUM(D50:D52) -> 19058.917

Sheet Item-1_AY30013
A1: COSTING SHEET
A2: PRODUCT NAME:- | B2: ='BOM R2D CatWalk'!I4 -> WELDMENT, PC4100 R2D SLAVE SKID, PC4100 | E2: RFQ Ref.
A3: ITEM DRG NO | B3: ='BOM R2D CatWalk'!G4 -> AY30013 | E3: Total Quantity | G3: ='BOM R2D CatWalk'!K4 -> 1
A4: Total Net WT as per Drawing | C4: ='BOM R2D CatWalk'!N4 -> 4034 | K4: S.No | L4: Type | M4: Size (mm) | N4: Material | O4: Sum of Total Weight (Kg) | P4: Sum of Gross Wt (kg) | Q4: MOQ Weight | R4: Remarks | S4: Cal. Weight | T4: Collective Weight | U4: Rate/Kg | V4: Cost
A5: COSTBREAKUP OF COMPONENT (QTY-01 No.) | K5: 1 | L5: Plate | M5: 6 | N5: E350 A/BR | O5: ='RM Details'!E3 -> 107.02366 | P5: ='RM Details'!F3 -> 118.91781 | Q5: 0 | S5: =IF(Q5>P5,Q5,IF(Q5<P5,P5)) -> 118.91781 | U5: 90 | V5: =U5*S5 -> 10702.603
A6: RAW MATERIAL COST | K6: 2 | L6: Plate | M6: 10 | N6: E350 A/BR | O6: ='RM Details'!E4 -> 824.37734 | P6: ='RM Details'!F4 -> 1100.4267 | Q6: 0 | S6: =IF(Q6>P6,Q6,IF(Q6<P6,P6)) -> 1100.4267 | U6: 90 | V6: =U6*S6 -> 99038.403
A7: SPEC | B7: IS 2062 E350 A/BO | C7: IS 2062 E250 A/BO | D7: YST 310 | E7: ASTM A106 GR.B | F7: Rolled Section E350A | G7: Rolled Section E250A | K7: 3 | L7: Plate | M7: 12 | N7: E350 A/BR | O7: ='RM Details'!E5 -> 243.8 | P7: ='RM Details'!F5 -> 331.38795 | Q7: 0 | S7: =IF(Q7>P7,Q7,IF(Q7<P7,P7)) -> 331.38795 | U7: 90 | V7: =U7*S7 -> 29824.916
A8: GROSS WT. (KG) | B8: =T8 -> 1677.6324 | C8: =T14 -> 559.15472 | D8: =T17 -> 195.66 | E8: =T22 -> 534.24 | F8: =T24 -> 2162.3149 | G8: =T26 -> 168.79942 | H8: =SUM(B8:G8) -> 5297.8014 | K8: 4 | L8: Plate | M8: 50 | N8: E350 A/BR | O8: ='RM Details'!E6 -> 76 | P8: ='RM Details'!F6 -> 126.89996 | Q8: 0 | S8: =IF(Q8>P8,Q8,IF(Q8<P8,P8)) -> 126.89996 | T8: =SUM(S5:S8) -> 1677.6324 | U8: 90 | V8: =U8*S8 -> 11420.996 | W8: =SUM(V5:V8)/T8 -> 90
A9: NET WT (KG) | B9: =SUM(O5:O8) -> 1251.201 | C9: =SUM(O9:O14) -> 462.81396 | D9: =SUM(O15:O17) -> 70.33084 | E9: =SUM(O18:O22) -> 139.60883 | F9: =SUM(O23:O24) -> 1978.1207 | G9: =SUM(O25:O26) -> 149.99104 | H9: =SUM(B9:G9) -> 4052.0664 | K9: 5 | L9: Plate | M9: 5 | N9: E250 A/BR | O9: ='RM Details'!E7 -> 0.199861 | P9: ='RM Details'!F7 -> 0.199861 | Q9: 0 | S9: =IF(Q9>P9,Q9,IF(Q9<P9,P9)) -> 0.199861 | U9: 110 | V9: =U9*S9 -> 21.98471
A10: SCRAP (KG) | B10: =(B8-B9)*80% -> 341.14514 | C10: =(C8-C9)*80% -> 77.072611 | D10: =(D8-D9)*80% -> 100.26333 | E10: =(E8-E9)*80% -> 315.70494 | F10: =(F8-F9)*80% -> 147.35533 | G10: =(G8-G9)*80% -> 15.046707 | H10: =(H8-H9)/H9 -> 0.30743205 | K10: 6 | L10: Plate | M10: 6 | N10: E250 A/BR | O10: ='RM Details'!E8 -> 36.027967 | P10: ='RM Details'!F8 -> 39.630764 | Q10: 0 | S10: =IF(Q10>P10,Q10,IF(Q10<P10,P10)) -> 39.630764 | U10: 110 | V10: =U10*S10 -> 4359.3841
A11: RM RATE (RS/KG) | B11: 85 | C11: 85 | D11: 200 | E11: 125 | F11: 120 | G11: 120 | H11: =SUMPRODUCT(B11:G11,B8:G8) -> 575772.62 | K11: 7 | L11: Plate | M11: 12 | N11: E250 A/BR | O11: ='RM Details'!E9 -> 5.38353 | P11: ='RM Details'!F9 -> 5.921883 | Q11: 0 | S11: =IF(Q11>P11,Q11,IF(Q11<P11,P11)) -> 5.921883 | U11: 110 | V11: =U11*S11 -> 651.40713
A12: SCRAP RATE (RS/KG) | B12: 30 | C12: 30 | D12: 30 | E12: 30 | F12: 30 | G12: 30 | K12: 8 | L12: Plate | M12: 20 | N12: E250 A/BR | O12: ='RM Details'!E10 -> 315.9956 | P12: ='RM Details'!F10 -> 352.37708 | Q12: 0 | S12: =IF(Q12>P12,Q12,IF(Q12<P12,P12)) -> 352.37708 | U12: 90 | V12: =U12*S12 -> 31713.937
A13: NET RM COST (RS) | B13: =(B8*B11)-(B10*B12) -> 132364.4 | C13: =(C8*C11)-(C10*C12) -> 45215.973 | D13: =(D8*D11)-(D10*D12) -> 36124.1 | E13: =(E8*E11)-(E10*E12) -> 57308.852 | F13: =(F8*F11)-(F10*F12) -> 255057.12 | G13: =(G8*G11)-(G10*G12) -> 19804.53 | H13: =SUM(B13:G13) -> 545874.98 | K13: 9 | L13: Plate | M13: 25 | N13: E250 A/BR | O13: ='RM Details'!E11 -> 16.007 | P13: ='RM Details'!F11 -> 21.630675 | Q13: 0 | S13: =IF(Q13>P13,Q13,IF(Q13<P13,P13)) -> 21.630675 | U13: 110 | V13: =U13*S13 -> 2379.3742
A14: TOTAL (RS) | B14: =SUM(B13:G13) -> 545874.98 | H14: =H13/H8 -> 103.03802 | K14: 10 | L14: Plate | M14: 40 | N14: E250 A/BR | O14: ='RM Details'!E12 -> 89.2 | P14: ='RM Details'!F12 -> 139.39446 | Q14: 0 | S14: =IF(Q14>P14,Q14,IF(Q14<P14,P14)) -> 139.39446 | T14: =SUM(S9:S14) -> 559.15472 | U14: 90 | V14: =U14*S14 -> 12545.501 | W14: =SUM(V9:V14)/T14 -> 92.41018
A15: BOP COST | K15: 11 | L15: Rec Tube | M15: 100x80x 5thk 120x60x5 thk | N15: YST 310 | O15: ='RM Details'!E13 -> 23.0688 | P15: ='RM Details'!F13 -> 25.37568 | Q15: =12.84*6 -> 77.04 | R15: Apollo Make | S15: =IF(Q15>P15,Q15,IF(Q15<P15,P15)) -> 77.04 | U15: 120 | V15: =U15*S15 -> 9244.8
A16: BOP COST (RS) | G16: ='BOM R2D CatWalk'!AE32+'BOM R2D CatWalk'!AE59+'BOM R2D CatWalk'!AE69+'BOM R2D CatWalk'!AE85 -> 8000 | H16: estimated | K16: 12 | L16: Sq. Tube | M16: 50x50x 5thk | N16: YST 310 | O16: ='RM Details'!E14 -> 20.44644 | P16: ='RM Details'!F14 -> 22.491084 | Q16: =6.56*6 -> 39.36 | R16: Apollo Make | S16: =IF(Q16>P16,Q16,IF(Q16<P16,P16)) -> 39.36 | U16: 120 | V16: =U16*S16 -> 4723.2
A17: TOTAL BOP | G17: =SUM(G16:G16) -> 8000 | K17: 13 | L17: Sq. Tube | M17: 80x80x 10thk x 6 thk | N17: YST 310 | O17: ='RM Details'!E15 -> 26.8156 | P17: ='RM Details'!F15 -> 29.49716 | Q17: =13.21*6 -> 79.26 | R17: Apollo Make | S17: =IF(Q17>P17,Q17,IF(Q17<P17,P17)) -> 79.26 | T17: =SUM(S15:S17) -> 195.66 | U17: 120 | V17: =U17*S17 -> 9511.2 | W17: =SUM(V15:V17)/T17 -> 120
A18: TOTAL OF RM + BOP (RS) | G18: =B14+G17 -> 553874.98 | K18: 14 | L18: Pipe | M18: Dia 101.6 x 8.08 thk | N18: ASTM A106 GR.B | O18: ='RM Details'!E16 -> 9.3032968 | P18: ='RM Details'!F16 -> 10.233626 | Q18: =18.64*6 -> 111.84 | R18: Yash Pipe | S18: =IF(Q18>P18,Q18,IF(Q18<P18,P18)) -> 111.84 | U18: 110 | V18: =U18*S18 -> 12302.4
A19: PROCESS COST | K19: 15 | L19: Pipe | M19: Dia 114.3 x 8.56 thk | N19: ASTM A106 GR.B | O19: ='RM Details'!E17 -> 28.04648 | P19: ='RM Details'!F17 -> 30.851128 | Q19: =22.33*6 -> 133.98 | R19: Yash Pipe | S19: =IF(Q19>P19,Q19,IF(Q19<P19,P19)) -> 133.98 | U19: 110 | V19: =U19*S19 -> 14737.8
A20: SPEC | B20: QTY | D20: RATE | G20: TOTAL COST | K20: 16 | L20: Pipe | M20: Dia 168.28 x 10.97thk | N20: ASTM A106 GR.B | O20: ='RM Details'!E18 -> 101.63328 | P20: ='RM Details'!F18 -> 111.79661 | Q20: =42.56*6 -> 255.36 | R20: Yash Pipe | S20: =IF(Q20>P20,Q20,IF(Q20<P20,P20)) -> 255.36 | U20: 110 | V20: =U20*S20 -> 28089.6
A21: LASER /PLASMA/PIPE - Cutting (Min.) | B21: ='BOM R2D CatWalk'!X4 -> 373.86909 | D21: 45 | G21: =B21*D21 -> 16824.109 | I21: =G21/$H$9 -> 4.1519826 | K21: 17 | L21: Pipe | M21: Dia 21.3 x 2.77 thk | N21: ASTM A106 GR.B | O21: ='RM Details'!E19 -> 0.26289 | P21: ='RM Details'!F19 -> 0.289179 | Q21: =1.27*6 -> 7.62 | R21: Yash Pipe | S21: =IF(Q21>P21,Q21,IF(Q21<P21,P21)) -> 7.62 | U21: 160 | V21: =U21*S21 -> 1219.2
A22: Machining (Hrs) | B22: ='BOM R2D CatWalk'!AB4/60 -> 3.9666667 | D22: 1000 | G22: =B22*D22 -> 3966.6667 | I22: =G22/$H$9 -> 0.97892441 | K22: 18 | L22: Pipe | M22: Dia 33.4x 6.35 | N22: ASTM A106 GR.B | O22: ='RM Details'!E20 -> 0.36288 | P22: ='RM Details'!F20 -> 0.399168 | Q22: =4.24*6 -> 25.44 | R22: Yash Pipe | S22: =IF(Q22>P22,Q22,IF(Q22<P22,P22)) -> 25.44 | T22: =SUM(S18:S22) -> 534.24 | U22: 130 | V22: =U22*S22 -> 3307.2 | W22: =SUM(V18:V22)/T22 -> 111.66554
A23: BENDING BY CNC BENDING (STROKE) | B23: ='BOM R2D CatWalk'!Z4 -> 9 | D23: 100 | G23: =B23*D23 -> 900 | I23: =G23/$H$9 -> 0.2221089 | K23: 19 | L23: Channel | M23: ISMC 200 x 75 | N23: E350 A | O23: ='RM Details'!E21 -> 982.1207 | P23: ='RM Details'!F21 -> 1080.3328 | Q23: =22.3*6 -> 133.8 | R23: JSIL | S23: =IF(Q23>P23,Q23,IF(Q23<P23,P23)) -> 1080.3328 | U23: 100 | V23: =U23*S23 -> 108033.28
A24: MIG WELDING (MTR.) | B24: 500 | D24: 300 | G24: =B24*D24 -> 150000 | I24: =G24/$H$9 -> 37.01815 | K24: 20 | L24: Beam | M24: NPB 600x 220x 107.57 | N24: E350 A | O24: ='RM Details'!E22 -> 996 | P24: ='RM Details'!F22 -> 1081.9821 | Q24: =107.6*6 -> 645.6 | R24: SAIL | S24: =IF(Q24>P24,Q24,IF(Q24<P24,P24)) -> 1081.9821 | T24: =S23+S24 -> 2162.3149 | U24: 100 | V24: =U24*S24 -> 108198.21 | W24: =SUM(V23:V24)/T24 -> 100
A25: GRINDING/BUFFING & FINISHING (hrs) | B25: =B24/12.5 -> 40 | D25: 250 | G25: =B25*D25 -> 10000 | I25: =G25/$H$9 -> 2.4678767 | K25: 21 | L25: Channel | M25: UPN80 X 45/ISMC 75x40 | N25: E250 A | O25: ='RM Details'!E23 -> 149.95104 | P25: ='RM Details'!F23 -> 166.13942 | Q25: =7.14*6 -> 42.84 | R25: SAIL | S25: =IF(Q25>P25,Q25,IF(Q25<P25,P25)) -> 166.13942 | U25: 100 | V25: =U25*S25 -> 16613.942
A26: INSPECTION & TESTING (HRS) | B26: =H9/95 -> 42.65333 | D26: 1200 | G26: =B26*D26 -> 51183.996 | I26: =G26/$H$9 -> 12.631579 | K26: 22 | L26: Rod | M26: Dia 12 | N26: E250 A/BR | O26: ='RM Details'!E24 -> 0.04 | P26: ='RM Details'!F24 -> 0.29315 | Q26: 2.66 | R26: Yash Pipe | S26: =IF(Q26>P26,Q26,IF(Q26<P26,P26)) -> 2.66 | T26: =S25+S26 -> 168.79942 | U26: 150 | V26: =U26*S26 -> 399 | W26: =SUM(V25:V26)/T26 -> 100.78792
A27: STRESS RELIEVING | D27: 250 | G27: =B27*D27 -> 0 | H27: As Actual, If required | I27: =G27/$H$9 -> 0 | M27: Total | O27: =SUM(O5:O25) -> 4052.0264 | P27: =SUM(P5:P25) -> 4796.1751 | S27: =SUM(S5:S25) -> 5295.1414 | U27: =V27/S27 -> 97.946267 | V27: =SUM(V5:V25) -> 518639.33
A28: Shot Blasting | D28: 5 | G28: =D28*H9 -> 20260.332 | I28: =G28/$H$9 -> 5
A29: Hot Dip Galvanization | B29: 0 | D29: 50 | G29: =B29*D29 -> 0 | I29: =G29/$H$9 -> 0
A30: PAINTING (including material & Labor) | B30: ='BOM R2D CatWalk'!AI4 -> 51.842346 | D30: 1250 | G30: =B30*D30 -> 64802.932 | H30: No paint Detail Found | I30: =G30/$H$9 -> 15.992564
A31: Stamping Cost (HRS) | B31: =15/60 -> 0.25 | D31: 250 | G31: =B31*D31 -> 62.5 | I31: =G31/$H$9 -> 0.015424229
A32: FE cost | D32: 4.5 | G32: =D32*H9 -> 18234.299 | I32: =G32/$H$9 -> 4.5
A33: TOTAL PROCESS COST OF PC | G33: =SUM(G21:G32) -> 336234.83 | I33: =G33/$H$9 -> 82.97861
A34: TOTAL RM+BOP+PC | G34: =G18+G33 -> 890109.81
A35: OH + Contingency | E35: 0.1 | G35: =G34*E35 -> 89010.981 | I35: =G35/$H$9 -> 21.966812
A36: Total Product Cost Without Profit | G36: =SUM(G34:G35) -> 979120.8 | I36: =G36/H9 -> 241.63494 | K36: =G36/H8 -> 184.81644
H39: Min.
A40: NOTES:- | G40: OTHER COST | H40: Min.
A41: No BOP found in the Drawing Details
A42: Stress relieveing NOT FOUND ON PRINTS, IF REQUIRED | G42: As Actual
A45: NRC COST BREAKUP
A46: Fixture Details | B46: Approx Wt /Days | C46: Rate | D46: Cost
A47: Tacking Fixture main Frame | B47: =C4*0.8 -> 3227.2 | C47: 100 | D47: =B47*C47 -> 322720
A48: Templates | B48: =C4*0.2 -> 806.8 | C48: 100 | D48: =B48*C48 -> 80680
A49: FE COST | B49: =SUM(B47:B48) -> 4034 | C49: 4.5 | D49: =B49*C49 -> 18153
A50: SUB TOTAL | D50: =SUM(D47:D49) -> 421553
A51: Development and Engg | B51: 15 | C51: =75000/30 -> 2500 | D51: =B51*C51 -> 37500
A52: OH + Contingency | C52: 0.0255 | D52: =(D50+D51)*C52 -> 11705.851
A53: Total Cost | D53: =SUM(D50:D52) -> 470758.85 | E53: 470823.59 | F53: =D53-E53 -> -64.738245

Sheet BOM R2D CatWalk
A1: S.No | C1: Level | G1: BOM All RFQ PACKAGE PC4100 | M1: 0.4536 | S1: 25.4 | V1: 0.1 | W1: 0.15 | AC1: 550 | AF1: 0.2 | AI1: 0.15
B2: Assembly | C2: L1 | D2: L2 | E2: L3 | F2: L4 | G2: Drawing No. | H2: Rev | I2: Description | J2: Qty. | K2: Total Qty. | L2: Net Wt. LBS | M2: Net Weight (Kg) | N2: Total Weight (Kg) | O2: Type | P2: DRG. Material | Q2: Alt. Material | R2: IS Thk (Inch) | S2: IS Thk (mm) | T2: Width | U2: Length | V2: Gross Wt (kg) | W2: Cutting Perimeter(M) | X2: Cutting Time | Y2: Cutting Cost | Z2: No. of bends | AA2: Bending Details | AB2: Machining Time (min) | AC2: Machining Cost | AD2: Other Process | AE2: Other process Cost | AF2: Welding Length (M) | AG2: Remarks | AH2: Paint | AI2: Surface Area SQM
C3: 00 | I3: All RFQ PACKAGE PC4100 | N3: =N4+N93+N97+N100+N105+N109+N114+N119+N128+N145+N162+N171+N187 -> 7416.1738 | O3: All | V3: =V4+V93+V97+V100+V105+V109+V114+V119+V128+V145+V162+V171+V187 -> 9171.8161
A4: 1 | B4: AY30013 | C4: 0 | G4: AY30013 | H4: A | I4: WELDMENT, PC4100 R2D SLAVE SKID, PC4100 | J4: =VLOOKUP(G4,'Customer Data '!$B$1:$D$14,3,0) -> 1 | K4: =J4 -> 1 | M4: 4034 | N4: =M4*K4 -> 4034 | O4: Main Assy. | V4: =SUM(V5:V92) -> 4796.4882 | X4: =SUMPRODUCT(X5:X92,$K$5:$K$92) -> 373.86909 | Y4: =SUM(Y5:Y92) -> 0 | Z4: =SUMPRODUCT(Z5:Z92,$K$5:$K$92) -> 9 | AB4: =SUMPRODUCT(AB5:AB92,$K$5:$K$92) -> 238 | AC4: =SUM(AC5:AC92) -> 2181.6667 | AF4: 0 | AI4: =SUM(AI5:AI92) -> 51.842346
A5: 2 | B5: AY30013 | C5: 1A | D5: * | E5: * | G5: AY30012 | I5: WELDMENT, R2D CATWALK, LEV 2, PC4100 | J5: 1 | K5: =J5*$K$4 -> 1 | M5: 3370 | N5: =M5*K5 -> 3370 | O5: Sub Assy. | P5: -
A6: 3 | B6: AY30013 | D6: 1A.1 | G6: AY30011 | H6: A | I6: WELDMENT, R2D CATWALK, LEV 1, PC4100 | J6: 1 | K6: =J6*$K$5 -> 1 | M6: 3208 | N6: =M6*K6 -> 3208 | O6: Sub Assy. | P6: -
A7: 4 | B7: AY30013 | E7: 1A.1.1 | G7: AY30010 | H7: A | I7: WELDMENT, CATWALK ODS BEAM, R2D, PC4100 | J7: 1 | K7: =J7*$K$6 -> 1 | M7: 679 | N7: =M7*K7 -> 679 | O7: Sub Assy. | P7: -
A8: 5 | B8: AY30013 | F8: 1A.1.1.1 | G8: DT34393 | I8: REAR ODS BEAM WEB | J8: 1 | K8: =J8*$K$7 -> 1 | M8: 339 | N8: =M8*K8 -> 339 | O8: Plate | P8: A572 Gr. 50 | Q8: IS 2062 E350 A/BR | S8: 10 | T8: 1022 | U8: 5080 | V8: =S8*T8*U8*0.00000785*(1+$V$1)*K8 -> 448.30848 | W8: =((T8+U8)*2*(1+$W$1))/1000 -> 14.0346 | X8: =W8/1.1 -> 12.758727 | AI8: =(T8*U8*2)/1000000*(1+$AI$1)*K8 -> 11.941048
A9: 6 | B9: AY30013 | F9: 1A.1.1.2 | G9: DT34394 | I9: PLATE, OUTER ODS BEAM TOP FLANGE, R2D, PC4100 | J9: 1 | K9: =J9*$K$7 -> 1 | M9: 76 | N9: =M9*K9 -> 76 | O9: Plate | P9: A572 Gr. 50 | Q9: IS 2062 E350 A/BR | S9: 12 | T9: 180 | U9: 4775 | V9: =S9*T9*U9*0.00000785*(1+$V$1)*K9 -> 89.06139 | W9: =((T9+U9)*2*(1+$W$1))/1000 -> 11.3965 | X9: =W9/1.1 -> 10.360455 | AI9: =(T9*U9*2)/1000000*(1+$AI$1)*K9 -> 1.97685
A10: 7 | B10: AY30013 | F10: 1A.1.1.3 | G10: DT34395 | I10: PLATE, OUTER BEAM BACK ANGLE CAP, PC4100 | J10: 1 | K10: =J10*$K$7 -> 1 | M10: 9 | N10: =M10*K10 -> 9 | O10: Plate | P10: A572 Gr. 50 | Q10: IS 2062 E350 A/BR | S10: 12 | T10: 180 | U10: 572 | V10: =S10*T10*U10*0.00000785*(1+$V$1)*K10 -> 10.668715 | W10: =((T10+U10)*2*(1+$W$1))/1000 -> 1.7296 | X10: =W10/1.1 -> 1.5723636 | AI10: =(T10*U10*2)/1000000*(1+$AI$1)*K10 -> 0.236808
A11: 8 | B11: AY30013 | F11: 1A.1.1.4 | G11: DT34315 | I11: PLATE, OUTER FRONT BEAM NOSE CAP, PC4100 | J11: 1 | K11: =J11*$K$7 -> 1 | M11: 8 | N11: =M11*K11 -> 8 | O11: Plate | P11: A36/S275JR/SA 516 GR.70 | Q11: IS 2062 E250 A/BR | S11: 20 | T11: 200 | U11: 324 | V11: =S11*T11*U11*0.00000785*(1+$V$1)*K11 -> 11.19096 | W11: =((T11+U11)*2*(1+$W$1))/1000 -> 1.2052 | X11: =W11/1.5 -> 0.80346667 | AI11: =(T11*U11*2)/1000000*(1+$AI$1)*K11 -> 0.14904
A12: 9 | B12: AY30013 | F12: 1A.1.1.5 | G12: DT34396 | I12: PLATE, REAR OUTER BEAM ANGLE CAP, PC4100 | J12: 1 | K12: =J12*$K$7 -> 1 | M12: 37 | N12: =M12*K12 -> 37 | O12: Plate | P12: ASTM A572 Gr. 50 / S355JR | Q12: IS 2062 E350 A/BR | S12: 10 | T12: 100 | U12: 4702 | V12: =S12*T12*U12*0.00000785*(1+$V$1)*K12 -> 40.60177 | W12: =((T12+U12)*2*(1+$W$1))/1000 -> 11.0446 | X12: =W12/1.1 -> 10.040545 | AI12: =(T12*U12*2)/1000000*(1+$AI$1)*K12 -> 1.08146
A13: 10 | B13: AY30013 | F13: 1A.1.1.6 | G13: DT34397 | I13: PLATE, ANGLE CAP, PC4100 | J13: 1 | K13: =J13*$K$7 -> 1 | M13: 0.8 | N13: =M13*K13 -> 0.8 | O13: Plate | P13: A572 Gr. 50 | Q13: IS 2062 E350 A/BR | S13: 10 | T13: 100 | U13: 191 | V13: =S13*T13*U13*0.00000785*(1+$V$1)*K13 -> 1.649285 | W13: =((T13+U13)*2*(1+$W$1))/1000 -> 0.6693 | X13: =W13/1.1 -> 0.60845455 | AI13: =(T13*U13*2)/1000000*(1+$AI$1)*K13 -> 0.04393
A14: 11 | B14: AY30013 | F14: 1A.1.1.7 | G14: DT34327 | I14: CATWALK CONNECTION PLATE, PC4100 | J14: 1 | K14: =J14*$K$7 -> 1 | M14: 11.6 | N14: =M14*K14 -> 11.6 | O14: Plate | P14: A36/S275JR/SA 516 GR.70 | Q14: IS 2062 E250 A/BR | S14: 40 | T14: 200 | U14: 200 | V14: =S14*T14*U14*0.00000785*(1+$V$1)*K14 -> 13.816 | W14: =((T14+U14)*2*(1+$W$1))/1000 -> 0.92 | X14: =W14/0.35 -> 2.6285714 | AB14: 10 | AC14: =AB14*($AC$1/60)*K14 -> 91.666667 | AI14: =(T14*U14*2)/1000000*(1+$AI$1)*K14 -> 0.092
A15: 12 | B15: AY30013 | F15: 1A.1.1.8 | G15: DT34328 | I15: PLATE, CARRIER CONNECTION PLATE GUSSET, PC4100 | J15: 1 | K15: =J15*$K$7 -> 1 | M15: 4 | N15: =M15*K15 -> 4 | O15: Plate | P15: A36/S275JR/SA 516 GR.70 | Q15: IS 2062 E250 A/BR | S15: 25 | T15: 165 | U15: 180 | V15: =S15*T15*U15*0.00000785*(1+$V$1)*K15 -> 6.4114875 | W15: =((T15+U15)*2*(1+$W$1))/1000 -> 0.7935 | X15: =W15/1.3 -> 0.61038462 | AI15: =(T15*U15*2)/1000000*(1+$AI$1)*K15 -> 0.06831
A16: 13 | B16: AY30013 | F16: 1A.1.1.9 | G16: DT34378 | I16: PIPE, 33 OD x 21 ID X 51 L | J16: 4 | K16: =J16*$K$7 -> 4 | M16: =0.2*0.4536 -> 0.09072 | N16: =M16*K16 -> 0.36288 | O16: Pipe | P16: ASTM A106 GR.B | Q16: ASTM A106 GR.B | S16: Dia 33.4x 6.35 | U16: 51 | V16: =M16*K16*(1+$V$1) -> 0.399168 | X16: 2
A17: 14 | B17: AY30013 | F17: 1A.1.1.10 | G17: DT34398 | I17: REAR CATWALK CONNECTION BLOCK, PC4100 | J17: 2 | K17: =J17*$K$7 -> 2 | M17: 19 | N17: =M17*K17 -> 38 | O17: Plate | P17: ASTM A572 Gr. 50 / S355JR | Q17: IS 2062 E350 A/BR | S17: 50 | T17: 220 | U17: 334 | V17: =S17*T17*U17*0.00000785*(1+$V$1)*K17 -> 63.44998 | W17: =((T17+U17)*2*(1+$W$1))/1000 -> 1.2742 | X17: =W17/0.32 -> 3.981875 | AB17: 45 | AC17: =AB17*($AC$1/60)*K17 -> 825 | AI17: =(T17*U17*2)/1000000*(1+$AI$1)*K17 -> 0.338008
A18: 15 | B18: AY30013 | F18: 1A.1.1.11 | G18: - | I18: BAR, FLAT, 200 X 20 X 4777 LG | J18: 1 | K18: =J18*$K$7 -> 1 | M18: =S18*T18*U18*0.00000785 -> 149.9978 | N18: =M18*K18 -> 149.9978 | O18: Plate | P18: A36/S275JR/SA 516 GR.70 | Q18: IS 2062 E250 A/BR | S18: 20 | T18: 200 | U18: 4777 | V18: =S18*T18*U18*0.00000785*(1+$V$1)*K18 -> 164.99758 | W18: =((T18+U18)*2*(1+$W$1))/1000 -> 11.4471 | X18: =W18/1.5 -> 7.6314 | AI18: =(T18*U18*2)/1000000*(1+$AI$1)*K18 -> 2.19742
A19: 16 | B19: AY30013 | F19: 1A.1.1.12 | G19: - | I19: BAR, FLAT, 75 x 12 x 381 LG | J19: 2 | K19: =J19*$K$7 -> 2 | M19: =S19*T19*U19*0.00000785 -> 2.691765 | N19: =M19*K19 -> 5.38353 | O19: Plate | P19: A36/S275JR/SA 516 GR.70 | Q19: IS 2062 E250 A/BR | S19: 12 | T19: 75 | U19: 381 | V19: =S19*T19*U19*0.00000785*(1+$V$1)*K19 -> 5.921883 | W19: =((T19+U19)*2*(1+$W$1))/1000 -> 1.0488 | X19: =W19/1.1 -> 0.95345455 | AI19: =(T19*U19*2)/1000000*(1+$AI$1)*K19 -> 0.131445
A20: 17 | B20: AY30013 | E20: 1A.1.2 | G20: AY30009 | I20: WELDMENT, CATWALK DS BEAM, R2D, PC4100 | J20: 1 | K20: =J20*$K$6 -> 1 | M20: 667 | N20: =M20*K20 -> 667 | O20: Sub Assy. | P20: -
A21: 18 | B21: AY30013 | F21: 1A.1.2.1 | G21: DT34400 | I21: REAR DS BEAM WEB, R2D, PC4100 | J21: 1 | K21: =J21*$K$20 -> 1 | M21: 321 | N21: =M21*K21 -> 321 | O21: Plate | P21: A572 Gr. 50 | Q21: IS 2062 E350 A/BR | S21: 10 | T21: 1022 | U21: 5080 | V21: =S21*T21*U21*0.00000785*(1+$V$1)*K21 -> 448.30848 | W21: =((T21+U21)*2*(1+$W$1))/1000 -> 14.0346 | X21: =W21/1.1 -> 12.758727 | AI21: =(T21*U21*2)/1000000*(1+$AI$1)*K21 -> 11.941048
A22: 19 | B22: AY30013 | F22: 1A.1.2.2 | G22: DT34401 | I22: PLATE, OUTER BEAM D5 TOP FLANGE, R2D, PC4100 | J22: 1 | K22: =J22*$K$20 -> 1 | M22: 83 | N22: =M22*K22 -> 83 | O22: Plate | P22: A572 Gr. 50 | Q22: IS 2062 E350 A/BR | S22: 12 | T22: 180 | U22: 4775 | V22: =S22*T22*U22*0.00000785*(1+$V$1)*K22 -> 89.06139 | W22: =((T22+U22)*2*(1+$W$1))/1000 -> 11.3965 | X22: =W22/1.1 -> 10.360455 | AI22: =(T22*U22*2)/1000000*(1+$AI$1)*K22 -> 1.97685
A23: 20 | B23: AY30013 | F23: 1A.1.2.3 | G23: DT34395 | I23: PLATE, OUTER BEAM BACK ANGLE CAP, PC4100 | J23: 1 | K23: =J23*$K$20 -> 1 | M23: 9 | N23: =M23*K23 -> 9 | O23: Plate | P23: A572 Gr. 50 | Q23: IS 2062 E350 A/BR | S23: 12 | T23: 180 | U23: 572 | V23: =S23*T23*U23*0.00000785*(1+$V$1)*K23 -> 10.668715 | W23: =((T23+U23)*2*(1+$W$1))/1000 -> 1.7296 | X23: =W23/1.1 -> 1.5723636 | AI23: =(T23*U23*2)/1000000*(1+$AI$1)*K23 -> 0.236808
A24: 21 | B24: AY30013 | F24: 1A.1.2.4 | G24: DT34315 | I24: PLATE, OUTER FRONT BEAM NOSE CAP, PC4100 | J24: 1 | K24: =J24*$K$20 -> 1 | M24: 8 | N24: =M24*K24 -> 8 | O24: Plate | P24: A36/S275JR/SA 516 GR.70 | Q24: IS 2062 E250 A/BR | S24: 20 | T24: 200 | U24: 324 | V24: =S24*T24*U24*0.00000785*(1+$V$1)*K24 -> 11.19096 | W24: =((T24+U24)*2*(1+$W$1))/1000 -> 1.2052 | X24: =W24/1.5 -> 0.80346667 | AI24: =(T24*U24*2)/1000000*(1+$AI$1)*K24 -> 0.14904
A25: 22 | B25: AY30013 | F25: 1A.1.2.5 | G25: DT34396 | I25: PLATE, REAR OUTER BEAM ANGLE CAP, PC4100 | J25: 1 | K25: =J25*$K$20 -> 1 | M25: 37 | N25: =M25*K25 -> 37 | O25: Plate | P25: ASTM A572 Gr. 50 / S355JR | Q25: IS 2062 E350 A/BR | S25: 10 | T25: 100 | U25: 4702 | V25: =S25*T25*U25*0.00000785*(1+$V$1)*K25 -> 40.60177 | W25: =((T25+U25)*2*(1+$W$1))/1000 -> 11.0446 | X25: =W25/1.1 -> 10.040545 | AI25: =(T25*U25*2)/1000000*(1+$AI$1)*K25 -> 1.08146
A26: 23 | B26: AY30013 | F26: 1A.1.2.6 | G26: DT34397 | I26: PLATE, ANGLE CAP, PC4100 | J26: 1 | K26: =J26*$K$20 -> 1 | M26: 0.8 | N26: =M26*K26 -> 0.8 | O26: Plate | P26: A572 Gr. 50 | Q26: IS 2062 E350 A/BR | S26: 10 | T26: 100 | U26: 191 | V26: =S26*T26*U26*0.00000785*(1+$V$1)*K26 -> 1.649285 | W26: =((T26+U26)*2*(1+$W$1))/1000 -> 0.6693 | X26: =W26/1.1 -> 0.60845455 | AI26: =(T26*U26*2)/1000000*(1+$AI$1)*K26 -> 0.04393
A27: 24 | B27: AY30013 | F27: 1A.1.2.7 | G27: DT34327 | I27: CATWALK CONNECTION PLATE, PC4100 | J27: 1 | K27: =J27*$K$20 -> 1 | M27: 11.6 | N27: =M27*K27 -> 11.6 | O27: Plate | P27: A36/S275JR/SA 516 GR.70 | Q27: IS 2062 E250 A/BR | S27: 40 | T27: 200 | U27: 200 | V27: =S27*T27*U27*0.00000785*(1+$V$1)*K27 -> 13.816 | W27: =((T27+U27)*2*(1+$W$1))/1000 -> 0.92 | X27: =W27/0.35 -> 2.6285714 | AB27: 10 | AC27: =AB27*($AC$1/60)*K27 -> 91.666667 | AI27: =(T27*U27*2)/1000000*(1+$AI$1)*K27 -> 0.092
A28: 25 | B28: AY30013 | F28: 1A.1.2.8 | G28: DT34328 | I28: PLATE, CARRIER CONNECTION PLATE GUSSET, PC4100 | J28: 1 | K28: =J28*$K$20 -> 1 | M28: 4 | N28: =M28*K28 -> 4 | O28: Plate | P28: A36/S275JR/SA 516 GR.70 | Q28: IS 2062 E250 A/BR | S28: 25 | T28: 165 | U28: 180 | V28: =S28*T28*U28*0.00000785*(1+$V$1)*K28 -> 6.4114875 | W28: =((T28+U28)*2*(1+$W$1))/1000 -> 0.7935 | X28: =W28/1.3 -> 0.61038462 | AI28: =(T28*U28*2)/1000000*(1+$AI$1)*K28 -> 0.06831
A29: 26 | B29: AY30013 | F29: 1A.1.2.9 | G29: DT34398 | I29: REAR CATWALK CONNECTION BLOCK, PC4100 | J29: 2 | K29: =J29*$K$20 -> 2 | M29: 19 | N29: =M29*K29 -> 38 | O29: Plate | P29: ASTM A572 Gr. 50 / S355JR | Q29: IS 2062 E350 A/BR | S29: 50 | T29: 220 | U29: 334 | V29: =S29*T29*U29*0.00000785*(1+$V$1)*K29 -> 63.44998 | W29: =((T29+U29)*2*(1+$W$1))/1000 -> 1.2742 | X29: =W29/0.32 -> 3.981875 | AB29: 45 | AC29: =AB29*($AC$1/60)*K29 -> 825 | AI29: =(T29*U29*2)/1000000*(1+$AI$1)*K29 -> 0.338008
A30: 27 | B30: AY30013 | F30: 1A.1.2.10 | G30: - | I30: BAR, FLAT, 200 X 20 X 4777 LG | J30: 1 | K30: =J30*$K$20 -> 1 | M30: =S30*T30*U30*0.00000785 -> 149.9978 | N30: =M30*K30 -> 149.9978 | O30: Plate | P30: A36/S275JR/SA 516 GR.70 | Q30: IS 2062 E250 A/BR | S30: 20 | T30: 200 | U30: 4777 | V30: =S30*T30*U30*0.00000785*(1+$V$1)*K30 -> 164.99758 | W30: =((T30+U30)*2*(1+$W$1))/1000 -> 11.4471 | X30: =W30/1.5 -> 7.6314 | AI30: =(T30*U30*2)/1000000*(1+$AI$1)*K30 -> 2.19742
A31: 28 | B31: AY30013 | F31: 1A.1.2.11 | G31: - | I31: PIPE, 1/2" SCH 40 x 1035 LG | J31: 2 | K31: =J31*$K$20 -> 2 | M31: =1.27*U31/1000 -> 0.131445 | N31: =M31*K31 -> 0.26289 | O31: Pipe | P31: A.S.T.M. A106 GR.B | Q31: ASTM A106 GR.B | S31: Dia 21.3 x 2.77 thk | U31: 103.5 | V31: =M31*K31*(1+$V$1) -> 0.289179 | X31: 2
A32: 29 | B32: AY30013 | F32: 1A.1.2.12 | G32: - | I32: UNISTRUT, 41.3 x 22.2 x 457 LG | J32: 2 | K32: =J32*$K$20 -> 2 | N32: =M32*K32 -> 0 | O32: BOP Unistruct | P32: G40.21-44W / A572 G50 | AE32: =500*K32 -> 1000
A33: 30 | B33: AY30013 | F33: 1A.1.2.13 | G33: DT34399 | I33: PLATE, SAFETY BAR HOLDER, PC4100 | J33: 2 | K33: =J33*$K$20 -> 2 | M33: 2 | N33: =M33*K33 -> 4 | O33: Plate | P33: A572 Gr. 50 | Q33: IS 2062 E350 A/BR | S33: 10 | T33: 210 | U33: 210 | V33: =S33*T33*U33*0.00000785*(1+$V$1)*K33 -> 7.61607 | W33: =((T33+U33)*2*(1+$W$1))/1000 -> 0.966 | X33: =W33/1.1 -> 0.87818182 | AI33: =(T33*U33*2)/1000000*(1+$AI$1)*K33 -> 0.20286
A34: 31 | B34: AY30013 | E34: 1A.1.3 | G34: DT34313 | I34: PLATE, ROLL BAR END CAP, PC4100 | J34: 2 | K34: =J34*$K$6 -> 2 | M34: 3.4 | N34: =M34*K34 -> 6.8 | O34: Plate | P34: A572 Gr. 50 | Q34: IS 2062 E350 A/BR | S34: 12 | T34: 200 | U34: 240 | V34: =S34*T34*U34*0.00000785*(1+$V$1)*K34 -> 9.94752 | W34: =((T34+U34)*2*(1+$W$1))/1000 -> 1.012 | X34: =W34/1.1 -> 0.92 | AI34: =(T34*U34*2)/1000000*(1+$AI$1)*K34 -> 0.2208
A35: 32 | B35: AY30013 | E35: 1A.1.4 | G35: DT34402 | I35: PLATE, BACK MID STOP RIB, PC4100 | J35: 4 | K35: =J35*$K$6 -> 4 | M35: 15 | N35: =M35*K35 -> 60 | O35: Plate | P35: A572 Gr. 50 | Q35: IS 2062 E350 A/BR | S35: 12 | T35: 373 | U35: 789 | V35: =S35*T35*U35*0.00000785*(1+$V$1)*K35 -> 121.98022 | W35: =((T35+U35)*2*(1+$W$1))/1000 -> 2.6726 | X35: =W35/1.1 -> 2.4296364 | AI35: =(T35*U35*2)/1000000*(1+$AI$1)*K35 -> 2.7075324
A36: 33 | B36: AY30013 | E36: 1A.1.5 | G36: DT34403 | I36: PIPE, CABLE ROLL, PC4100 | J36: 2 | K36: =J36*$K$6 -> 2 | M36: 5 | N36: =M36*K36 -> 10 | O36: Sub Assy. | P36: -
A37: 34 | B37: AY30013 | F37: 1A.1.5.1 | I37: PIPE, 4SCH80 X 254 LG | J37: 1 | K37: =J37*$K$36 -> 2 | M37: =M36-M38 -> 4.6516484 | N37: =M37*K37 -> 9.3032968 | O37: Pipe | P37: A.S.T.M. A106 GR.B | Q37: ASTM A106 GR.B | S37: Dia 101.6 x 8.08 thk | U37: 255 | V37: =M37*K37*(1+$V$1) -> 10.233626 | X37: 2 | AB37: 5 | AC37: =AB37*($AC$1/60)*K37 -> 91.666667
A38: 35 | B38: AY30013 | F38: 1A.1.5.2 | I38: PLATE, 86 X 86X 6 | J38: 1 | K38: =J38*$K$36 -> 2 | M38: =S38*T38*U38*0.00000785 -> 0.3483516 | N38: =M38*K38 -> 0.6967032 | O38: Plate | P38: A.S.T.M. A106 GR.B | Q38: IS 2062 E350 A/BR | S38: 6 | T38: 86 | U38: 86 | V38: =S38*T38*U38*0.00000785*(1+$V$1)*K38 -> 0.76637352 | W38: =((T38+U38)*2*(1+$W$1))/1000 -> 0.3956 | X38: =1.5/W38 -> 3.7917088 | AI38: =(T38*U38*2)/1000000*(1+$AI$1)*K38 -> 0.0340216
A39: 36 | B39: AY30013 | E39: 1A.1.6 | G39: DT34404 | I39: W-BEAM 600 X 220 X 4572 LG | J39: 2 | K39: =J39*$K$6 -> 2 | M39: 498 | N39: =M39*K39 -> 996 | O39: Beam | P39: A992 / A572 | Q39: IS 2062 E350 A/BR | S39: NPB 600x 220x 107.57 | U39: 4572 | V39: =107.57*U39/1000*(1+$V$1)*K39 -> 1081.9821 | X39: 6 | AG39: Sail (IS 808:2021 E350)
A40: 37 | B40: AY30013 | E40: 1A.1.7 | G40: DT34405 | I40: CARRIER RAIL BOTTOM STIFFNER, DS, PC4100 UPN80 X 45 | J40: 1 | K40: =J40*$K$6 -> 1 | M40: 3 | N40: =M40*K40 -> 3 | O40: Channel | P40: A36/S275JR | Q40: IS 2062 E250 A/BR | S40: UPN80 X 45 | U40: 410 | V40: =8.64*U40/1000*(1+$V$1)*K40 -> 3.89664 | X40: 2
A41: 38 | B41: AY30013 | E41: 1A.1.8 | G41: DT34406 | I41: CARRIER RAIL BOTTOM STIFFNER, ODS, PC4100 UPN80 X 45 | J41: 1 | K41: =J41*$K$6 -> 1 | M41: 3 | N41: =M41*K41 -> 3 | O41: Channel | P41: A36/S275JR | Q41: IS 2062 E250 A/BR | S41: UPN80 X 45 | U41: 410 | V41: =8.64*U41/1000*(1+$V$1)*K41 -> 3.89664 | X41: 2
A42: 39 | B42: AY30013 | E42: 1A.1.9 | G42: - | I42: CHANNEL, UPN200x2198 LG | J42: 7 | K42: =J42*$K$6 -> 7 | M42: =25.3*U42/1000 -> 55.6094 | N42: =M42*K42 -> 389.2658 | O42: Channel | P42: A572 Gr. 50 | Q42: IS 2062 E350 A/BR | S42: ISMC 200 x 75 | U42: 2198 | V42: =25.3*U42/1000*(1+$V$1)*K42 -> 428.19238 | X42: 3
A43: 40 | B43: AY30013 | E43: 1A.1.10 | G43: DT34390 | I43: PLATE, BOTTOM PLATE, JUNK BOX, PC4100 | J43: 1 | K43: =J43*$K$6 -> 1 | M43: 27.7 | N43: =M43*K43 -> 27.7 | O43: Plate | P43: ASTM A572 Gr. 50 / A516 Gr.70 / S355JR | Q43: IS 2062 E350 A/BR | S43: 6 | T43: 720 | U43: 819 | V43: =S43*T43*U43*0.00000785*(1+$V$1)*K43 -> 30.551321 | W43: =((T43+U43)*2*(1+$W$1))/1000 -> 3.5397 | X43: =1.5/W43 -> 0.42376473 | Z43: 1 | AA43: R6 | AI43: =(T43*U43*2)/1000000*(1+$AI$1)*K43 -> 1.356264
A44: 41 | B44: AY30013 | E44: 1A.1.11 | G44: - | I44: CHANNEL, UPN80.000X 4672.000 LG | J44: 1 | K44: =J44*$K$6 -> 1 | M44: =8.64*U44/1000 -> 40.36608 | N44: =M44*K44 -> 40.36608 | O44: Channel | P44: A36/S275JR | Q44: IS 2062 E250 A/BR | S44: UPN80 X 45 | U44: 4672 | V44: =8.64*U44/1000*(1+$V$1)*K44 -> 44.402688 | X44: 2
A45: 42 | B45: AY30013 | E45: 1A.1.12 | G45: - | I45: CHANNEL, UPN80X1143 LG | J45: 5 | K45: =J45*$K$6 -> 5 | M45: =8.64*U45/1000 -> 9.87552 | N45: =M45*K45 -> 49.3776 | O45: Channel | P45: A36/S275JR | Q45: IS 2062 E250 A/BR | S45: UPN80 X 45 | U45: 1143 | V45: =8.64*U45/1000*(1+$V$1)*K45 -> 54.31536 | X45: 2
A46: 43 | B46: AY30013 | E46: 1A.1.13 | G46: UPN80x4623 | I46: CHANNEL, UPN80.000X4623.000 LG | J46: 1 | K46: =J46*$K$6 -> 1 | M46: =8.64*U46/1000 -> 39.94272 | N46: =M46*K46 -> 39.94272 | O46: Channel | P46: A36/S275JR | Q46: IS 2062 E250 A/BR | S46: UPN80 X 45 | U46: 4623 | V46: =8.64*U46/1000*(1+$V$1)*K46 -> 43.936992 | X46: 2
A47: 44 | B47: AY30013 | E47: 1A.1.14 | G47: FB45X6X329 | I47: BAR, FLAT, 45.000 X 6.000 X 329.406 LG | J47: 1 | K47: =J47*$K$6 -> 1 | M47: =S47*T47*U47*0.00000785 -> 0.6973155 | N47: =M47*K47 -> 0.6973155 | O47: Plate | P47: A36/S275JR/SA 516 GR.70 | Q47: IS 2062 E250 A/BR | S47: 6 | T47: 45 | U47: 329 | V47: =S47*T47*U47*0.00000785*(1+$V$1)*K47 -> 0.76704705 | W47: =((T47+U47)*2*(1+$W$1))/1000 -> 0.8602 | X47: =1.5/W47 -> 1.7437805 | AI47: =(T47*U47*2)/1000000*(1+$AI$1)*K47 -> 0.0340515
A48: 45 | B48: AY30013 | E48: 1A.1.15 | G48: - | I48: PI 6" SCH XS X 2388mm | J48: 1 | K48: =J48*$K$6 -> 1 | M48: =42.56*U48/1000 -> 101.63328 | N48: =M48*K48 -> 101.63328 | O48: Pipe | P48: G40.21-44W | Q48: ASTM A106 GR.B | S48: Dia 168.28 x 10.97thk | U48: 2388 | V48: =M48*K48*(1+$V$1) -> 111.79661 | X48: 3 | AI48: =0.534*U48/1000*K48*(1+$AI$1) -> 1.4664708
A49: 46 | B49: AY30013 | E49: 1A.1.16 | G49: FB45X6X280 | I49: BAR, FLAT, 45.000 X 6.000 X 280.194 LG | J49: 1 | K49: =J49*$K$6 -> 1 | M49: =S49*T49*U49*0.00000785 -> 0.59346 | N49: =M49*K49 -> 0.59346 | O49: Plate | P49: A36/S275JR/SA 516 GR.70 | Q49: IS 2062 E250 A/BR | S49: 6 | T49: 45 | U49: 280 | V49: =S49*T49*U49*0.00000785*(1+$V$1)*K49 -> 0.652806 | W49: =((T49+U49)*2*(1+$W$1))/1000 -> 0.7475 | X49: =1.5/W49 -> 2.006689 | AI49: =(T49*U49*2)/1000000*(1+$AI$1)*K49 -> 0.02898
A50: 47 | B50: AY30013 | E50: 1A.1.17 | G50: DT34389 | I50: PLATE, FRONT LIP, JUNK BOX, PC4100 | J50: 1 | K50: =J50*$K$6 -> 1 | M50: 4.1 | N50: =M50*K50 -> 4.1 | O50: Plate | P50: ASTM A572 Gr. 50 / A516 Gr.70 / S355JR | Q50: IS 2062 E350 A/BR | S50: 6 | T50: 126 | U50: 691 | V50: =S50*T50*U50*0.00000785*(1+$V$1)*K50 -> 4.5108895 | W50: =((T50+U50)*2*(1+$W$1))/1000 -> 1.8791 | X50: =1.5/W50 -> 0.79825448 | Z50: 1 | AA50: Die Bending | AI50: =(T50*U50*2)/1000000*(1+$AI$1)*K50 -> 0.2002518
A51: 48 | B51: AY30013 | E51: 1A.1.18 | G51: UPN80X1651 | I51: CHANNEL, UPN80.000 LG | J51: 1 | K51: =J51*$K$6 -> 1 | M51: =8.64*U51/1000 -> 14.26464 | N51: =M51*K51 -> 14.26464 | O51: Channel | P51: A36/S275JR | Q51: IS 2062 E250 A/BR | S51: UPN80 X 45 | U51: 1651 | V51: =8.64*U51/1000*(1+$V$1)*K51 -> 15.691104 | X51: 2
A52: 49 | B52: AY30013 | E52: 1A.1.19 | G52: FB80X6X4634 | I52: BAR, FLAT, 80.000 X 6.000 X 4634.000 LG | J52: 1 | K52: =J52*$K$6 -> 1 | M52: =S52*T52*U52*0.00000785 -> 17.460912 | N52: =M52*K52 -> 17.460912 | O52: Plate | P52: A36/S275JR/SA 516 GR.70 | Q52: IS 2062 E250 A/BR | S52: 6 | T52: 80 | U52: 4634 | V52: =S52*T52*U52*0.00000785*(1+$V$1)*K52 -> 19.207003 | W52: =((T52+U52)*2*(1+$W$1))/1000 -> 10.8422 | X52: =1.5/W52 -> 0.13834831 | AI52: =(T52*U52*2)/1000000*(1+$AI$1)*K52 -> 0.852656
A53: 50 | B53: AY30013 | E53: 1A.1.20 | G53: FB80X6X4585 | I53: BAR, FLAT, 80.000 X 6.000 X 4585.000 LG | J53: 1 | K53: =J53*$K$6 -> 1 | M53: =S53*T53*U53*0.00000785 -> 17.27628 | N53: =M53*K53 -> 17.27628 | O53: Plate | P53: A36/S275JR/SA 516 GR.70 | Q53: IS 2062 E250 A/BR | S53: 6 | T53: 80 | U53: 4585 | V53: =S53*T53*U53*0.00000785*(1+$V$1)*K53 -> 19.003908 | W53: =((T53+U53)*2*(1+$W$1))/1000 -> 10.7295 | X53: =1.5/W53 -> 0.13980148 | AI53: =(T53*U53*2)/1000000*(1+$AI$1)*K53 -> 0.84364
A54: 51 | B54: AY30013 | E54: 1A.1.21 | G54: AY30006.002 | I54: BAR, FLAT, 5 X 38 X 67 LG | J54: 2 | K54: =J54*$K$6 -> 2 | M54: =S54*T54*U54*0.00000785 -> 0.0999305 | N54: =M54*K54 -> 0.199861 | O54: Plate | P54: A36/S275JR/SA 516 GR.70 | Q54: IS 2062 E250 A/BR | S54: 5 | T54: 38 | U54: 67 | V54: =S54*T54*U54*0.00000785*(1+$V$1)*K54 -> 0.2198471 | W54: =((T54+U54)*2*(1+$W$1))/1000 -> 0.2415 | X54: =1.5/W54 -> 6.2111801 | AI54: =(T54*U54*2)/1000000*(1+$AI$1)*K54 -> 0.0117116
A55: 52 | B55: AY30013 | E55: 1A.1.22 | G55: DT34392 | I55: PLATE, LEFT SIDE WALL, JUNK BOX, PC4100 | J55: 1 | K55: =J55*$K$6 -> 1 | M55: 28.6 | N55: =M55*K55 -> 28.6 | O55: Plate | P55: ASTM A572 Gr. 50 / A516 Gr.70 / S355JR | Q55: IS 2062 E350 A/BR | S55: 6 | T55: 630 | U55: 967 | V55: =S55*T55*U55*0.00000785*(1+$V$1)*K55 -> 31.56317 | W55: =((T55+U55)*2*(1+$W$1))/1000 -> 3.6731 | X55: =1.5/W55 -> 0.4083744 | Z55: 3 | AA55: R6 | AI55: =(T55*U55*2)/1000000*(1+$AI$1)*K55 -> 1.401183
A56: 53 | B56: AY30013 | E56: 1A.1.23 | G56: DT34391 | I56: PLATE, BACK LIP, JUNK BOX, PC4100 | J56: 1 | K56: =J56*$K$6 -> 1 | M56: 4 | N56: =M56*K56 -> 4 | O56: Plate | P56: ASTM A572 Gr. 50 / A516 Gr.70 / S355JR | Q56: IS 2062 E350 A/BR | S56: 6 | T56: 119 | U56: 691 | V56: =S56*T56*U56*0.00000785*(1+$V$1)*K56 -> 4.2602845 | W56: =((T56+U56)*2*(1+$W$1))/1000 -> 1.863 | X56: =1.5/W56 -> 0.80515298 | Z56: 2 | AA56: R6 | AI56: =(T56*U56*2)/1000000*(1+$AI$1)*K56 -> 0.1891267
A57: 54 | B57: AY30013 | E57: 1A.1.24 | G57: DT34388 | I57: PLATE, RIGHT SIDE WALL, JUNK BOX, PC4100 | J57: 1 | K57: =J57*$K$6 -> 1 | M57: 23 | N57: =M57*K57 -> 23 | O57: Plate | P57: ASTM A572 Gr. 50 / A516 Gr.70 / S355JR | Q57: IS 2062 E350 A/BR | S57: 6 | T57: 630 | U57: 802 | V57: =S57*T57*U57*0.00000785*(1+$V$1)*K57 -> 26.177521 | W57: =((T57+U57)*2*(1+$W$1))/1000 -> 3.2936 | X57: =1.5/W57 -> 0.45542871 | AI57: =(T57*U57*2)/1000000*(1+$AI$1)*K57 -> 1.162098
A58: 55 | B58: AY30013 | E58: 1A.1.25 | G58: DT34387 | I58: PLATE, BOTTOM PLATE, JUNK BOX, PC4100 | J58: 1 | K58: =J58*$K$6 -> 1 | M58: 9 | N58: =M58*K58 -> 9 | O58: Plate | P58: ASTM A572 Gr. 50 / A516 Gr.70 / S355JR | Q58: IS 2062 E350 A/BR | S58: 6 | T58: 365.13 | U58: 526.8 | V58: =S58*T58*U58*0.00000785*(1+$V$1)*K58 -> 9.9656786 | W58: =((T58+U58)*2*(1+$W$1))/1000 -> 2.051439 | X58: =1.5/W58 -> 0.73119405 | AI58: =(T58*U58*2)/1000000*(1+$AI$1)*K58 -> 0.44240611
A59: 56 | B59: AY30013 | E59: 1A.1.26 | G59: M11504 | I59: FLANGE, SCULLY, 3/4" NPT | J59: 1 | K59: =J59*$K$6 -> 1 | N59: =M59*K59 -> 0 | O59: BOP | P59: CARBON STEEL | AE59: =1000*K59 -> 1000
A60: 57 | B60: AY30013 | E60: 1A.1.27 | G60: DT34314 | I60: PLATE, CROSS CHANNEL GUSSET, PC4100 | J60: 10 | K60: =J60*$K$6 -> 10 | M60: 1.8 | N60: =M60*K60 -> 18 | O60: Plate | P60: A572 Gr. 50 | Q60: IS 2062 E350 A/BR | S60: 10 | T60: 100 | U60: 254 | V60: =S60*T60*U60*0.00000785*(1+$V$1)*K60 -> 21.9329 | W60: =((T60+U60)*2*(1+$W$1))/1000 -> 0.8142 | X60: =W60/1.1 -> 0.74018182 | AI60: =(T60*U60*2)/1000000*(1+$AI$1)*K60 -> 0.5842
A61: 58 | B61: AY30013 | D61: 1A.2 | G61: DT34325 | I61: PLATE, ROLL SUPPORT, PC4100 | J61: 4 | K61: =J61*$K$5 -> 4 | M61: 2 | N61: =M61*K61 -> 8 | O61: Plate | P61: A572 Gr. 50 | Q61: IS 2062 E350 A/BR | S61: 10 | T61: 200 | U61: 200 | V61: =S61*T61*U61*0.00000785*(1+$V$1)*K61 -> 13.816 | W61: =((T61+U61)*2*(1+$W$1))/1000 -> 0.92 | X61: =W61/1.1 -> 0.83636364 | AI61: =(T61*U61*2)/1000000*(1+$AI$1)*K61 -> 0.368
A62: 59 | B62: AY30013 | D62: 1A.3 | G62: DT34333 | I62: MID FLOOR HANGER FRONT, PC4100 | J62: 7 | K62: =J62*$K$5 -> 7 | M62: 5 | N62: =M62*K62 -> 35 | O62: Plate | P62: A572 Gr. 50 | Q62: IS 2062 E350 A/BR | S62: 10 | T62: 113 | U62: 745 | V62: =S62*T62*U62*0.00000785*(1+$V$1)*K62 -> 50.885623 | W62: =((T62+U62)*2*(1+$W$1))/1000 -> 1.9734 | X62: =W62/1.1 -> 1.794 | AI62: =(T62*U62*2)/1000000*(1+$AI$1)*K62 -> 1.3553785
A63: 60 | B63: AY30013 | D63: 1A.4 | G63: DT34386 | I63: FLOOR, WIDE HANGER, PC4100 | J63: 2 | K63: =J63*$K$5 -> 2 | M63: 17 | N63: =M63*K63 -> 34 | O63: Plate | P63: A36 / S275JR / SA 516 GR.70 | Q63: IS 2062 E250 A/BR | S63: 40 | T63: 87 | U63: 813 | V63: =S63*T63*U63*0.00000785*(1+$V$1)*K63 -> 48.860975 | W63: =((T63+U63)*2*(1+$W$1))/1000 -> 2.07 | X63: =W63/0.35 -> 5.9142857 | AI63: =(T63*U63*2)/1000000*(1+$AI$1)*K63 -> 0.3253626
A64: 61 | B64: AY30013 | D64: 1A.5 | G64: DT34385 | I64: HSS, HORIZONTAL ALIGNER, PC4100 | J64: 2 | K64: =J64*$K$5 -> 2 | M64: 11 | N64: =M64*K64 -> 22 | O64: Sub Assy. | P64: -
A65: 62 | B65: AY30013 | E65: 1A.5.1 | I65: HSS, 80 X 80 X 10 LG | J65: 1 | K65: =J65*$K$64 -> 2 | M65: =21.98*U65/1000 -> 13.4078 | N65: =M65*K65 -> 26.8156 | O65: Sq. Tube | P65: A36/S275JR | Q65: YST 310 | S65: 80x80x 10thk | U65: 610 | V65: =M65*K65*(1+$V$1) -> 29.49716 | X65: 3
A66: 63 | B66: AY30013 | E66: 1A.5.2 | I66: PLATE, 97X60X6 | J66: 2 | K66: =J66*$K$64 -> 4 | M66: =S66*T66*U66*0.00000785 -> 0.274122 | N66: =M66*K66 -> 1.096488 | O66: Plate | P66: ASTM A572 Gr. 50 / A516 Gr.70 / S355JR | Q66: IS 2062 E350 A/BR | S66: 6 | T66: 60 | U66: 97 | V66: =S66*T66*U66*0.00000785*(1+$V$1)*K66 -> 1.2061368 | W66: =((T66+U66)*2*(1+$W$1))/1000 -> 0.3611 | X66: =1.5/W66 -> 4.153974 | AI66: =(T66*U66*2)/1000000*(1+$AI$1)*K66 -> 0.053544
A67: 64 | B67: AY30013 | D67: 1A.6 | G67: — | I67: BAR, FLAT, 51 X 25 X 400 LG | J67: 2 | K67: =J67*$K$5 -> 2 | M67: =S67*T67*U67*0.00000785 -> 4.0035 | N67: =M67*K67 -> 8.007 | O67: Plate | P67: A36 / S275JR / SA 516 GR.70 | Q67: IS 2062 E250 A/BR | S67: 25 | T67: 51 | U67: 400 | V67: =S67*T67*U67*0.00000785*(1+$V$1)*K67 -> 8.8077 | W67: =((T67+U67)*2*(1+$W$1))/1000 -> 1.0373 | X67: =W67/1.3 -> 0.79792308 | AI67: =(T67*U67*2)/1000000*(1+$AI$1)*K67 -> 0.09384
A68: 65 | B68: AY30013 | D68: 1A.7 | G68: — | I68: PIPE, 4 SCH 80 X 628 LG | J68: 2 | K68: =J68*$K$5 -> 2 | M68: =22.33*U68/1000 -> 14.02324 | N68: =M68*K68 -> 28.04648 | O68: Pipe | P68: ASTM A106 GR.B | Q68: ASTM A106 GR.B | S68: Dia 114.3 x 8.56 thk | U68: 628 | V68: =M68*K68*(1+$V$1) -> 30.851128 | X68: 3
A69: 66 | B69: AY30013 | D69: 1A.8 | G69: — | I69: UNISTRUCT, 41 X 22 X 368 LG | J69: 2 | K69: =J69*$K$5 -> 2 | N69: =M69*K69 -> 0 | O69: BOP Unistruct | P69: ASTM A572 Gr. 50 / S355JR | AE69: =500*K69 -> 1000
A70: 67 | B70: AY30013 | D70: 1A.9 | G70: DT34360 | I70: FLOOR, WIDE HANGER, PC4100 | J70: 2 | K70: =J70*$K$5 -> 2 | M70: 16 | N70: =M70*K70 -> 32 | O70: Plate | P70: A36 / S275JR / SA 516 GR.70 | Q70: IS 2062 E250 A/BR | S70: 40 | T70: 112 | U70: 813 | V70: =S70*T70*U70*0.00000785*(1+$V$1)*K70 -> 62.901485 | W70: =((T70+U70)*2*(1+$W$1))/1000 -> 2.1275 | X70: =W70/0.35 -> 6.0785714 | AI70: =(T70*U70*2)/1000000*(1+$AI$1)*K70 -> 0.4188576
A71: 68 | B71: AY30013 | C71: 1B | G71: DT34384 | I71: WELDMENT, PANEL GUARD, PC4100 | J71: 1 | K71: =J71*$K$4 -> 1 | M71: 20.45 | N71: =M71*K71 -> 20.45 | O71: Sub Assy. | P71: -
A72: 69 | B72: AY30013 | D72: 1B.1 | I72: HSS, 50 X 50 X 5 X 184 LG | J72: 4 | K72: =J72*$K$71 -> 4 | M72: =7.07*U72/1000 -> 1.30088 | N72: =M72*K72 -> 5.20352 | O72: Sq. Tube | P72: ASTM A516 Gr. 70/S275JR | Q72: YST 310 | S72: 50x50x 5thk | U72: 184 | V72: =M72*K72*(1+$V$1) -> 5.723872 | X72: 2 | AG72: Apollo
A73: 70 | B73: AY30013 | D73: 1B.2 | I73: HSS, 50 X 50 X 5 X 558 LG | J73: 2 | K73: =J73*$K$71 -> 2 | M73: =7.07*U73/1000 -> 3.94506 | N73: =M73*K73 -> 7.89012 | O73: Sq. Tube | P73: ASTM A516 Gr. 70/S275JR | Q73: YST 310 | S73: 50x50x 5thk | U73: 558 | V73: =M73*K73*(1+$V$1) -> 8.679132 | X73: 2 | AB73: 2 | AC73: =AB73*($AC$1/60)*K73 -> 36.666667 | AG73: Apollo
A74: 71 | B74: AY30013 | D74: 1B.3 | I74: HSS, 50 X 50 X 5 X 520 LG | J74: 2 | K74: =J74*$K$71 -> 2 | M74: =7.07*U74/1000 -> 3.6764 | N74: =M74*K74 -> 7.3528 | O74: Sq. Tube | P74: ASTM A516 Gr. 70/S275JR | Q74: YST 310 | S74: 50x50x 5thk | U74: 520 | V74: =M74*K74*(1+$V$1) -> 8.08808 | X74: 2 | AB74: 2 | AC74: =AB74*($AC$1/60)*K74 -> 36.666667 | AG74: Apollo
A75: 72 | B75: AY30013 | C75: 1C | G75: DT34383 | I75: PLATE, SLAVE SKID CHANNEL CAP, PC4100 | J75: 2 | K75: =J75*$K$4 -> 2 | M75: 6.7 | N75: =M75*K75 -> 13.4 | O75: Plate | P75: A572 Gr. 50 | Q75: IS 2062 E350 A/BR | S75: 10 | T75: 121 | U75: 708 | V75: =S75*T75*U75*0.00000785*(1+$V$1)*K75 -> 14.794864 | W75: =((T75+U75)*2*(1+$W$1))/1000 -> 1.9067 | X75: =W75/1.1 -> 1.7333636 | AI75: =(T75*U75*2)/1000000*(1+$AI$1)*K75 -> 0.3940728
A76: 73 | B76: AY30013 | C76: 1D | G76: DT34381 | I76: HSS, RIGHT SIDE LASER POST, PC4100 | J76: 1 | K76: =J76*$K$4 -> 1 | M76: 10 | N76: =M76*K76 -> 10 | O76: Sub Assy. | P76: -
A77: 74 | B77: AY30013 | D77: 1D.1 | I77: PLATE, 116X76X6 | J77: 1 | K77: =J77*$K$76 -> 1 | M77: =S77*T77*U77*0.00000785 -> 0.4152336 | N77: =M77*K77 -> 0.4152336 | O77: Plate | P77: ASTM A572 Gr. 50 / A516 Gr.70 / S355JR | Q77: IS 2062 E350 A/BR | S77: 6 | T77: 76 | U77: 116 | V77: =S77*T77*U77*0.00000785*(1+$V$1)*K77 -> 0.45675696 | W77: =((T77+U77)*2*(1+$W$1))/1000 -> 0.4416 | X77: =1.5/W77 -> 3.3967391 | AI77: =(T77*U77*2)/1000000*(1+$AI$1)*K77 -> 0.0202768
A78: 75 | B78: AY30013 | D78: 1D.2 | I78: HSS,100 X 80 X 5X 864 LG | J78: 1 | K78: =J78*$K$76 -> 1 | M78: =13.35*U78/1000 -> 11.5344 | N78: =M78*K78 -> 11.5344 | O78: Rec. Tube | P78: A36 / S275JR | Q78: YST 310 | S78: 100x80x 5thk | U78: 864 | V78: =M78*K78*(1+$V$1) -> 12.68784 | X78: 3 | AB78: 10 | AC78: =AB78*($AC$1/60)*K78 -> 91.666667
A79: 76 | B79: AY30013 | C79: 1E | G79: DT34382 | I79: HSS, LEFT SIDE LASER POST, PC4100 | J79: 1 | K79: =J79*$K$4 -> 1 | M79: 10 | N79: =M79*K79 -> 10 | O79: Sub Assy. | P79: -
A80: 77 | B80: AY30013 | D80: 1E.1 | I80: PLATE, 116X76X6 | J80: 1 | K80: =J80*$K$79 -> 1 | M80: =S80*T80*U80*0.00000785 -> 0.4152336 | N80: =M80*K80 -> 0.4152336 | O80: Plate | P80: ASTM A572 Gr. 50 / A516 Gr.70 / S355JR | Q80: IS 2062 E350 A/BR | S80: 6 | T80: 76 | U80: 116 | V80: =S80*T80*U80*0.00000785*(1+$V$1)*K80 -> 0.45675696 | W80: =((T80+U80)*2*(1+$W$1))/1000 -> 0.4416 | X80: =1.5/W80 -> 3.3967391 | AI80: =(T80*U80*2)/1000000*(1+$AI$1)*K80 -> 0.0202768
A81: 78 | B81: AY30013 | D81: 1E.2 | I81: HSS,100 X 80 X 5X 864 LG | J81: 1 | K81: =J81*$K$79 -> 1 | M81: =13.35*U81/1000 -> 11.5344 | N81: =M81*K81 -> 11.5344 | O81: Rec. Tube | P81: A36 / S275JR | Q81: YST 310 | S81: 100x80x 5thk | U81: 864 | V81: =M81*K81*(1+$V$1) -> 12.68784 | X81: 3 | AB81: 10 | AC81: =AB81*($AC$1/60)*K81 -> 91.666667
A82: 79 | B82: AY30013 | C82: 1F | G82: — | I82: CHANNEL, UPN200 X 464 LG | J82: 3 | K82: =J82*$K$4 -> 3 | M82: =25.3*U82/1000 -> 11.7392 | N82: =M82*K82 -> 35.2176 | O82: Channel | P82: A572 Gr. 50 | Q82: IS 2062 E350 A/BR | S82: ISMC 200 x 75 | U82: 464 | V82: =25.3*U82/1000*(1+$V$1)*K82 -> 38.73936 | X82: 3
A83: 80 | B83: AY30013 | C83: 1G | G83: — | I83: CHANNEL, UPN200 X 4321.175 LG | J83: 3 | K83: =J83*$K$4 -> 3 | M83: =25.3*U83/1000 -> 109.3466 | N83: =M83*K83 -> 328.0398 | O83: Channel | P83: A572 Gr. 50 | Q83: IS 2062 E350 A/BR | S83: ISMC 200 x 75 | U83: 4322 | V83: =25.3*U83/1000*(1+$V$1)*K83 -> 360.84378 | X83: 3
A84: 81 | B84: AY30013 | C84: 1H | G84: — | I84: BAR, FLAT, 30 X 10 X 622 LG | J84: 4 | K84: =J84*$K$4 -> 4 | M84: =S84*T84*U84*0.00000785 -> 1.46481 | N84: =M84*K84 -> 5.85924 | O84: Plate | P84: A572 Gr. 50 | Q84: IS 2062 E350 A/BR | S84: 10 | T84: 30 | U84: 622 | V84: =S84*T84*U84*0.00000785*(1+$V$1)*K84 -> 6.445164 | W84: =((T84+U84)*2*(1+$W$1))/1000 -> 1.4996 | X84: =W84/1.1 -> 1.3632727 | AI84: =(T84*U84*2)/1000000*(1+$AI$1)*K84 -> 0.171672
A85: 82 | B85: AY30013 | C85: 1I | G85: — | I85: COUPLING, HALF, 3/4" NPT | J85: 5 | K85: =J85*$K$4 -> 5 | M85: 0.1 | N85: =M85*K85 -> 0.5 | O85: BOP | P85: — | AE85: =1000*K85 -> 5000
A86: 83 | B86: AY30013 | C86: 1J | G86: — | I86: CHANNEL, UPN200 X 3025 LG | J86: 3 | K86: =J86*$K$4 -> 3 | M86: =25.3*U86/1000 -> 76.5325 | N86: =M86*K86 -> 229.5975 | O86: Channel | P86: A572 Gr. 50 | Q86: IS 2062 E350 A/BR | S86: ISMC 200 x 75 | U86: 3025 | V86: =25.3*U86/1000*(1+$V$1)*K86 -> 252.55725 | X86: 3
A87: 84 | B87: AY30013 | C87: 1K | G87: AY30014 | I87: WELDMENT, HINGED FLOOR MNT, PC4100 | J87: 1 | K87: =J87*$K$4 -> 1 | M87: 11 | N87: =M87*K87 -> 11 | O87: Sub Assy. | P87: -
A88: 85 | B88: AY30013 | D88: 1K.1 | G88: DT34373 | I88: PLATE, HINGED FLOOR FORMING CAP, PC4100 | J88: 2 | K88: =J88*$K$87 -> 2 | M88: 1 | N88: =M88*K88 -> 2 | O88: Plate | P88: A572 Gr. 50 | Q88: IS 2062 E350 A/BR | S88: 10 | T88: 83 | U88: 119 | V88: =S88*T88*U88*0.00000785*(1+$V$1)*K88 -> 1.7057579 | W88: =((T88+U88)*2*(1+$W$1))/1000 -> 0.4646 | X88: =W88/1.1 -> 0.42236364 | AI88: =(T88*U88*2)/1000000*(1+$AI$1)*K88 -> 0.0454342
A89: 86 | B89: AY30013 | D89: 1K.2 | G89: DT34374 | I89: PLATE, HINGED FLOOR MNT, PC4100 | J89: 2 | K89: =J89*$K$87 -> 2 | M89: 1 | N89: =M89*K89 -> 2 | O89: Plate | P89: A572 Gr. 50 | Q89: IS 2062 E350 A/BR | S89: 10 | T89: 75 | U89: 119 | V89: =S89*T89*U89*0.00000785*(1+$V$1)*K89 -> 1.5413475 | W89: =((T89+U89)*2*(1+$W$1))/1000 -> 0.4462 | X89: =W89/1.1 -> 0.40563636 | AI89: =(T89*U89*2)/1000000*(1+$AI$1)*K89 -> 0.041055
A90: 87 | B90: AY30013 | D90: 1K.3 | G90: DT34339 | I90: PLATE, HINGE FLOOR MOUNT SHORT, PC4100 | J90: 2 | K90: =J90*$K$87 -> 2 | M90: =S90*T90*U90*0.00000785 -> 0.25905 | N90: =M90*K90 -> 0.5181 | O90: Plate | P90: A572 Gr. 50 | Q90: IS 2062 E350 A/BR | S90: 10 | T90: 44 | U90: 75 | V90: =S90*T90*U90*0.00000785*(1+$V$1)*K90 -> 0.56991 | W90: =((T90+U90)*2*(1+$W$1))/1000 -> 0.2737 | X90: =W90/1.1 -> 0.24881818 | AI90: =(T90*U90*2)/1000000*(1+$AI$1)*K90 -> 0.01518
A91: 88 | B91: AY30013 | D91: 1K.4 | G91: DT34366 | I91: BAR, RD, 12 x 25 LG, PC4100 | J91: 2 | K91: =J91*$K$87 -> 2 | M91: 0.02 | N91: =M91*K91 -> 0.04 | O91: Rod | P91: A36/275JR | Q91: IS 2062 E250 A/BR | S91: Dia 12 | U91: 25 | V91: =5.33*U91/1000*(1+$V$1)*K91 -> 0.29315 | X91: 2 | AI91: =(3.14*12*U91/1000000*K91)*(+$AI$1) -> 0.0002826
A92: 89 | B92: AY30013 | D92: 1K.5 | G92: DT34379 | I92: PLATE, 6 x 232 x 749, PC4100 | J92: 1 | K92: =J92*$K$87 -> 1 | M92: 8 | N92: =M92*K92 -> 8 | O92: Plate | P92: ASTM A572 Gr. 50 /A516 Gr.70/S355JR | Q92: IS 2062 E350 A/BR | S92: 6 | T92: 232 | U92: 749 | V92: =S92*T92*U92*0.00000785*(1+$V$1)*K92 -> 9.0029201 | W92: =((T92+U92)*2*(1+$W$1))/1000 -> 2.2563 | X92: =1.5/W92 -> 0.66480521 | Z92: 2 | AA92: R6 | AI92: =(T92*U92*2)/1000000*(1+$AI$1)*K92 -> 0.3996664
A93: 1 | B93: =G93 -> AY30017 | C93: 2 | G93: AY30017 | H93: A | I93: WELDMENT, FALSE FLOOR, PC4100 | J93: =VLOOKUP(G93,'Customer Data '!$B$1:$D$14,3,0) -> 2 | K93: =J93 -> 2 | M93: 65 | N93: =M93*K93 -> 130 | O93: Main Assy. | V93: =SUM(V94:V96) -> 149.49659 | X93: =SUMPRODUCT(X94:X96,$K$94:$K$96) -> 25.102121 | Y93: =SUM(Y94:Y96) -> 0 | Z93: =SUMPRODUCT(Z94:Z96,$K$94:$K$96) -> 0 | AB93: =SUMPRODUCT(AB94:AB96,$K$94:$K$96) -> 0 | AC93: =SUM(AC94:AC96) -> 0 | AD93: STAMP | AF93: =((2000)+(650*4))*(1+$AF$1)/1000*K93 -> 11.04 | AI93: =SUM(AI94:AI96) -> 2.3088964
A94: 2 | B94: AY30017 | D94: 2.1 | I94: UPN200 X 740 LG | J94: 3 | K94: =J94*$K$93 -> 6 | M94: =25.3*U94/1000 -> 18.722 | N94: =M94*K94 -> 112.332 | O94: Channel | P94: A572 Gr. 50 | Q94: IS 2062 E350 A/BR | S94: ISMC 200 x 75 | U94: 740 | V94: =25.3*U94/1000*(1+$V$1)*K94 -> 123.5652 | X94: 3 | AG94: JSPL | AI94: =0.3516*(U94/1000)*K94*(1+$AI$1) -> 1.7952696
A95: 3 | B95: AY30017 | D95: 2.2 | G95: DT34447 | I95: POSITIONING CAP. FALSE FLOOR | J95: 2 | K95: =J95*$K$93 -> 4 | M95: 3 | N95: =M95*K95 -> 12 | O95: Plate | P95: ASTM A516 Gr. 70/S275JR | Q95: IS 2062 E250 A/BR | S95: 16 | T95: 51 | U95: 629 | V95: =S95*T95*U95*0.00000785*(1+$V$1)*K95 -> 17.728139 | W95: =((T95+U95)*2*(1+$W$1))/1000 -> 1.564 | X95: =W95/1.5 -> 1.0426667 | AI95: =(T95*U95*2)/1000000*(1+$AI$1)*K95 -> 0.2951268
A96: 4 | B96: AY30017 | D96: 2.3 | G96: DT34448 | I96: RIB, FALSE FLOOR, PC4100 | J96: 1 | K96: =J96*$K$93 -> 2 | M96: 3 | N96: =M96*K96 -> 6 | O96: Plate | P96: ASTM A516 Gr. 70/S275JR | Q96: IS 2062 E250 A/BR | S96: 10 | T96: 76 | U96: 625 | V96: =S96*T96*U96*0.00000785*(1+$V$1)*K96 -> 8.20325 | W96: =((T96+U96)*2*(1+$W$1))/1000 -> 1.6123 | X96: =W96/1.1 -> 1.4657273 | AI96: =(T96*U96*2)/1000000*(1+$AI$1)*K96 -> 0.2185
A97: 1 | B97: AY30018 | C97: 3 | G97: AY30018 | H97: A | I97: WELDMENT, HINGED FLOOR, PC4100 | J97: =VLOOKUP(G97,'Customer Data '!$B$1:$D$14,3,0) -> 1 | K97: =J97 -> 1 | M97: 27 | N97: =M97*K97 -> 27 | O97: Main Assy. | V97: =SUM(V98:V99) -> 29.666872 | X97: =SUMPRODUCT(X98:X99,$K$98:$K$99) -> 1.1326886 | Y97: =SUM(Y98:Y99) -> 0 | Z97: =SUMPRODUCT(Z98:Z99,$K$98:$K$99) -> 4 | AB97: =SUMPRODUCT(AB98:AB99,$K$98:$K$99) -> 0 | AC97: =SUM(AC98:AC99) -> 0 | AD97: STAMP | AF97: =((50*4)+(42*4))*(1+$AF$1)/1000*K97 -> 0.4416 | AI97: =SUM(AI98:AI99) -> 1.2501494
A98: 2 | B98: AY30018 | D98: 3.1 | G98: DT34407 | I98: PLATE 6 X 622 X854, PC4100 | J98: 1 | K98: =J98*$K$97 -> 1 | M98: 26 | N98: =M98*K98 -> 26 | O98: Plate | P98: ASTM A572 GR.50/S355JR | Q98: IS 2062 E350 A/BR | S98: 6 | T98: 622 | U98: 854 | V98: =N98*(1+V1) -> 28.6 | W98: =((T98+U98)*2*(1+$W$1))/1000 -> 3.3948 | X98: =1.5/W98 -> 0.44185224 | Z98: 4 | AA98: R11 | AI98: =(T98*U98*2)/1000000*(1+$AI$1)*K98 -> 1.2217324
A99: 3 | B99: AY30018 | D99: 3.2 | G99: DT34380 | I99: PLATE, HINGED FLOOR CONNECTION, PC4100 | J99: 2 | K99: =J99*$K$97 -> 2 | M99: 0.4 | N99: =M99*K99 -> 0.8 | O99: Plate | P99: A572 Gr. 50 | Q99: IS 2062 E350 A/BR | S99: 10 | T99: 57.2 | U99: 108 | V99: =S99*T99*U99*0.00000785*(1+$V$1)*K99 -> 1.0668715 | W99: =((T99+U99)*2*(1+$W$1))/1000 -> 0.37996 | X99: =W99/1.1 -> 0.34541818 | AI99: =(T99*U99*2)/1000000*(1+$AI$1)*K99 -> 0.02841696
A100: 1 | B100: AY30027 | C100: 4 | G100: AY30027 | H100: A | I100: WELDMENT, HINGED FLOOR, PC4100 | J100: =VLOOKUP(G100,'Customer Data '!$B$1:$D$14,3,0) -> 23 | K100: =J100 -> 23 | M100: 19.8 | N100: =M100*K100 -> 455.4 | O100: Main Assy. | V100: =SUM(V101:V104) -> 490.53806 | X100: =SUMPRODUCT(X101:X104,$K$7:$K$10) -> 3.199351 | Y100: =SUM(Y101:Y104) -> 0 | Z100: =SUMPRODUCT(Z101:Z104,$K$101:$K$104) -> 92 | AB100: =SUMPRODUCT(AB101:AB104,$K$7:$K$10) -> 0 | AC100: =SUM(AC101:AC104) -> 0 | AD100: STAMP | AF100: =((50*4)+(42*4)+(724+355))/1000*(1+$AF$1)*K100 -> 39.9372 | AI100: =SUM(AI101:AI104) -> 20.683276
...

Sheet RM Details
A1: Assy No | H1: =P1 -> AY30013 | O1: Assembly | P1: AY30013
A2: S.No | B2: Type | C2: Size (mm) | D2: Material | E2: Sum of Total Weight (Kg) | F2: Sum of Gross Wt (kg) | G2: MOQ Weight | H2: Remarks | I2: Cal. Weight | J2: Rate/Kg | K2: Cost | O2: Type | P2: (All)
A3: 1 | B3: Plate | C3: 6 | D3: E350 A/BR | E3: =GETPIVOTDATA("Sum of Total Weight (Kg)",$O$4,"Alt. Material","IS 2062 E350 A/BR","IS Thk (mm)",6) -> 107.02366 | F3: =GETPIVOTDATA("Sum of Gross Wt (kg)",$O$4,"Alt. Material","IS 2062 E350 A/BR","IS Thk (mm)",6) -> 118.91781 | G3: 0 | I3: =IF(G3>F3,G3,IF(G3<F3,F3)) -> 118.91781 | J3: 90 | K3: =J3*I3 -> 10702.603
A4: 2 | B4: Plate | C4: 10 | D4: E350 A/BR | E4: =GETPIVOTDATA("Sum of Total Weight (Kg)",$O$4,"Alt. Material","IS 2062 E350 A/BR","IS Thk (mm)",10) -> 824.37734 | F4: =GETPIVOTDATA("Sum of Gross Wt (kg)",$O$4,"Alt. Material","IS 2062 E350 A/BR","IS Thk (mm)",10) -> 1100.4267 | G4: 0 | I4: =IF(G4>F4,G4,IF(G4<F4,F4)) -> 1100.4267 | J4: 90 | K4: =J4*I4 -> 99038.403 | P4: Column Labels
A5: 3 | B5: Plate | C5: 12 | D5: E350 A/BR | E5: =GETPIVOTDATA("Sum of Total Weight (Kg)",$O$4,"Alt. Material","IS 2062 E350 A/BR","IS Thk (mm)",12) -> 243.8 | F5: =GETPIVOTDATA("Sum of Gross Wt (kg)",$O$4,"Alt. Material","IS 2062 E350 A/BR","IS Thk (mm)",12) -> 331.38795 | G5: 0 | I5: =IF(G5>F5,G5,IF(G5<F5,F5)) -> 331.38795 | J5: 90 | K5: =J5*I5 -> 29824.916 | P5: ASTM A106 GR.B | R5: YST 310 | T5: IS 2062 E350 A/BR | V5: IS 2062 E250 A/BR | X5: Total Sum of Total Weight (Kg) | Y5: Total Sum of Gross Wt (kg)
A6: 4 | B6: Plate | C6: 50 | D6: E350 A/BR | E6: =GETPIVOTDATA("Sum of Total Weight (Kg)",$O$4,"Alt. Material","IS 2062 E350 A/BR","IS Thk (mm)",50) -> 76 | F6: =GETPIVOTDATA("Sum of Gross Wt (kg)",$O$4,"Alt. Material","IS 2062 E350 A/BR","IS Thk (mm)",50) -> 126.89996 | G6: 0 | I6: =IF(G6>F6,G6,IF(G6<F6,F6)) -> 126.89996 | J6: 90 | K6: =J6*I6 -> 11420.996 | O6: Row Labels | P6: Sum of Total Weight (Kg) | Q6: Sum of Gross Wt (kg) | R6: Sum of Total Weight (Kg) | S6: Sum of Gross Wt (kg) | T6: Sum of Total Weight (Kg) | U6: Sum of Gross Wt (kg) | V6: Sum of Total Weight (Kg) | W6: Sum of Gross Wt (kg)
A7: 5 | B7: Plate | C7: 5 | D7: E250 A/BR | E7: =GETPIVOTDATA("Sum of Total Weight (Kg)",$O$4,"Alt. Material","IS 2062 E250 A/BR","IS Thk (mm)",5) -> 0.199861 | F7: =GETPIVOTDATA("Sum of Total Weight (Kg)",$O$4,"Alt. Material","IS 2062 E250 A/BR","IS Thk (mm)",5) -> 0.199861 | G7: 0 | I7: =IF(G7>F7,G7,IF(G7<F7,F7)) -> 0.199861 | J7: 110 | K7: =J7*I7 -> 21.98471 | O7: 5 | V7: 0.199861 | W7: 0.2198471 | X7: 0.199861 | Y7: 0.2198471
A8: 6 | B8: Plate | C8: 6 | D8: E250 A/BR | E8: =GETPIVOTDATA("Sum of Total Weight (Kg)",$O$4,"Alt. Material","IS 2062 E250 A/BR","IS Thk (mm)",6) -> 36.027967 | F8: =GETPIVOTDATA("Sum of Gross Wt (kg)",$O$4,"Alt. Material","IS 2062 E250 A/BR","IS Thk (mm)",6) -> 39.630764 | G8: 0 | I8: =IF(G8>F8,G8,IF(G8<F8,F8)) -> 39.630764 | J8: 110 | K8: =J8*I8 -> 4359.3841 | O8: 6 | T8: 107.02366 | U8: 118.91781 | V8: 36.027967 | W8: 39.630764 | X8: 143.05163 | Y8: 158.54857
A9: 7 | B9: Plate | C9: 12 | D9: E250 A/BR | E9: =GETPIVOTDATA("Sum of Total Weight (Kg)",$O$4,"Alt. Material","IS 2062 E250 A/BR","IS Thk (mm)",12) -> 5.38353 | F9: =GETPIVOTDATA("Sum of Gross Wt (kg)",$O$4,"Alt. Material","IS 2062 E250 A/BR","IS Thk (mm)",12) -> 5.921883 | G9: 0 | I9: =IF(G9>F9,G9,IF(G9<F9,F9)) -> 5.921883 | J9: 110 | K9: =J9*I9 -> 651.40713 | O9: 10 | T9: 824.37734 | U9: 1100.4267 | X9: 824.37734 | Y9: 1100.4267
A10: 8 | B10: Plate | C10: 20 | D10: E250 A/BR | E10: =GETPIVOTDATA("Sum of Total Weight (Kg)",$O$4,"Alt. Material","IS 2062 E250 A/BR","IS Thk (mm)",20) -> 315.9956 | F10: =GETPIVOTDATA("Sum of Gross Wt (kg)",$O$4,"Alt. Material","IS 2062 E250 A/BR","IS Thk (mm)",20) -> 352.37708 | G10: 0 | I10: =IF(G10>F10,G10,IF(G10<F10,F10)) -> 352.37708 | J10: 90 | K10: =J10*I10 -> 31713.937 | O10: 12 | T10: 243.8 | U10: 331.38795 | V10: 5.38353 | W10: 5.921883 | X10: 249.18353 | Y10: 337.30983
A11: 9 | B11: Plate | C11: 25 | D11: E250 A/BR | E11: =GETPIVOTDATA("Sum of Total Weight (Kg)",$O$4,"Alt. Material","IS 2062 E250 A/BR","IS Thk (mm)",25) -> 16.007 | F11: =GETPIVOTDATA("Sum of Gross Wt (kg)",$O$4,"Alt. Material","IS 2062 E250 A/BR","IS Thk (mm)",25) -> 21.630675 | G11: 0 | I11: =IF(G11>F11,G11,IF(G11<F11,F11)) -> 21.630675 | J11: 110 | K11: =J11*I11 -> 2379.3742 | O11: 20 | V11: 315.9956 | W11: 352.37708 | X11: 315.9956 | Y11: 352.37708
A12: 10 | B12: Plate | C12: 40 | D12: E250 A/BR | E12: =GETPIVOTDATA("Sum of Total Weight (Kg)",$O$4,"Alt. Material","IS 2062 E250 A/BR","IS Thk (mm)",40) -> 89.2 | F12: =GETPIVOTDATA("Sum of Gross Wt (kg)",$O$4,"Alt. Material","IS 2062 E250 A/BR","IS Thk (mm)",40) -> 139.39446 | G12: 0 | I12: =IF(G12>F12,G12,IF(G12<F12,F12)) -> 139.39446 | J12: 90 | K12: =J12*I12 -> 12545.501 | O12: 25 | V12: 16.007 | W12: 21.630675 | X12: 16.007 | Y12: 21.630675
A13: 11 | B13: Rec Tube | C13: 100x80x 5thk 120x60x5 thk | D13: YST 310 | E13: =GETPIVOTDATA("Sum of Total Weight (Kg)",$O$4,"Alt. Material","YST 310","IS Thk (mm)","100x80x 5thk") -> 23.0688 | F13: =GETPIVOTDATA("Sum of Gross Wt (kg)",$O$4,"Alt. Material","YST 310","IS Thk (mm)","100x80x 5thk") -> 25.37568 | G13: =12.84*6 -> 77.04 | H13: Apollo Make | I13: =IF(G13>F13,G13,IF(G13<F13,F13)) -> 77.04 | J13: 110 | K13: =J13*I13 -> 8474.4 | O13: 40 | V13: 89.2 | W13: 139.39446 | X13: 89.2 | Y13: 139.39446
A14: 12 | B14: Sq. Tube | C14: 50x50x 5thk | D14: YST 310 | E14: =GETPIVOTDATA("Sum of Total Weight (Kg)",$O$4,"Alt. Material","YST 310","IS Thk (mm)","50x50x 5thk") -> 20.44644 | F14: =GETPIVOTDATA("Sum of Gross Wt (kg)",$O$4,"Alt. Material","YST 310","IS Thk (mm)","50x50x 5thk") -> 22.491084 | G14: =6.56*6 -> 39.36 | H14: Apollo Make | I14: =IF(G14>F14,G14,IF(G14<F14,F14)) -> 39.36 | J14: 110 | K14: =J14*I14 -> 4329.6 | O14: 50 | T14: 76 | U14: 126.89996 | X14: 76 | Y14: 126.89996
A15: 13 | B15: Sq. Tube | C15: 80x80x 10thk x 6 thk | D15: YST 310 | E15: =GETPIVOTDATA("Sum of Total Weight (Kg)",$O$4,"Alt. Material","YST 310","IS Thk (mm)","80x80x 10thk") -> 26.8156 | F15: =GETPIVOTDATA("Sum of Gross Wt (kg)",$O$4,"Alt. Material","YST 310","IS Thk (mm)","80x80x 10thk") -> 29.49716 | G15: =13.21*6 -> 79.26 | H15: Apollo Make | I15: =IF(G15>F15,G15,IF(G15<F15,F15)) -> 79.26 | J15: 110 | K15: =J15*I15 -> 8718.6 | O15: 100x80x 5thk | R15: 23.0688 | S15: 25.37568 | X15: 23.0688 | Y15: 25.37568
A16: 14 | B16: Pipe | C16: Dia 101.6 x 8.08 thk | D16: ASTM A106 GR.B | E16: =GETPIVOTDATA("Sum of Total Weight (Kg)",$O$4,"Alt. Material","ASTM A106 GR.B","IS Thk (mm)","Dia 101.6 x 8.08 thk") -> 9.3032968 | F16: =GETPIVOTDATA("Sum of Gross Wt (kg)",$O$4,"Alt. Material","ASTM A106 GR.B","IS Thk (mm)","Dia 101.6 x 8.08 thk") -> 10.233626 | G16: =18.64*6 -> 111.84 | H16: Yash Pipe | I16: =IF(G16>F16,G16,IF(G16<F16,F16)) -> 111.84 | J16: 110 | K16: =J16*I16 -> 12302.4 | O16: 50x50x 5thk | R16: 20.44644 | S16: 22.491084 | X16: 20.44644 | Y16: 22.491084
A17: 15 | B17: Pipe | C17: Dia 114.3 x 8.56 thk | D17: ASTM A106 GR.B | E17: =GETPIVOTDATA("Sum of Total Weight (Kg)",$O$4,"Alt. Material","ASTM A106 GR.B","IS Thk (mm)","Dia 114.3 x 8.56 thk") -> 28.04648 | F17: =GETPIVOTDATA("Sum of Gross Wt (kg)",$O$4,"Alt. Material","ASTM A106 GR.B","IS Thk (mm)","Dia 114.3 x 8.56 thk") -> 30.851128 | G17: =22.33*6 -> 133.98 | H17: Yash Pipe | I17: =IF(G17>F17,G17,IF(G17<F17,F17)) -> 133.98 | J17: 110 | K17: =J17*I17 -> 14737.8 | O17: 80x80x 10thk | R17: 26.8156 | S17: 29.49716 | X17: 26.8156 | Y17: 29.49716
A18: 16 | B18: Pipe | C18: Dia 168.28 x 10.97thk | D18: ASTM A106 GR.B | E18: =GETPIVOTDATA("Sum of Total Weight (Kg)",$O$4,"Alt. Material","ASTM A106 GR.B","IS Thk (mm)","Dia 168.28 x 10.97thk") -> 101.63328 | F18: =GETPIVOTDATA("Sum of Gross Wt (kg)",$O$4,"Alt. Material","ASTM A106 GR.B","IS Thk (mm)","Dia 168.28 x 10.97thk") -> 111.79661 | G18: =42.56*6 -> 255.36 | H18: Yash Pipe | I18: =IF(G18>F18,G18,IF(G18<F18,F18)) -> 255.36 | J18: 110 | K18: =J18*I18 -> 28089.6 | O18: Dia 101.6 x 8.08 thk | P18: 9.3032968 | Q18: 10.233626 | X18: 9.3032968 | Y18: 10.233626
A19: 17 | B19: Pipe | C19: Dia 21.3 x 2.77 thk | D19: ASTM A106 GR.B | E19: =GETPIVOTDATA("Sum of Total Weight (Kg)",$O$4,"Alt. Material","ASTM A106 GR.B","IS Thk (mm)","Dia 21.3 x 2.77 thk") -> 0.26289 | F19: =GETPIVOTDATA("Sum of Gross Wt (kg)",$O$4,"Alt. Material","ASTM A106 GR.B","IS Thk (mm)","Dia 21.3 x 2.77 thk") -> 0.289179 | G19: =1.27*6 -> 7.62 | H19: Yash Pipe | I19: =IF(G19>F19,G19,IF(G19<F19,F19)) -> 7.62 | J19: 160 | K19: =J19*I19 -> 1219.2 | O19: Dia 114.3 x 8.56 thk | P19: 28.04648 | Q19: 30.851128 | X19: 28.04648 | Y19: 30.851128
A20: 18 | B20: Pipe | C20: Dia 33.4x 6.35 | D20: ASTM A106 GR.B | E20: =GETPIVOTDATA("Sum of Total Weight (Kg)",$O$4,"Alt. Material","ASTM A106 GR.B","IS Thk (mm)","Dia 33.4x 6.35") -> 0.36288 | F20: =GETPIVOTDATA("Sum of Gross Wt (kg)",$O$4,"Alt. Material","ASTM A106 GR.B","IS Thk (mm)","Dia 33.4x 6.35") -> 0.399168 | G20: =4.24*6 -> 25.44 | H20: Yash Pipe | I20: =IF(G20>F20,G20,IF(G20<F20,F20)) -> 25.44 | J20: 130 | K20: =J20*I20 -> 3307.2 | O20: Dia 12 | V20: 0.04 | W20: 0.29315 | X20: 0.04 | Y20: 0.29315
A21: 19 | B21: Channel | C21: ISMC 200 x 75 | D21: E350 A | E21: =GETPIVOTDATA("Sum of Total Weight (Kg)",$O$4,"Alt. Material","IS 2062 E350 A/BR","IS Thk (mm)","ISMC 200 x 75") -> 982.1207 | F21: =GETPIVOTDATA("Sum of Gross Wt (kg)",$O$4,"Alt. Material","IS 2062 E350 A/BR","IS Thk (mm)","ISMC 200 x 75") -> 1080.3328 | G21: =22.3*6 -> 133.8 | H21: JSIL | I21: =IF(G21>F21,G21,IF(G21<F21,F21)) -> 1080.3328 | J21: 110 | K21: =J21*I21 -> 118836.6 | O21: Dia 168.28 x 10.97thk | P21: 101.63328 | Q21: 111.79661 | X21: 101.63328 | Y21: 111.79661
A22: 20 | B22: Beam | C22: NPB 600x 220x 107.57 | D22: E350 A | E22: =GETPIVOTDATA("Sum of Total Weight (Kg)",$O$4,"Alt. Material","IS 2062 E350 A/BR","IS Thk (mm)","NPB 600x 220x 107.57") -> 996 | F22: =GETPIVOTDATA("Sum of Gross Wt (kg)",$O$4,"Alt. Material","IS 2062 E350 A/BR","IS Thk (mm)","NPB 600x 220x 107.57") -> 1081.9821 | G22: =107.6*6 -> 645.6 | H22: SAIL | I22: =IF(G22>F22,G22,IF(G22<F22,F22)) -> 1081.9821 | J22: 110 | K22: =J22*I22 -> 119018.03 | O22: Dia 21.3 x 2.77 thk | P22: 0.26289 | Q22: 0.289179 | X22: 0.26289 | Y22: 0.289179
A23: 21 | B23: Channel | C23: UPN80 X 45/ ISMC 75x40 | D23: E250 A/ | E23: =GETPIVOTDATA("Sum of Total Weight (Kg)",$O$4,"Alt. Material","IS 2062 E250 A/BR","IS Thk (mm)","UPN80 X 45") -> 149.95104 | F23: =GETPIVOTDATA("Sum of Gross Wt (kg)",$O$4,"Alt. Material","IS 2062 E250 A/BR","IS Thk (mm)","UPN80 X 45") -> 166.13942 | G23: =7.14*6 -> 42.84 | H23: SAIL | I23: =IF(G23>F23,G23,IF(G23<F23,F23)) -> 166.13942 | J23: 110 | K23: =J23*I23 -> 18275.337 | O23: Dia 33.4x 6.35 | P23: 0.36288 | Q23: 0.399168 | X23: 0.36288 | Y23: 0.399168
A24: 22 | B24: Rod | C24: Dia 12 | D24: E250 A/BR | E24: =GETPIVOTDATA("Sum of Total Weight (Kg)",$O$4,"Alt. Material","IS 2062 E250 A/BR","IS Thk (mm)","Dia 12") -> 0.04 | F24: =GETPIVOTDATA("Sum of Gross Wt (kg)",$O$4,"Alt. Material","IS 2062 E250 A/BR","IS Thk (mm)","Dia 12") -> 0.29315 | G24: 2.66 | H24: Yash Pipe | I24: =IF(G24>F24,G24,IF(G24<F24,F24)) -> 2.66 | J24: 110 | K24: =J24*I24 -> 292.6 | O24: ISMC 200 x 75 | T24: 982.1207 | U24: 1080.3328 | X24: 982.1207 | Y24: 1080.3328
C25: Total | E25: =SUM(E3:E24) -> 4052.0664 | F25: =SUM(F3:F24) -> 4796.4682 | I25: =SUM(I3:I24) -> 5297.8014 | J25: =K25/I25 -> 101.97813 | K25: =SUM(K3:K24) -> 540259.88 | O25: NPB 600x 220x 107.57 | T25: 996 | U25: 1081.9821 | X25: 996 | Y25: 1081.9821
O26: UPN80 X 45 | V26: 149.95104 | W26: 166.13942 | X26: 149.95104 | Y26: 166.13942
O27: Grand Total | P27: 139.60883 | Q27: 153.56971 | R27: 70.33084 | S27: 77.363924 | T27: 3229.3217 | U27: 3839.9473 | V27: 612.805 | W27: 725.60728 | X27: 4052.0664 | Y27: 4796.4882
A30: Assy No | H30: =P30 -> AY30017 | O30: Assembly | P30: AY30017
A31: S.No | B31: Type | C31: Size (mm) | D31: Material | E31: Sum of Total Weight (Kg) | F31: Sum of Gross Wt (kg) | G31: MOQ Weight | H31: Remarks | I31: Cal. Weight | J31: Rate/Kg | K31: Cost | O31: Type | P31: (All)
A32: 1 | B32: Plate | C32: 10 | D32: E250 A/BR | E32: =GETPIVOTDATA("Sum of Total Weight (Kg)",$O$33,"Alt. Material","IS 2062 E250 A/BR","IS Thk (mm)",10) -> 6 | F32: =GETPIVOTDATA("Sum of Gross Wt (kg)",$O$33,"Alt. Material","IS 2062 E250 A/BR","IS Thk (mm)",10) -> 8.20325 | G32: 0 | I32: =IF(G32>F32,G32,IF(G32<F32,F32)) -> 8.20325 | J32: 110 | K32: =J32*I32 -> 902.3575
A33: 2 | B33: Plate | C33: 16 | D33: E250 A/BR | E33: =GETPIVOTDATA("Sum of Total Weight (Kg)",$O$33,"Alt. Material","IS 2062 E250 A/BR","IS Thk (mm)",16) -> 12 | F33: =GETPIVOTDATA("Sum of Gross Wt (kg)",$O$33,"Alt. Material","IS 2062 E250 A/BR","IS Thk (mm)",16) -> 17.728139 | G33: 0 | I33: =IF(G33>F33,G33,IF(G33<F33,F33)) -> 17.728139 | J33: 110 | K33: =J33*I33 -> 1950.0952 | P33: Column Labels
A34: 3 | B34: Plate | C34: ISMC 200x 75 | D34: E350 A | E34: =GETPIVOTDATA("Sum of Total Weight (Kg)",$O$33,"Alt. Material","IS 2062 E350 A/BR","IS Thk (mm)","ISMC 200 x 75") -> 112.332 | F34: =GETPIVOTDATA("Sum of Gross Wt (kg)",$O$33,"Alt. Material","IS 2062 E350 A/BR","IS Thk (mm)","ISMC 200 x 75") -> 123.5652 | G34: =22.3*6 -> 133.8 | H34: JSPL | I34: =IF(G34>F34,G34,IF(G34<F34,F34)) -> 133.8 | J34: 110 | K34: =J34*I34 -> 14718 | P34: IS 2062 E350 A/BR | R34: IS 2062 E250 A/BR | T34: Total Sum of Total Weight (Kg) | U34: Total Sum of Gross Wt (kg)
C35: Total | E35: =SUM(E32:E34) -> 130.332 | F35: =SUM(F32:F34) -> 149.49659 | I35: =SUM(I32:I34) -> 159.73139 | J35: =K35/I35 -> 110 | K35: =SUM(K32:K34) -> 17570.453 | O35: Row Labels | P35: Sum of Total Weight (Kg) | Q35: Sum of Gross Wt (kg) | R35: Sum of Total Weight (Kg) | S35: Sum of Gross Wt (kg)
O36: 10 | R36: 6 | S36: 8.20325 | T36: 6 | U36: 8.20325
O37: 16 | R37: 12 | S37: 17.728139 | T37: 12 | U37: 17.728139
O38: ISMC 200 x 75 | P38: 112.332 | Q38: 123.5652 | T38: 112.332 | U38: 123.5652
O39: Grand Total | P39: 112.332 | Q39: 123.5652 | R39: 18 | S39: 25.931389 | T39: 130.332 | U39: 149.49659
A42: Assy No | H42: =P42 -> AY30018 | O42: Assembly | P42: AY30018
A43: S.No | B43: Type | C43: Size (mm) | D43: Material | E43: Sum of Total Weight (Kg) | F43: Sum of Gross Wt (kg) | G43: MOQ Weight | H43: Remarks | I43: Cal. Weight | J43: Rate/Kg | K43: Cost | O43: Type | P43: (All)
A44: 1 | B44: Plate | C44: 6 | D44: E350 A/BR | E44: =GETPIVOTDATA("Sum of Total Weight (Kg)",$O$45,"Alt. Material","IS 2062 E350 A/BR","IS Thk (mm)",6) -> 26 | F44: =GETPIVOTDATA("Sum of Gross Wt (kg)",$O$45,"Alt. Material","IS 2062 E350 A/BR","IS Thk (mm)",6) -> 28.6 | G44: 0 | I44: =IF(G44>F44,G44,IF(G44<F44,F44)) -> 28.6 | J44: 110 | K44: =J44*I44 -> 3146
A45: 2 | B45: Plate | C45: 10 | D45: E350 A/BR | E45: =GETPIVOTDATA("Sum of Total Weight (Kg)",$O$45,"Alt. Material","IS 2062 E350 A/BR","IS Thk (mm)",10) -> 0.8 | F45: =GETPIVOTDATA("Sum of Gross Wt (kg)",$O$45,"Alt. Material","IS 2062 E350 A/BR","IS Thk (mm)",10) -> 1.0668715 | G45: 0 | I45: =IF(G45>F45,G45,IF(G45<F45,F45)) -> 1.0668715 | J45: 110 | K45: =J45*I45 -> 117.35587 | P45: Column Labels
C46: Total | E46: =SUM(E44:E45) -> 26.8 | F46: =SUM(F44:F45) -> 29.666872 | I46: =SUM(I44:I45) -> 29.666872 | J46: =K46/I46 -> 110 | K46: =SUM(K44:K45) -> 3263.3559 | P46: IS 2062 E350 A/BR | R46: Total Sum of Total Weight (Kg) | S46: Total Sum of Gross Wt (kg)
O47: Row Labels | P47: Sum of Total Weight (Kg) | Q47: Sum of Gross Wt (kg)
O48: 6 | P48: 26 | Q48: 28.6 | R48: 26 | S48: 28.6
O49: 10 | P49: 0.8 | Q49: 1.0668715 | R49: 0.8 | S49: 1.0668715
O50: Grand Total | P50: 26.8 | Q50: 29.666872 | R50: 26.8 | S50: 29.666872
A54: Assy No | H54: =P54 -> AY30027 | O54: Assembly | P54: AY30027
A55: S.No | B55: Type | C55: Size (mm) | D55: Material | E55: Sum of Total Weight (Kg) | F55: Sum of Gross Wt (kg) | G55: MOQ Weight | H55: Remarks | I55: Cal. Weight | J55: Rate/Kg | K55: Cost | O55: Type | P55: (All)
A56: 1 | B56: Plate | C56: 6 | D56: E350 A/BR | E56: =GETPIVOTDATA("Sum of Total Weight (Kg)",$O$57,"Alt. Material","IS 2062 E350 A/BR","IS Thk (mm)",6) -> 391 | F56: =GETPIVOTDATA("Sum of Gross Wt (kg)",$O$57,"Alt. Material","IS 2062 E350 A/BR","IS Thk (mm)",6) -> 428.97608 | G56: 0 | I56: =IF(G56>F56,G56,IF(G56<F56,F56)) -> 428.97608 | J56: 90 | K56: =J56*I56 -> 38607.847
A57: 2 | B57: Plate | C57: 10 | D57: E350 A/BR | E57: =GETPIVOTDATA("Sum of Total Weight (Kg)",$O$57,"Alt. Material","IS 2062 E350 A/BR","IS Thk (mm)",10) -> 52.058131 | F57: =GETPIVOTDATA("Sum of Gross Wt (kg)",$O$57,"Alt. Material","IS 2062 E350 A/BR","IS Thk (mm)",10) -> 61.561989 | G57: 0 | I57: =IF(G57>F57,G57,IF(G57<F57,F57)) -> 61.561989 | J57: 110 | K57: =J57*I57 -> 6771.8188 | P57: Column Labels
C58: Total | E58: =SUM(E56:E57) -> 443.05813 | F58: =SUM(F56:F57) -> 490.53806 | I58: =SUM(I56:I57) -> 490.53806 | J58: =K58/I58 -> 92.509978 | K58: =SUM(K56:K57) -> 45379.666 | P58: IS 2062 E350 A/BR | R58: Total Sum of Total Weight (Kg) | S58: Total Sum of Gross Wt (kg)
O59: Row Labels | P59: Sum of Total Weight (Kg) | Q59: Sum of Gross Wt (kg)
O60: 6 | P60: 391 | Q60: 428.97608 | R60: 391 | S60: 428.97608
O61: 10 | P61: 52.058131 | Q61: 61.561989 | R61: 52.058131 | S61: 61.561989
O62: Grand Total | P62: 443.05813 | Q62: 490.53806 | R62: 443.05813 | S62: 490.53806
A65: Assy No | H65: =P65 -> AY30062 | O65: Assembly | P65: AY30062
A66: S.No | B66: Type | C66: Size (mm) | D66: Material | E66: Sum of Total Weight (Kg) | F66: Sum of Gross Wt (kg) | G66: MOQ Weight | H66: Remarks | I66: Cal. Weight | J66: Rate/Kg | K66: Cost | O66: Type | P66: (All)
A67: 1 | B67: Plate | C67: 10 | D67: E350 A/BR | E67: =GETPIVOTDATA("Sum of Total Weight (Kg)",$O$68,"Alt. Material","IS 2062 E350 A/BR","IS Thk (mm)",10) -> 2.4 | F67: =GETPIVOTDATA("Sum of Gross Wt (kg)",$O$68,"Alt. Material","IS 2062 E350 A/BR","IS Thk (mm)",10) -> 3.38492 | G67: 0 | I67: =IF(G67>F67,G67,IF(G67<F67,F67)) -> 3.38492 | J67: 90 | K67: =J67*I67 -> 304.6428
A68: 2 | B68: Pipe | C68: Dia 101.6 x 8.08 thk | D68: ASTM A106 GR.B | E68: =GETPIVOTDATA("Sum of Total Weight (Kg)",$O$68,"Alt. Material","ASTM A106 GR.B","IS Thk (mm)","Dia 101.6 x 8.08 thk") -> 17.9876 | F68: =GETPIVOTDATA("Sum of Gross Wt (kg)",$O$68,"Alt. Material","ASTM A106 GR.B","IS Thk (mm)","Dia 101.6 x 8.08 thk") -> 19.78636 | G68: =18.64*6/2 -> 55.92 | I68: =IF(G68>F68,G68,IF(G68<F68,F68)) -> 55.92 | J68: 110 | K68: =J68*I68 -> 6151.2 | P68: Column Labels
A69: 3 | B69: Rod | C69: Dia 12 | D69: E250 A/BR | E69: =GETPIVOTDATA("Sum of Total Weight (Kg)",$O$68,"Alt. Material","IS 2062 E250 A/BR","IS Thk (mm)","Dia 12") -> 0.3 | F69: =GETPIVOTDATA("Sum of Gross Wt (kg)",$O$68,"Alt. Material","IS 2062 E250 A/BR","IS Thk (mm)","Dia 12") -> 2.011009 | G69: =0.89*3 -> 2.67 | I69: =IF(G69>F69,G69,IF(G69<F69,F69)) -> 2.67 | J69: 110 | K69: =J69*I69 -> 293.7 | P69: ASTM A106 GR.B | R69: IS 2062 E350 A/BR | T69: IS 2062 E250 A/BR | V69: Total Sum of Total Weight (Kg) | W69: Total Sum of Gross Wt (kg)
C70: Total | E70: =SUM(E67:E69) -> 20.6876 | F70: =SUM(F67:F69) -> 25.182289 | I70: =SUM(I67:I69) -> 61.97492 | J70: =K70/I70 -> 108.90765 | K70: =SUM(K67:K69) -> 6749.5428 | O70: Row Labels | P70: Sum of Total Weight (Kg) | Q70: Sum of Gross Wt (kg) | R70: Sum of Total Weight (Kg) | S70: Sum of Gross Wt (kg) | T70: Sum of Total Weight (Kg) | U70: Sum of Gross Wt (kg)
O71: 10 | R71: 2.4 | S71: 3.38492 | V71: 2.4 | W71: 3.38492
O72: Dia 101.6 x 8.08 thk | P72: 17.9876 | Q72: 19.78636 | V72: 17.9876 | W72: 19.78636
O73: Dia 12 | T73: 0.3 | U73: 2.011009 | V73: 0.3 | W73: 2.011009
O74: Grand Total | P74: 17.9876 | Q74: 19.78636 | R74: 2.4 | S74: 3.38492 | T74: 0.3 | U74: 2.011009 | V74: 20.6876 | W74: 25.182289
A77: Assy No | H77: =P77 -> AY30084 | O77: Assembly | P77: AY30084
A78: S.No | B78: Type | C78: Size (mm) | D78: Material | E78: Sum of Total Weight (Kg) | F78: Sum of Gross Wt (kg) | G78: MOQ Weight | H78: Remarks | I78: Cal. Weight | J78: Rate/Kg | K78: Cost | O78: Type | P78: (All)
A79: 1 | B79: Sq. Tube | C79: 40x40x 5thk | D79: YST 310 | E79: =GETPIVOTDATA("Sum of Total Weight (Kg)",$O$80,"Alt. Material","YST 310","IS Thk (mm)","40x40x 5thk") -> 88.946 | F79: =GETPIVOTDATA("Sum of Gross Wt (kg)",$O$80,"Alt. Material","YST 310","IS Thk (mm)","40x40x 5thk") -> 97.8406 | G79: =5.5*6 -> 33 | I79: =IF(G79>F79,G79,IF(G79<F79,F79)) -> 97.8406 | J79: 110 | K79: =J79*I79 -> 10762.466
C80: Total | E80: =SUM(E79:E79) -> 88.946 | F80: =SUM(F79:F79) -> 97.8406 | I80: =SUM(I79:I79) -> 97.8406 | J80: =K80/I80 -> 110 | K80: =SUM(K79:K79) -> 10762.466 | P80: Column Labels
P81: YST 310 | R81: Total Sum of Total Weight (Kg) | S81: Total Sum of Gross Wt (kg)
O82: Row Labels | P82: Sum of Total Weight (Kg) | Q82: Sum of Gross Wt (kg)
O83: 40x40x 5thk | P83: 88.946 | Q83: 97.8406 | R83: 88.946 | S83: 97.8406
O84: Grand Total | P84: 88.946 | Q84: 97.8406 | R84: 88.946 | S84: 97.8406
A87: Assy No | H87: =P87 -> AY30107 | O87: Assembly | P87: AY30107
A88: S.No | B88: Type | C88: Size (mm) | D88: Material | E88: Sum of Total Weight (Kg) | F88: Sum of Gross Wt (kg) | G88: MOQ Weight | H88: Remarks | I88: Cal. Weight | J88: Rate/Kg | K88: Cost | O88: Type | P88: (All)
A89: 1 | B89: Plate | C89: 10 | D89: E350 A/BR | E89: =GETPIVOTDATA("Sum of Total Weight (Kg)",$O$90,"Alt. Material","IS 2062 E350 A/BR","IS Thk (mm)",10) -> 2 | F89: =GETPIVOTDATA("Sum of Gross Wt (kg)",$O$90,"Alt. Material","IS 2062 E350 A/BR","IS Thk (mm)",10) -> 4.1130232 | I89: =IF(G89>F89,G89,IF(G89<F89,F89)) -> 4.1130232 | J89: 90 | K89: =J89*I89 -> 370.17209
A90: 2 | B90: Plate | C90: 20 | D90: E250 A/BR | E90: =GETPIVOTDATA("Sum of Total Weight (Kg)",$O$90,"Alt. Material","IS 2062 E250 A/BR","IS Thk (mm)",20) -> 28 | F90: =GETPIVOTDATA("Sum of Gross Wt (kg)",$O$90,"Alt. Material","IS 2062 E250 A/BR","IS Thk (mm)",20) -> 38.74559 | I90: =IF(G90>F90,G90,IF(G90<F90,F90)) -> 38.74559 | J90: 90 | K90: =J90*I90 -> 3487.1031 | P90: Column Labels
A91: 3 | B91: Plate | C91: 25 | D91: E250 A/BR | E91: =GETPIVOTDATA("Sum of Total Weight (Kg)",$O$90,"Alt. Material","IS 2062 E250 A/BR","IS Thk (mm)",25) -> 50.5 | F91: =GETPIVOTDATA("Sum of Gross Wt (kg)",$O$90,"Alt. Material","IS 2062 E250 A/BR","IS Thk (mm)",25) -> 94.58412 | I91: =IF(G91>F91,G91,IF(G91<F91,F91)) -> 94.58412 | J91: 90 | K91: =J91*I91 -> 8512.5708 | P91: IS 2062 E350 A/BR | R91: IS 2062 E250 A/BR | T91: Total Sum of Total Weight (Kg) | U91: Total Sum of Gross Wt (kg)
C92: Total | E92: =SUM(E89:E91) -> 80.5 | F92: =SUM(F89:F91) -> 137.44273 | I92: =SUM(I89:I91) -> 137.44273 | J92: =K92/I92 -> 90 | K92: =SUM(K89:K91) -> 12369.846 | O92: Row Labels | P92: Sum of Total Weight (Kg) | Q92: Sum of Gross Wt (kg) | R92: Sum of Total Weight (Kg) | S92: Sum of Gross Wt (kg)
O93: 10 | P93: 2 | Q93: 4.1130232 | T93: 2 | U93: 4.1130232
O94: 20 | R94: 28 | S94: 38.74559 | T94: 28 | U94: 38.74559
O95: 25 | R95: 50.5 | S95: 94.58412 | T95: 50.5 | U95: 94.58412
O96: Grand Total | P96: 2 | Q96: 4.1130232 | R96: 78.5 | S96: 133.32971 | T96: 80.5 | U96: 137.44273
A98: Assy No | H98: =P98 -> AY30133 | O98: Assembly | P98: AY30133
A99: S.No | B99: Type | C99: Size (mm) | D99: Material | E99: Sum of Total Weight (Kg) | F99: Sum of Gross Wt (kg) | G99: MOQ Weight | H99: Remarks | I99: Cal. Weight | J99: Rate/Kg | K99: Cost | O99: Type | P99: (All)
A100: 1 | B100: Sq. Tube | C100: 50x50x 5thk | D100: YST 310 | E100: =GETPIVOTDATA("Sum of Total Weight (Kg)",$O$101,"Alt. Material","YST 310","IS Thk (mm)","50x50x 5thk") -> 124.5734 | F100: =GETPIVOTDATA("Sum of Gross Wt (kg)",$O$101,"Alt. Material","YST 310","IS Thk (mm)","50x50x 5thk") -> 137.03074 | G100: =6.56*6 -> 39.36 | I100: =IF(G100>F100,G100,IF(G100<F100,F100)) -> 137.03074 | J100: 110 | K100: =J100*I100 -> 15073.381
C101: Total | E101: =SUM(E100:E100) -> 124.5734 | F101: =SUM(F100:F100) -> 137.03074 | I101: =SUM(I100:I100) -> 137.03074 | J101: =K101/I101 -> 110 | K101: =SUM(K100:K100) -> 15073.381 | P101: Column Labels
P102: YST 310 | R102: Total Sum of Total Weight (Kg) | S102: Total Sum of Gross Wt (kg)
O103: Row Labels | P103: Sum of Total Weight (Kg) | Q103: Sum of Gross Wt (kg)
O104: 50x50x 5thk | P104: 124.5734 | Q104: 137.03074 | R104: 124.5734 | S104: 137.03074
O105: Grand Total | P105: 124.5734 | Q105: 137.03074 | R105: 124.5734 | S105: 137.03074
A108: Assy No | H108: =P108 -> AY30134 | O108: Assembly | P108: AY30134
A109: S.No | B109: Type | C109: Size (mm) | D109: Material | E109: Sum of Total Weight (Kg) | F109: Sum of Gross Wt (kg) | G109: MOQ Weight | H109: Remarks | I109: Cal. Weight | J109: Rate/Kg | K109: Cost | O109: Type | P109: (All)
A110: 1 | B110: Plate | C110: 12 | D110: E350 A/BR | E110: =GETPIVOTDATA("Sum of Total Weight (Kg)",$O$111,"Alt. Material","IS 2062 E350 A/BR","IS Thk (mm)",12) -> 96.257444 | F110: =GETPIVOTDATA("Sum of Gross Wt (kg)",$O$111,"Alt. Material","IS 2062 E350 A/BR","IS Thk (mm)",12) -> 153.65012 | I110: =IF(G110>F110,G110,IF(G110<F110,F110)) -> 153.65012 | J110: 90 | K110: =J110*I110 -> 13828.511
A111: 2 | B111: Plate | C111: 20 | D111: E350 A/BR | E111: =GETPIVOTDATA("Sum of Total Weight (Kg)",$O$111,"Alt. Material","IS 2062 E350 A/BR","IS Thk (mm)",20) -> 168.89231 | F111: =GETPIVOTDATA("Sum of Gross Wt (kg)",$O$111,"Alt. Material","IS 2062 E350 A/BR","IS Thk (mm)",20) -> 387.04488 | I111: =IF(G111>F111,G111,IF(G111<F111,F111)) -> 387.04488 | J111: 90 | K111: =J111*I111 -> 34834.039 | P111: Column Labels
A112: 3 | B112: Plate | C112: 20 | D112: E250 A/BR | E112: =GETPIVOTDATA("Sum of Total Weight (Kg)",$O$111,"Alt. Material","IS 2062 E250 A/BR","IS Thk (mm)",20) -> 42 | F112: =GETPIVOTDATA("Sum of Gross Wt (kg)",$O$111,"Alt. Material","IS 2062 E250 A/BR","IS Thk (mm)",20) -> 63.824739 | I112: =IF(G112>F112,G112,IF(G112<F112,F112)) -> 63.824739 | J112: 90 | K112: =J112*I112 -> 5744.2265 | P112: ASTM A106 GR.B | R112: IS 2062 E350 A/BR | T112: IS 2062 E250 A/BR | V112: Total Sum of Total Weight (Kg) | W112: Total Sum of Gross Wt (kg)
A113: 4 | B113: Plate | C113: 25 | D113: E250 A/BR | E113: =GETPIVOTDATA("Sum of Total Weight (Kg)",$O$111,"Alt. Material","IS 2062 E250 A/BR","IS Thk (mm)",25) -> 4.6 | F113: =GETPIVOTDATA("Sum of Gross Wt (kg)",$O$111,"Alt. Material","IS 2062 E250 A/BR","IS Thk (mm)",25) -> 7.787043 | I113: =IF(G113>F113,G113,IF(G113<F113,F113)) -> 7.787043 | J113: 90 | K113: =J113*I113 -> 700.83387 | O113: Row Labels | P113: Sum of Total Weight (Kg) | Q113: Sum of Gross Wt (kg) | R113: Sum of Total Weight (Kg) | S113: Sum of Gross Wt (kg) | T113: Sum of Total Weight (Kg) | U113: Sum of Gross Wt (kg)
A114: 5 | B114: Pipe | C114: Dia 168.28 x 10.97thk | D114: ASTM A106 GR.B | E114: =GETPIVOTDATA("Sum of Total Weight (Kg)",$O$111,"Alt. Material","ASTM A106 GR.B","IS Thk (mm)","Dia 168.28 x 10.97thk") -> 58.4 | F114: =GETPIVOTDATA("Sum of Gross Wt (kg)",$O$111,"Alt. Material","ASTM A106 GR.B","IS Thk (mm)","Dia 168.28 x 10.97thk") -> 64.24 | G114: =42.56*6 -> 255.36 | I114: =IF(G114>F114,G114,IF(G114<F114,F114)) -> 255.36 | J114: 110 | K114: =J114*I114 -> 28089.6 | O114: 12 | R114: 96.257444 | S114: 153.65012 | V114: 96.257444 | W114: 153.65012
A115: 6 | B115: Pipe | C115: Dia 60.3 x 3.91 thk | D115: ASTM A106 GR.B | E115: =GETPIVOTDATA("Sum of Total Weight (Kg)",$O$111,"Alt. Material","ASTM A106 GR.B","IS Thk (mm)","Dia 60.3 x 3.91 thk") -> 0.276352 | F115: =GETPIVOTDATA("Sum of Gross Wt (kg)",$O$111,"Alt. Material","ASTM A106 GR.B","IS Thk (mm)","Dia 60.3 x 3.91 thk") -> 0.3039872 | G115: =5.44*6 -> 32.64 | I115: =IF(G115>F115,G115,IF(G115<F115,F115)) -> 32.64 | J115: 110 | K115: =J115*I115 -> 3590.4 | O115: 20 | R115: 168.89231 | S115: 387.04488 | T115: 42 | U115: 63.824739 | V115: 210.89231 | W115: 450.86962
C116: Total | E116: =SUM(E110:E115) -> 370.42611 | F116: =SUM(F110:F115) -> 676.85077 | I116: =SUM(I110:I115) -> 900.30678 | J116: =K116/I116 -> 96.397819 | K116: =SUM(K110:K115) -> 86787.61 | O116: 25 | T116: 4.6 | U116: 7.787043 | V116: 4.6 | W116: 7.787043
...

Sheet RM Combined all
A1: S.No | B1: Type | C1: Size (mm) | D1: Material | E1: Gross Weight (Kg) | F1: Rate /Meter | G1: Size Remarks | H1: Vendor | I1: Weight /Meter | J1: Rate/kg | K1: MOQ Weight | L1: Calculated Gross Wt. | M1: Cost On Calculated Gross | P1: Assembly | Q1: (All)
A2: 1 | B2: Plate | C2: 6 | D2: IS 2062 E350 A/BR | E2: 580.26519
A3: 2 | B3: Plate | C3: 10 | D3: IS 2062 E350 A/BR | E3: 2443.8055 | P3: Sum of Gross Wt (kg) | Q3: Column Labels
A4: 3 | B4: Plate | C4: 12 | D4: IS 2062 E350 A/BR | E4: 798.68213 | P4: Row Labels | Q4: AISI C1045 | R4: ASTM A106 GR.B | S4: BROWNING SCS-2 | T4: YST 310 | U4: IS 2062 E350 A/BR | V4: IS 2062 E250 A/BR | W4: Grand Total
A5: 4 | B5: Plate | C5: 20 | D5: IS 2062 E350 A/BR | E5: 393.25448 | P5: 5 | V5: 0.2198471 | W5: 0.2198471
A6: 5 | B6: Plate | C6: 25 | D6: IS 2062 E350 A/BR | E6: 1.079375 | P6: 6 | U6: 580.26519 | V6: 40.921869 | W6: 621.18705
A7: 6 | B7: Plate | C7: 40 | D7: IS 2062 E350 A/BR | E7: 157.47477 | P7: 10 | U7: 2528.988 | V7: 8.20325 | W7: 2537.1913
A8: 7 | B8: Plate | C8: 50 | D8: IS 2062 E350 A/BR | E8: 126.89996 | P8: 12 | U8: 1244.37 | V8: 38.873043 | W8: 1283.243
A9: 8 | B9: Plate | C9: 5 | D9: IS 2062 E250 A/BR | E9: 0.2198471 | P9: 16 | V9: 17.728139 | W9: 17.728139
A10: 9 | B10: Plate | C10: 6 | D10: IS 2062 E250 A/BR | E10: 40.921869 | P10: 20 | U10: 393.25448 | V10: 749.42561 | W10: 1142.6801
A11: 10 | B11: Plate | C11: 10 | D11: IS 2062 E250 A/BR | E11: 8.20325 | P11: 25 | U11: 1.079375 | V11: 323.42112 | W11: 324.50049
A12: 11 | B12: Plate | C12: 12 | D12: IS 2062 E250 A/BR | E12: 38.873043 | P12: 40 | U12: 157.47477 | V12: 139.39446 | W12: 296.86923
A13: 12 | B13: Plate | C13: 16 | D13: IS 2062 E250 A/BR | E13: 17.728139 | P13: 50 | U13: 126.89996 | W13: 126.89996
A14: 13 | B14: Plate | C14: 20 | D14: IS 2062 E250 A/BR | E14: 749.42561 | P14: 100x80x 5thk | T14: 25.37568 | W14: 25.37568
A15: 14 | B15: Plate | C15: 25 | D15: IS 2062 E250 A/BR | E15: 323.42112 | P15: 120x80x 5thk | T15: 60.203 | W15: 60.203
A16: 15 | B16: Plate | C16: 40 | D16: IS 2062 E250 A/BR | E16: 139.39446 | P16: 150x100x 12thk | T16: 813.29503 | W16: 813.29503
P17: 150x50x 6thk | T17: 43.949136 | W17: 43.949136
A18: 16 | B18: Beam | C18: NPB 450x190x67.16 | D18: E350 A/BR | E18: 531.9072 | P18: 150x80x 10thk | T18: 122.39167 | W18: 122.39167
A19: 17 | B19: Beam | C19: NPB 600x 220x 107.57 | D19: E350 A/BR | E19: 1081.9821 | P19: 200x150x 12thk | T19: 945.25994 | W19: 945.25994
A20: 18 | B20: Channel | C20: ISMC 200 x 75 | D20: E350 A/BR | E20: 1203.898 | P20: 40x40x 5thk | T20: 97.8406 | W20: 97.8406
A21: 19 | B21: Channel | C21: UPN 160 X 65 X 18.8 | D21: E350 A/BR | E21: 1933.7454 | P21: 50x50x 5thk | T21: 159.52182 | W21: 159.52182
A22: 20 | B22: Channel | C22: UPN 80 X 45 | D22: E250 A/BR | E22: 166.13942 | P22: 80x80x 10thk | T22: 29.49716 | W22: 29.49716
P23: Dia 101.6 x 8.08 thk | R23: 30.019986 | W23: 30.019986
A24: 21 | B24: Rec Tube | C24: 100x80x 5thk | D24: YST 310 | E24: 25.37568 | F24: 2900 | G24: 100x80x6 | H24: Hi tech | I24: 15.83 | J24: =F24/I24 -> 183.19646 | K24: =I24*6 -> 94.98 | L24: =IF(K24>E24,K24,IF(K24<E24,E24)) -> 94.98 | M24: =L24*J24 -> 17400 | P24: Dia 114.3 x 8.56 thk | R24: 30.851128 | W24: 30.851128
A25: 22 | B25: Rec Tube | C25: 120x80x 5thk | D25: YST 310 | E25: 60.203 | F25: 3510 | G25: 120x80x6.5 | H25: Hi tech | I25: 19.08 | J25: =F25/I25 -> 183.96226 | K25: =I25*6 -> 114.48 | L25: =IF(K25>E25,K25,IF(K25<E25,E25)) -> 114.48 | M25: =L25*J25 -> 21060 | P25: Dia 12 | V25: 4.813523 | W25: 4.813523
A26: 23 | B26: Rec Tube | C26: 150x100x 12thk | D26: YST 310 | E26: 813.29503 | F26: 7160 | G26: 150x100x11to12 | H26: Hi tech | I26: 39.38 | J26: =F26/I26 -> 181.81818 | K26: =I26*6 -> 236.28 | L26: =IF(K26>E26,K26,IF(K26<E26,E26)) -> 813.29503 | M26: =L26*J26 -> 147871.82 | P26: Dia 168.28 x 10.97thk | R26: 176.03661 | W26: 176.03661
A27: 24 | B27: Rec Tube | C27: 150x80x 10thk | D27: YST 310 | E27: 122.39167 | F27: 6360 | G27: 150x80x9.5 to 10thk | H27: Hi tech | I27: 31.5 | J27: =F27/I27 -> 201.90476 | K27: =I27*6 -> 189 | L27: =IF(K27>E27,K27,IF(K27<E27,E27)) -> 189 | M27: =L27*J27 -> 38160 | P27: Dia 21.3 x 2.77 thk | R27: 0.289179 | W27: 0.289179
A28: 25 | B28: Rec Tube | C28: 200x150x 12thk | D28: YST 310 | E28: 945.25994 | F28: 10665 | H28: Hi tech | I28: 61.42 | J28: =F28/I28 -> 173.64051 | K28: =I28*6 -> 368.52 | L28: =IF(K28>E28,K28,IF(K28<E28,E28)) -> 945.25994 | M28: =L28*J28 -> 164135.42 | P28: Dia 30 | Q28: 13.35774 | W28: 13.35774
A29: 25 | B29: Rec Tube | C29: 150x50x 6thk | D29: YST 310 | E29: =GETPIVOTDATA("Gross Wt (kg)",$P$3,"Alt. Material","YST 310","IS Thk (mm)","150x50x 6thk ") -> 43.949136 | F29: 3610 | H29: Hi tech | I29: 17.71 | J29: =F29/I29 -> 203.83964 | K29: =I29*6 -> 106.26 | L29: =IF(K29>E29,K29,IF(K29<E29,E29)) -> 106.26 | M29: =L29*J29 -> 21660 | P29: Dia 33.4x 6.35 | R29: 111.28577 | W29: 111.28577
A30: 26 | B30: Sq. Tube | C30: 40x40x 5thk | D30: YST 310 | E30: 97.8406 | J30: 110 | L30: =IF(K30>E30,K30,IF(K30<E30,E30)) -> 97.8406 | M30: =L30*J30 -> 10762.466 | P30: Dia 60.3 x 3.91 thk | R30: 0.3039872 | W30: 0.3039872
A31: 27 | B31: Sq. Tube | C31: 50x50x 5thk | D31: YST 310 | E31: 159.52182 | J31: 110 | L31: =IF(K31>E31,K31,IF(K31<E31,E31)) -> 159.52182 | M31: =L31*J31 -> 17547.401 | P31: Dia 72 | Q31: 1.76 | W31: 1.76
A32: 28 | B32: Sq. Tube | C32: 80x80x 10thk | D32: YST 310 | E32: 29.49716 | F32: 2985 | G32: 80x80x 8thk | H32: Hi tech | I32: 21.98 | J32: =F32/I32 -> 135.80528 | K32: =I32*6 -> 131.88 | L32: =IF(K32>E32,K32,IF(K32<E32,E32)) -> 131.88 | M32: =L32*J32 -> 17910 | P32: Dia 76 | S32: 2.64 | W32: 2.64
C33: Total For Tubes | J33: =(M33/L33)*(1+12%) -> 192.75574 | L33: =SUM(L24:L32) -> 2652.5174 | M33: =SUM(M24:M32) -> 456507.11 | P33: ISMC 200 x 75 | U33: 1203.898 | W33: 1203.898
A34: 29 | B34: Pipe | C34: Dia 101.6 x 8.08 thk | D34: ASTM A106 GR.B | E34: 30.019986 | H34: Pipe Sind | J34: 90 | K34: =18.65*6 -> 111.9 | L34: =IF(K34>E34,K34,IF(K34<E34,E34)) -> 111.9 | M34: =L34*J34 -> 10071 | P34: NPB 450x190x67.16 | U34: 531.9072 | W34: 531.9072
A35: 30 | B35: Pipe | C35: Dia 114.3 x 8.56 thk | D35: ASTM A106 GR.B | E35: 30.851128 | H35: Pipe Sind | J35: 90 | K35: =22.32*6 -> 133.92 | L35: =IF(K35>E35,K35,IF(K35<E35,E35)) -> 133.92 | M35: =L35*J35 -> 12052.8 | P35: NPB 600x 220x 107.57 | U35: 1081.9821 | W35: 1081.9821
A36: 31 | B36: Pipe | C36: Dia 168.28 x 10.97thk | D36: ASTM A106 GR.B | E36: 176.03661 | H36: Pipe Sind | J36: 90 | K36: =42.56*6 -> 255.36 | L36: =IF(K36>E36,K36,IF(K36<E36,E36)) -> 255.36 | M36: =L36*J36 -> 22982.4 | P36: UPN 160 X 65 X 18.8 | U36: 1933.7454 | W36: 1933.7454
A37: 32 | B37: Pipe | C37: Dia 21.3 x 2.77 thk | D37: ASTM A106 GR.B | E37: 0.289179 | H37: Pipe Sind | J37: 150 | K37: =1.27*6 -> 7.62 | L37: =IF(K37>E37,K37,IF(K37<E37,E37)) -> 7.62 | M37: =L37*J37 -> 1143 | P37: UPN80 X 45 | V37: 166.13942 | W37: 166.13942
A38: 33 | B38: Pipe | C38: Dia 33.4x 6.35 | D38: ASTM A106 GR.B | E38: 111.28577 | H38: Pipe Sind | J38: 120 | K38: =4.24*6 -> 25.44 | L38: =IF(K38>E38,K38,IF(K38<E38,E38)) -> 111.28577 | M38: =L38*J38 -> 13354.292 | P38: Grand Total | Q38: 15.11774 | R38: 348.78666 | S38: 2.64 | T38: 2297.334 | U38: 9783.8645 | V38: 1489.1403 | W38: 13936.883
A39: 34 | B39: Pipe | C39: Dia 60.3 x 3.91 thk | D39: ASTM A106 GR.B | E39: 0.3039872 | H39: Pipe Sind | J39: 90 | K39: =5.44*6 -> 32.64 | L39: =IF(K39>E39,K39,IF(K39<E39,E39)) -> 32.64 | M39: =L39*J39 -> 2937.6
C40: Total For Pipe | J40: =(M40/L40)*(1+12%) -> 107.3131 | L40: =SUM(L34:L39) -> 652.72577 | M40: =SUM(M34:M39) -> 62541.092
A41: 35 | B41: Rod | C41: Dia 12 | D41: IS 2062 E250 A/BR | E41: 4.813523 | J41: 90
A42: 36 | B42: Rod | C42: Dia 72 | D42: AISI C1045 | E42: 1.76 | J42: 200
A43: 37 | B43: Rod | C43: Dia 76 | D43: BROWNING SCS-2 | E43: 2.64 | J43: 200
C44: Total | E44: =SUM(E2:E43) -> 13392.655
K45: =M45/L45 -> 157.03783 | L45: =SUM(L2:L44) -> 6610.4863 | M45: =SUM(M2:M44) -> 1038096.4

Sheet Welding Details
B2: Assy No. | C2: Item No. | D2: Weld Length | E2: No of Run | F2: No of Places | G2: Total Weld
