Workbook
Name a: #REF!
Name a: #REF!
Name a: '[1]BOM '!#REF!
Name a: #REF!
Name a_1: #REF!
Name a_1: #REF!
Name a_1: #REF!
Name b: #REF!
Name b: #REF!
Name b: #REF!

Sheet Customer Data 
A1: Part ID | B1: Description | C1: Usage
A2: AY30013 | B2: WELDMENT, PC4100 R2D SLAVE SKID, PC4100 | C2: 1
A3: AY30017 | B3: WELDMENT, FALSE FLOOR, PC4100 | C3: 2
A4: AY30018 | B4: WELDMENT, HINGED FLOOR, PC4100 | C4: 1
A5: AY30027 | B5: WELDMENT, HINGED FLOOR, PC4100 | C5: 23
A6: AY30062 | B6: WELDMENT, SAFETY BAR, PC4100 | C6: 1
A7: AY30084 | B7: HAND RAIL, WELDMENT, 42" CATWALK, PC4100 | C7: 4
A8: AY30107 | B8: WELDMENT,SKATE BODY, REVERSE VEE,PC4100 | C8: 1
A9: AY30130 | B9: WELDMENT, PC4100, 42' CATWALK, RAMP B | C9: 0
A10: AY30133 | B10: WELDMENT, RAMP RAIL, PC4100 | C10: 1
A11: AY30134 | B11: WLDMNT, RAMP, SHEAVE SUB B, PC4100 | C11: 1
A12: AY30144 | B12: WELDMENT, 30FT LIFT ARM, PC4100 | C12: 1
A13: AY30150 | B13: WELDMENT, SPEAR FRAME, PC4100 | C13: 1
... A16: AY51606 | B16: KIT, SHIPPING BRKTS, LONG,PC4000 | C16: 1

Sheet Quote Buggy Parts 
A1: RECURRING COST | D1: ITEM-1
D2: Assy. No | E2: Qty.
D3: ='BOM 42D CARRIER REAR_AY3016'!G3 -> AY30013 | E3: 5
A4: A. | B4: RM Cost | D4: Weight in Kg. | E4: Price in INR
A5: i. | B5: RM Gross Weight | D5: =Summary!G8 -> 228.15242
A6: ii. | B6: RM Net Weight | D6: =Summary!G9 -> 167.21302
A7: iii. | B7: Raw Material Cost | E7: =Summary!G13 -> 18585.923
A8: iv. | B8: Fastener and BOP | C8: No detail in Drg. | E8: 0
B9: TOTAL RM COST | E9: =SUM(E7:E8) -> 18585.923
D10: =(D5-D6)/D6 -> 0.36444171
A11: B. | B11: Process Cost
A12: i. | B12: Assy Cost | C12: 0 | E12: 0
A13: ii. | B13: Fabrication / Process Cost | C13: 0 | E13: =Summary!F33 -> 6034.8548
A14: iii. | B14: Paint | C14: 0 | E14: =D6*20 -> 3344.2604
A15: iv. | B15: Inspection and Testing | C15: 0 | E15: =D6*12 -> 2006.5562
A16: v. | B16: Packaging | C16: Canrig Scope | E16: 0
B17: TOTAL BASIC COST | E17: =SUM(E9:E16) -> 29971.594
A19: C. | B19: Fixed Cost
A20: i | B20: ICC Cost | C20: 0.015 | E20: =E22*$C$20 -> 627.63895
A21: ii | B21: Rejection | C21: 0.015 | E21: =E22*$C$21 -> 627.63895
B22: Sub Total | E22: =SUM(E20:E21)+E17 -> 41842.596
A24: D. | B24: Variable Cost
A25: i. | B25: Contingency / Warranty | C25: 0.02 | E25: =E28*$C$25 -> 1101.121
A26: ii. | B26: Overheads | C26: 0.1 | E26: =E28*$C$26 -> 5505.6048
A27: iii. | B27: Contribution / Profit | C27: 0.12 | E27: =E28*$C$27 -> 6606.7258
B28: Total Price | E28: =SUM(E22:E27) -> 55056.048
A30: F | B30: Transportation | C30: EX Works | E30: 0
B31: Total Price for X Parts | D31: =E3 -> 5 | E31: =SUM(E28:E30) -> 55056.048
B32: Total Cost Each Part | E32: =E31/E3 -> 11011.21
B34: Rate Per Gross Wt kg | E34: =E31/D5 -> 241.31258
B35: Rate Per Net Wt kg | E35: =E31/D6 -> 329.25695
B36: Internal Cal. Cost Per X parts | D36: =E3 -> 5 | E36: =Summary!F36 -> 27082.855
B37: Margin | E37: =E31-E36 -> 16295.896
B38: Margin % | E38: =(E31-E36)/E31 -> 0.29598739
A44: NON-RECURRING COST | D44: ITEM-1
A45: 1 | B45: ENGINEERING CHARGES | E45: =Summary!D51 -> 5000
A46: 2 | B46: DEVELOPMENT OF JIG AND FIXTURES (01 time) | E46: =Summary!D50+Summary!D52 -> 23961.295
B47: Sub Total | E47: =SUM(E45:E46) -> 28961.295
B48: Overheads | C48: 0.1 | E48: =E50*$C$48 -> 3712.9865
B49: Contribution / Profit | C49: 0.12 | E49: =E50*$C$49 -> 4455.5838
B50: Total | E50: =SUM(E47:E49) -> 37129.865
B51: NRC Cost Without 20% Margin | E51: =E50*80% -> 29703.892

Sheet Summary
A1: COSTING SHEET
A2: PRODUCT NAME:- | B2: ='BOM 42D CARRIER REAR_AY3016'!#REF! -> #REF! | E2: RFQ Ref.
A3: ITEM DRG NO | B3: ='BOM 42D CARRIER REAR_AY3016'!G3 -> AY30013 | E3: Total Quantity | F3: ='BOM 42D CARRIER REAR_AY3016'!K3 -> 1
A4: Total Net WT as per Drawing | C4: ='BOM 42D CARRIER REAR_AY3016'!N3 -> 4034 | I4: RM Details Assy. No
A5: COSTBREAKUP OF COMPONENT (QTY-01 No.) | I5: Type | J5: Drg. Material | K5: Material | L5: Size (thk) | M5: Net Wet(kg) | N5: Gross Weight (kg)
A6: RAW MATERIAL COST | I6: Plate | J6: ASTM A36/ Q235 | K6: IS 2062 E250 A/BO/BR | L6: 8 | M6: ='RM Details'!E4 -> 158.59462 | N6: ='RM Details'!F4 -> 218.0676
A7: SPEC | D7: IS 2062 E250 A/BO/BR | F7: ASTM A514 | I7: Plate | J7: ASTM A514/Q690 | K7: ASTM A514 | L7: 20 | M7: ='RM Details'!E5 -> 8.6184 | N7: ='RM Details'!F5 -> 10.084816
A8: GROSS WT. (KG) | D8: =N6 -> 218.0676 | F8: =N7 -> 10.084816 | G8: =SUM(B8:F8) -> 228.15242
A9: NET WT (KG) | D9: =M6 -> 158.59462 | F9: =M7 -> 8.6184 | G9: =SUM(B9:F9) -> 167.21302
A10: SCRAP (KG) | D10: =(D8-D9)*80% -> 47.578385 | F10: =(F8-F9)*80% -> 1.1731332 | G10: =(G8-G9)/G9 -> 0.36444171
A11: RM RATE (RS/KG) | D11: 85 | F11: 150 | G11: =SUMPRODUCT(B11:F11,B8:F8) -> 20048.468
A12: SCRAP RATE (RS/KG) | D12: 30 | F12: 30
A13: NET RM COST (RS) | D13: =(D8*D11)-(D10*D12) -> 17108.394 | F13: =(F8*F11)-(F10*F12) -> 1477.5285 | G13: =SUM(B13:F13) -> 18585.923
A14: TOTAL (RS) | B14: =SUM(B13:F13) -> 18585.923 | G14: =G13/G8 -> 81.462748
A15: BOP COST
A16: BOP COST (RS)
A17: TOTAL BOP | F17: =SUM(F16:F16) -> 0
A18: TOTAL OF RM + BOP (RS) | F18: =B14+F17 -> 18585.923
A19: PROCESS COST
A20: SPEC | B20: QTY | D20: RATE | F20: TOTAL COST
A21: LASER /PLASMA/PIPE - Cutting (Min.) | B21: ='BOM 42D CARRIER REAR_AY3016'!X3 -> 0 | D21: 50 | E21: Laser part | F21: =B21*D21 -> 0 | H21: =F21/$G$9 -> 0
A22: Machining (Hrs) | B22: ='BOM 42D CARRIER REAR_AY3016'!AB3/60 -> 3.9666667 | D22: 550 | F22: =B22*D22 -> 2181.6667 | H22: =F22/$G$9 -> 13.04723
A23: BENDING BY CNC BENDING (STROKE) | B23: ='BOM 42D CARRIER REAR_AY3016'!Z3 -> 9 | D23: 10 | F23: =B23*D23 -> 90 | H23: =F23/$G$9 -> 0.53823561
A24: MIG WELDING (MTR.) | B24: ='BOM 42D CARRIER REAR_AY3016'!AF3 -> 0 | D24: 250 | F24: =B24*D24 -> 0 | H24: =F24/$G$9 -> 0
A25: GRINDING/BUFFING & FINISHING (hrs) | B25: =B24/15 -> 0 | D25: 250 | F25: =B25*D25 -> 0 | H25: =F25/$G$9 -> 0
A26: INSPECTION & TESTING (HRS) | B26: =G9/95 -> 1.760137 | D26: 1200 | F26: =B26*D26 -> 2112.1644 | H26: =F26/$G$9 -> 12.631579
A27: STRESS RELIEVING | D27: 250 | F27: =B27*D27 -> 0 | G27: As Actual, If required | H27: =F27/$G$9 -> 0
A28: Shot Blasting | D28: 5 | F28: =D28*G9 -> 836.06509 | H28: =F28/$G$9 -> 5
A29: Hot Dip Galvanization | B29: 0 | D29: 50 | F29: =B29*D29 -> 0 | H29: =F29/$G$9 -> 0
A30: PAINTING (including material & Labor) | B30: ='BOM 42D CARRIER REAR_AY3016'!AI3 -> 0 | D30: 1250 | F30: =B30*D30 -> 0 | G30: No paint Detail Found | H30: =F30/$G$9 -> 0
A31: Stamping Cost (HRS) | B31: =15/60 -> 0.25 | D31: 250 | F31: =B31*D31 -> 62.5 | H31: =F31/$G$9 -> 0.37377473
A32: FE cost | D32: 4.5 | F32: =D32*G9 -> 752.45858 | H32: =F32/$G$9 -> 4.5
A33: TOTAL PROCESS COST OF PC | F33: =SUM(F21:F32) -> 6034.8548 | H33: =F33/$G$9 -> 36.090819
A34: TOTAL RM+BOP+PC | F34: =F18+F33 -> 24620.778
A35: OH + Contingency | E35: 0.1 | F35: =F34*E35 -> 2462.0778 | H35: =F35/$G$9 -> 14.724199
A36: Total Product Cost Without Profit | F36: =SUM(F34:F35) -> 27082.855 | H36: =F36/G9 -> 161.96619 | I36: =F36/G8 -> 118.7051
G39: Min.
A40: NOTES:- | F40: OTHER COST | G40: Min.
A41: No BOP found in the Drawing Details
A42: Stress relieveing NOT FOUND ON PRINTS, IF REQUIRED | F42: As Actual
A45: NRC COST BREAKUP
A46: Fixture Details | B46: Approx Wt /Days | C46: Rate | D46: Cost
A47: Tacking Fixture main Frame | B47: =20*2000*500*0.00000785 -> 157 | C47: 100 | D47: =B47*C47 -> 15700
A48: Testing Templates | B48: =6*1000*1000*0.00000785 -> 47.1 | C48: 100 | D48: =B48*C48 -> 4710
A49: FE COST | B49: =B47+B48 -> 204.1 | C49: 4.5 | D49: =B49*C49 -> 918.45
A50: SUB TOTAL | D50: =SUM(D47:D49) -> 21328.45
A51: Development and Engg | B51: 2 | C51: =75000/30 -> 2500 | D51: =B51*C51 -> 5000
A52: OH + Contingency | C52: 0.1 | D52: =(D50+D51)*C52 -> 2632.845
A53: Total Cost | D53: =SUM(D50:D52) -> 28961.295

Sheet BOM 42D CARRIER REAR_AY3016
A1: S.No | C1: Level | G1: BOM KIT, SHIPPING BRKTS, LONG,PC4000_AY51606 | M1: 0.4536 | S1: 25.4 | V1: 0.1 | W1: 0.15 | AC1: 550 | AF1: 0.2
B2: Assembly | C2: L1 | D2: L2 | E2: L3 | G2: Drawing No. | H2: Rev | I2: Description | J2: Qty. | K2: Total Qty. | L2: Net Wt. LBS | M2: Net Weight (Kg) | N2: Total Weight (Kg) | O2: Type | P2: DRG. Material | Q2: Alt. Material | R2: IS Thk (Inch) | S2: IS Thk (mm) | T2: Width | U2: Length | V2: Gross Wt (kg) | W2: Cutting Perimeter | X2: Cutting Time | Y2: Cutting Cost | Z2: No. of bends | AA2: Bending Details | AB2: Machining Time (min) | AC2: Machining Cost | AD2: Other Process | AE2: Other process Cost | AF2: Welding Length (M) | AG2: Remarks | AH2: Paint | AI2: Surface Area SQM
A3: 1 | B3: AY30011 | C3: 0 | G3: AY30013 | H3: A | I3: WELDMENT, PC4100 R2D SLAVE SKID, PC4100 | J3: =VLOOKUP(G3,'[2]Customer Data '!$A$1:$C$16,3,0) -> 1 | K3: =J3 -> 1 | L3: 7057.6 | M3: 4034 | N3: =M3*K3 -> 4034 | O3: Main Assy. | V3: =SUM(V4:V91) -> 160.05836 | X3: =SUMPRODUCT(X4:X91,$K$4:$K$91) -> 0 | Y3: =SUM(Y4:Y91) -> 0 | Z3: =SUMPRODUCT(Z4:Z91,$K$4:$K$91) -> 9 | AB3: =SUMPRODUCT(AB4:AB91,$K$4:$K$91) -> 238 | AC3: =SUM(AC4:AC91) -> 0 | AI3: =SUM(AI4:AI22) -> 0
A4: 2 | B4: AY30011 | C4: 1 | D4: * | E4: * | G4: AY30012 | I4: WELDMENT, R2D CATWALK, LEV 2, PC4100 | J4: 1 | K4: =J4*$K$3 -> 1 | M4: 3370 | N4: =M4*K4 -> 3370 | O4: Sub Assy | P4: -
A5: 3 | B5: AY30011 | D5: 1.1 | G5: AY30011 | H5: A | I5: WELDMENT, R2D CATWALK, LEV 1, PC4100 | J5: 1 | K5: =J5*$K$4 -> 1 | L5: 7057.6 | M5: 3208 | N5: =M5*K5 -> 3208 | O5: Sub Assy. | P5: - | AI5: =SUM(AI6:AI33) -> 0
A6: 4 | B6: AY30011 | E6: 1.1.1 | G6: AY30010 | H6: A | I6: WELDMENT, CATWALK ODS BEAM, R2D, PC4100 | J6: 1 | K6: =J6*$K$5 -> 1 | M6: 679 | N6: =M6*K6 -> 679 | O6: Sub Assy. | P6: -
A7: 5 | B7: AY30011 | F7: 1.1.1.1 | G7: DT34393 | I7: REAR ODS BEAM WEB | J7: 1 | K7: =J7*$K$6 -> 1 | M7: 339 | N7: =M7*K7 -> 339 | O7: Plate | P7: A572 Gr. 50 | S7: 10 | T7: 1022 | U7: 5080
A8: 6 | B8: AY30011 | F8: 1.1.1.2 | G8: DT34394 | I8: PLATE, OUTER ODS BEAM TOP FLANGE, R2D, PC4100 | J8: 1 | K8: =J8*$K$6 -> 1 | M8: 76 | N8: =M8*K8 -> 76 | O8: Plate | P8: A572 Gr. 50 | S8: 12 | T8: 180 | U8: 4775
A9: 7 | B9: AY30011 | F9: 1.1.1.3 | G9: DT34395 | I9: PLATE, OUTER BEAM BACK ANGLE CAP, PC4100 | J9: 1 | K9: =J9*$K$6 -> 1 | M9: 9 | N9: =M9*K9 -> 9 | O9: Plate | P9: A572 Gr. 50 | S9: 12 | T9: 180 | U9: 572
A10: 8 | B10: AY30011 | F10: 1.1.1.4 | G10: DT34315 | I10: PLATE, OUTER FRONT BEAM NOSE CAP, PC4100 | J10: 1 | K10: =J10*$K$6 -> 1 | M10: 8 | N10: =M10*K10 -> 8 | O10: Plate | P10: A36/S275JR/SA 516 GR.70 | S10: 20 | T10: 200 | U10: 324
A11: 9 | B11: AY30011 | F11: 1.1.1.5 | G11: DT34396 | I11: PLATE, REAR OUTER BEAM ANGLE CAP, PC4100 | J11: 1 | K11: =J11*$K$6 -> 1 | M11: 37 | N11: =M11*K11 -> 37 | O11: Plate | P11: ASTM A572 Gr. 50 / S355JR | S11: 10 | T11: 100 | U11: 4702
A12: 10 | B12: AY30011 | F12: 1.1.1.6 | G12: DT34397 | I12: PLATE, ANGLE CAP, PC4100 | J12: 1 | K12: =J12*$K$6 -> 1 | M12: 0.8 | N12: =M12*K12 -> 0.8 | O12: Plate | P12: A572 Gr. 50 | S12: 10 | T12: 100 | U12: 191
A13: 11 | B13: AY30011 | F13: 1.1.1.7 | G13: DT34327 | I13: CATWALK CONNECTION PLATE, PC4100 | J13: 1 | K13: =J13*$K$6 -> 1 | M13: 11.6 | N13: =M13*K13 -> 11.6 | O13: Plate | P13: A36/S275JR/SA 516 GR.70 | S13: 40 | T13: 200 | U13: 200 | AB13: 10
A14: 12 | B14: AY30011 | F14: 1.1.1.8 | G14: DT34328 | I14: PLATE, CARRIER CONNECTION PLATE GUSSET, PC4100 | J14: 1 | K14: =J14*$K$6 -> 1 | M14: 4 | N14: =M14*K14 -> 4 | O14: Plate | P14: A36/S275JR/SA 516 GR.70 | S14: 25 | T14: 165 | U14: 180
A15: 13 | B15: AY30011 | F15: 1.1.1.9 | G15: DT34378 | I15: PIPE, 33 OD x 21 ID X 51 L | J15: 4 | K15: =J15*$K$6 -> 4 | M15: =0.2*0.4536 -> 0.09072 | N15: =M15*K15 -> 0.36288 | O15: Pipe | P15: ASTM A106 GR.B | S15: Dia 33 x 6 thk | U15: 51
A16: 14 | B16: AY30011 | F16: 1.1.1.10 | G16: DT34398 | I16: REAR CATWALK CONNECTION BLOCK, PC4100 | J16: 2 | K16: =J16*$K$6 -> 2 | M16: 19 | N16: =M16*K16 -> 38 | O16: Plate | P16: ASTM A572 Gr. 50 / S355JR | S16: 50 | T16: 220 | U16: 334 | AB16: 45
A17: 15 | B17: AY30011 | F17: 1.1.1.11 | G17: - | I17: BAR, FLAT, 200 X 20 X 4777 LG | J17: 1 | K17: =J17*$K$6 -> 1 | M17: =S17*T17*U17*0.00000785 -> 149.9978 | N17: =M17*K17 -> 149.9978 | O17: Plate | P17: A36/S275JR/SA 516 GR.70 | S17: 20 | T17: 200 | U17: 4777
A18: 16 | B18: AY30011 | F18: 1.1.1.12 | G18: - | I18: BAR, FLAT, 75 x 12 x 381 LG | J18: 2 | K18: =J18*$K$6 -> 2 | M18: =S18*T18*U18*0.00000785 -> 2.691765 | N18: =M18*K18 -> 5.38353 | O18: Plate | P18: A36/S275JR/SA 516 GR.70 | S18: 12 | T18: 75 | U18: 381
A19: 17 | B19: AY30011 | E19: 1.1.2 | G19: AY30009 | I19: WELDMENT, CATWALK DS BEAM, R2D, PC4100 | J19: 1 | K19: =J19*$K$5 -> 1 | M19: 667 | N19: =M19*K19 -> 667 | O19: Sub Assy. | P19: SEE BOM
A20: 18 | B20: AY30011 | F20: 1.1.2.1 | G20: DT34400 | I20: REAR DS BEAM WEB, R2D, PC4100 | J20: 1 | K20: =J20*$K$19 -> 1 | M20: 321 | N20: =M20*K20 -> 321 | O20: Plate | P20: A572 Gr. 50 | S20: 10 | T20: 1022 | U20: 5080
A21: 19 | B21: AY30011 | F21: 1.1.2.2 | G21: DT34401 | I21: PLATE, OUTER BEAM D5 TOP FLANGE, R2D, PC4100 | J21: 1 | K21: =J21*$K$19 -> 1 | M21: 83 | N21: =M21*K21 -> 83 | O21: Plate | P21: A572 Gr. 50 | S21: 12 | T21: 180 | U21: 4775
A22: 20 | B22: AY30011 | F22: 1.1.2.3 | G22: DT34395 | I22: PLATE, OUTER BEAM BACK ANGLE CAP, PC4100 | J22: 1 | K22: =J22*$K$19 -> 1 | M22: 9 | N22: =M22*K22 -> 9 | O22: Plate | P22: A572 Gr. 50 | S22: 12 | T22: 180 | U22: 572
A23: 21 | B23: AY30011 | F23: 1.1.2.4 | G23: DT34315 | I23: PLATE, OUTER FRONT BEAM NOSE CAP, PC4100 | J23: 1 | K23: =J23*$K$19 -> 1 | M23: 8 | N23: =M23*K23 -> 8 | O23: Plate | P23: A36/S275JR/SA 516 GR.70 | S23: 20 | T23: 200 | U23: 324
A24: 22 | B24: AY30011 | F24: 1.1.2.5 | G24: DT34396 | I24: PLATE, REAR OUTER BEAM ANGLE CAP, PC4100 | J24: 1 | K24: =J24*$K$19 -> 1 | M24: 37 | N24: =M24*K24 -> 37 | O24: Plate | P24: ASTM A572 Gr. 50 / S355JR | S24: 10 | T24: 100 | U24: 4702
A25: 23 | B25: AY30011 | F25: 1.1.2.6 | G25: DT34397 | I25: PLATE, ANGLE CAP, PC4100 | J25: 1 | K25: =J25*$K$19 -> 1 | M25: 0.8 | N25: =M25*K25 -> 0.8 | O25: Plate | P25: A572 Gr. 50 | S25: 10 | T25: 100 | U25: 191
A26: 24 | B26: AY30011 | F26: 1.1.2.7 | G26: DT34327 | I26: CATWALK CONNECTION PLATE, PC4100 | J26: 1 | K26: =J26*$K$19 -> 1 | M26: 11.6 | N26: =M26*K26 -> 11.6 | O26: Plate | P26: A36/S275JR/SA 516 GR.70 | S26: 40 | T26: 200 | U26: 200 | AB26: 10
A27: 25 | B27: AY30011 | F27: 1.1.2.8 | G27: DT34328 | I27: PLATE, CARRIER CONNECTION PLATE GUSSET, PC4100 | J27: 1 | K27: =J27*$K$19 -> 1 | M27: 4 | N27: =M27*K27 -> 4 | O27: Plate | P27: A36/S275JR/SA 516 GR.70 | S27: 25 | T27: 165 | U27: 180
A28: 26 | B28: AY30011 | F28: 1.1.2.9 | G28: DT34398 | I28: REAR CATWALK CONNECTION BLOCK, PC4100 | J28: 2 | K28: =J28*$K$19 -> 2 | M28: 19 | N28: =M28*K28 -> 38 | O28: Plate | P28: ASTM A572 Gr. 50 / S355JR | S28: 50 | T28: 220 | U28: 334 | AB28: 45
A29: 27 | B29: AY30011 | F29: 1.1.2.10 | G29: - | I29: BAR, FLAT, 200 X 20 X 4777 LG | J29: 1 | K29: =J29*$K$19 -> 1 | M29: =S29*T29*U29*0.00000785 -> 149.9978 | N29: =M29*K29 -> 149.9978 | O29: Plate | P29: A36/S275JR/SA 516 GR.70 | S29: 20 | T29: 200 | U29: 4777
A30: 28 | B30: AY30011 | F30: 1.1.2.11 | G30: - | I30: PIPE, 1/2" SCH 40 x 1035 LG | J30: 2 | K30: =J30*$K$19 -> 2 | M30: =1.27*U30/1000 -> 0.131445 | N30: =M30*K30 -> 0.26289 | O30: Pipe | P30: A.S.T.M. A106 GR.B | S30: Dia 21.3 x 2.77 thk | U30: 103.5
A31: 29 | B31: AY30011 | F31: 1.1.2.12 | G31: - | I31: UNISTRUT, 41.3 x 22.2 x 457 LG | J31: 2 | K31: =J31*$K$19 -> 2 | N31: =M31*K31 -> 0 | O31: BOP Unistruct | P31: G40.21-44W / A572 G50
A32: 30 | B32: AY30011 | F32: 1.1.2.13 | G32: DT34399 | I32: PLATE, SAFETY BAR HOLDER, PC4100 | J32: 2 | K32: =J32*$K$19 -> 2 | M32: 2 | N32: =M32*K32 -> 4 | O32: Plate | P32: A572 Gr. 50 | S32: 10 | T32: 210 | U32: 210
A33: 31 | B33: AY30011 | E33: 1.1.3 | G33: DT34313 | I33: PLATE, ROLL BAR END CAP, PC4100 | J33: 2 | K33: =J33*$K$5 -> 2 | M33: 3.4 | N33: =M33*K33 -> 6.8 | O33: Plate | P33: A572 Gr. 50 | S33: 12 | T33: 200 | U33: 240
A34: 32 | B34: AY30011 | E34: 1.1.4 | G34: DT34402 | I34: PLATE, BACK MID STOP RIB, PC4100 | J34: 4 | K34: =J34*$K$5 -> 4 | M34: 15 | N34: =M34*K34 -> 60 | O34: Plate | P34: A572 Gr. 50 | S34: 12 | T34: 373 | U34: 789
A35: 33 | B35: AY30011 | E35: 1.1.5 | G35: DT34403 | I35: PIPE, CABLE ROLL, PC4100 | J35: 2 | K35: =J35*$K$5 -> 2 | M35: 5 | N35: =M35*K35 -> 10 | O35: Sub Assy.
A36: 34 | B36: AY30011 | F36: 1.1.5.1 | I36: PIPE, 4SCH80 X 254 LG | J36: 1 | K36: =J36*$K$35 -> 2 | M36: =M35-M37 -> 4.6516484 | N36: =M36*K36 -> 9.3032968 | O36: Pipe | P36: A.S.T.M. A106 GR.B | S36: Dia 102x8thk | U36: 255 | AB36: 5
A37: 35 | B37: AY30011 | F37: 1.1.5.2 | I37: PLATE, 86 X 86X 6 | J37: 1 | K37: =J37*$K$35 -> 2 | M37: =S37*T37*U37*0.00000785 -> 0.3483516 | N37: =M37*K37 -> 0.6967032 | O37: Plate | P37: A.S.T.M. A106 GR.B | S37: 6 | T37: 86 | U37: 86
A38: 36 | B38: AY30011 | E38: 1.1.6 | G38: DT34404 | I38: W-BEAM 600 X 220 X 4572 LG | J38: 2 | K38: =J38*$K$5 -> 2 | M38: 498 | N38: =M38*K38 -> 996 | O38: Beam | P38: A992 / A572 | S38: W-BEAM 600 X 220 | U38: 4572
A39: 37 | B39: AY30011 | E39: 1.1.7 | G39: DT34405 | I39: CARRIER RAIL BOTTOM STIFFNER, DS, PC4100 | J39: 1 | K39: =J39*$K$5 -> 1 | M39: 3 | N39: =M39*K39 -> 3 | O39: Channel | P39: A36/S275JR | S39: UPN80 X 45 | U39: 410
A40: 38 | B40: AY30011 | E40: 1.1.8 | G40: DT34406 | I40: CARRIER RAIL BOTTOM STIFFNER, ODS, PC4100 | J40: 1 | K40: =J40*$K$5 -> 1 | M40: 3 | N40: =M40*K40 -> 3 | O40: Channel | P40: A36/S275JR | S40: UPN80 X 45 | U40: 410
A41: 39 | B41: AY30011 | E41: 1.1.9 | G41: - | I41: CHANNEL, UPN200x2198 LG | J41: 7 | K41: =J41*$K$5 -> 7 | M41: =25.3*U41/1000 -> 55.6094 | N41: =M41*K41 -> 389.2658 | O41: Channel | P41: A572 Gr. 50 | S41: UPN 200x75 | U41: 2198 | V41: =25.3*U41/1000 -> 55.6094
A42: 40 | B42: AY30011 | E42: 1.1.10 | G42: DT34390 | I42: PLATE, BOTTOM PLATE, JUNK BOX, PC4100 | J42: 1 | K42: =J42*$K$5 -> 1 | M42: 27.7 | N42: =M42*K42 -> 27.7 | O42: Plate | P42: ASTM A572 Gr. 50 / A516 Gr.70 / S355JR | S42: 6 | T42: 720 | U42: 819 | Z42: 1 | AA42: R6
A43: 41 | B43: AY30011 | E43: 1.1.11 | G43: - | I43: CHANNEL, UPN80.000X 4672.000 LG | J43: 1 | K43: =J43*$K$5 -> 1 | M43: =8.64*U43/1000 -> 40.36608 | N43: =M43*K43 -> 40.36608 | O43: Channel | P43: A36/S275JR | S43: UPN80 X 45 | U43: 4672 | V43: =8.64*U43/1000 -> 40.36608
A44: 42 | B44: AY30011 | E44: 1.1.12 | G44: - | I44: CHANNEL, UPN80X1143 LG | J44: 5 | K44: =J44*$K$5 -> 5 | M44: =8.64*U44/1000 -> 9.87552 | N44: =M44*K44 -> 49.3776 | O44: Channel | P44: A36/S275JR | S44: UPN80 X 45 | U44: 1143 | V44: =8.64*U44/1000 -> 9.87552
A45: 43 | B45: AY30011 | E45: 1.1.13 | G45: UPN80x4623 | I45: CHANNEL, UPN80.000X4623.000 LG | J45: 1 | K45: =J45*$K$5 -> 1 | M45: =8.64*U45/1000 -> 39.94272 | N45: =M45*K45 -> 39.94272 | O45: Channel | P45: A36/S275JR | S45: UPN80 X 45 | U45: 4623 | V45: =8.64*U45/1000 -> 39.94272
A46: 44 | B46: AY30011 | E46: 1.1.14 | G46: FB45X6X329 | I46: BAR, FLAT, 45.000 X 6.000 X 329.406 LG | J46: 1 | K46: =J46*$K$5 -> 1 | M46: =S46*T46*U46*0.00000785 -> 0.6973155 | N46: =M46*K46 -> 0.6973155 | O46: Plate | P46: A36/S275JR/SA 516 GR.70 | S46: 6 | T46: 45 | U46: 329
A47: 45 | B47: AY30011 | E47: 1.1.15 | G47: - | I47: PI 6" SCH XS X 2388mm | J47: 1 | K47: =J47*$K$5 -> 1 | M47: =42.56*U47/1000 -> 101.63328 | N47: =M47*K47 -> 101.63328 | O47: Pipe | P47: G40.21-44W | S47: Dia 168.28 x 10.97thk | U47: 2388
A48: 46 | B48: AY30011 | E48: 1.1.16 | G48: FB45X6X280 | I48: BAR, FLAT, 45.000 X 6.000 X 280.194 LG | J48: 1 | K48: =J48*$K$5 -> 1 | M48: =S48*T48*U48*0.00000785 -> 0.59346 | N48: =M48*K48 -> 0.59346 | O48: Plate | P48: A36/S275JR/SA 516 GR.70 | S48: 6 | T48: 45 | U48: 280
A49: 47 | B49: AY30011 | E49: 1.1.17 | G49: DT34389 | I49: PLATE, FRONT LIP, JUNK BOX, PC4100 | J49: 1 | K49: =J49*$K$5 -> 1 | M49: 4.1 | N49: =M49*K49 -> 4.1 | O49: Plate | P49: ASTM A572 Gr. 50 / A516 Gr.70 / S355JR | S49: 6 | T49: 126 | U49: 691 | Z49: 1 | AA49: Die Bending
A50: 48 | B50: AY30011 | E50: 1.1.18 | G50: UPN80X1651 | I50: CHANNEL, UPN80.000 LG | J50: 1 | K50: =J50*$K$5 -> 1 | M50: =8.64*U50/1000 -> 14.26464 | N50: =M50*K50 -> 14.26464 | O50: Channel | P50: A36/S275JR | S50: UPN80 X 45 | U50: 1651 | V50: =8.64*U50/1000 -> 14.26464
A51: 49 | B51: AY30011 | E51: 1.1.19 | G51: FB80X6X4634 | I51: BAR, FLAT, 80.000 X 6.000 X 4634.000 LG | J51: 1 | K51: =J51*$K$5 -> 1 | M51: =S51*T51*U51*0.00000785 -> 17.460912 | N51: =M51*K51 -> 17.460912 | O51: Plate | P51: A36/S275JR/SA 516 GR.70 | S51: 6 | T51: 80 | U51: 4634
A52: 50 | B52: AY30011 | E52: 1.1.20 | G52: FB80X6X4585 | I52: BAR, FLAT, 80.000 X 6.000 X 4585.000 LG | J52: 1 | K52: =J52*$K$5 -> 1 | M52: =S52*T52*U52*0.00000785 -> 17.27628 | N52: =M52*K52 -> 17.27628 | O52: Plate | P52: A36/S275JR/SA 516 GR.70 | S52: 6 | T52: 80 | U52: 4585
A53: 51 | B53: AY30011 | E53: 1.1.21 | G53: AY30006.002 | I53: BAR, FLAT, 5 X 38 X 67 LG | J53: 2 | K53: =J53*$K$5 -> 2 | M53: =S53*T53*U53*0.00000785 -> 0.0999305 | N53: =M53*K53 -> 0.199861 | O53: Plate | P53: A36/S275JR/SA 516 GR.70 | S53: 5 | T53: 38 | U53: 67
A54: 52 | B54: AY30011 | E54: 1.1.22 | G54: DT34392 | I54: PLATE, LEFT SIDE WALL, JUNK BOX, PC4100 | J54: 1 | K54: =J54*$K$5 -> 1 | M54: 28.6 | N54: =M54*K54 -> 28.6 | O54: Plate | P54: ASTM A572 Gr. 50 / A516 Gr.70 / S355JR | S54: 6 | T54: 630 | U54: 967 | Z54: 3 | AA54: R6
A55: 53 | B55: AY30011 | E55: 1.1.23 | G55: DT34391 | I55: PLATE, BACK LIP, JUNK BOX, PC4100 | J55: 1 | K55: =J55*$K$5 -> 1 | M55: 4 | N55: =M55*K55 -> 4 | O55: Plate | P55: ASTM A572 Gr. 50 / A516 Gr.70 / S355JR | S55: 6 | T55: 119 | U55: 691 | Z55: 2 | AA55: R6
A56: 54 | B56: AY30011 | E56: 1.1.24 | G56: DT34388 | I56: PLATE, RIGHT SIDE WALL, JUNK BOX, PC4100 | J56: 1 | K56: =J56*$K$5 -> 1 | M56: 23 | N56: =M56*K56 -> 23 | O56: Plate | P56: ASTM A572 Gr. 50 / A516 Gr.70 / S355JR | S56: 6 | T56: 630 | U56: 802
A57: 55 | B57: AY30011 | E57: 1.1.25 | G57: DT34387 | I57: PLATE, BOTTOM PLATE, JUNK BOX, PC4100 | J57: 1 | K57: =J57*$K$5 -> 1 | M57: 9 | N57: =M57*K57 -> 9 | O57: Plate | P57: ASTM A572 Gr. 50 / A516 Gr.70 / S355JR | S57: 6 | T57: 365.13 | U57: 526.8
A58: 56 | B58: AY30011 | E58: 1.1.26 | G58: M11504 | I58: FLANGE, SCULLY, 3/4" NPT | J58: 1 | K58: =J58*$K$5 -> 1 | N58: =M58*K58 -> 0 | O58: BOP | P58: CARBON STEEL
A59: 57 | B59: AY30011 | E59: 1.1.27 | G59: DT34314 | I59: PLATE, CROSS CHANNEL GUSSET, PC4100 | J59: 10 | K59: =J59*$K$5 -> 10 | M59: 1.8 | N59: =M59*K59 -> 18 | O59: Plate | P59: A572 Gr. 50 | S59: 10 | T59: 100 | U59: 254
A60: 58 | B60: AY30011 | D60: 1.2 | G60: DT34325 | I60: PLATE, ROLL SUPPORT, PC4100 | J60: 4 | K60: =J60*$K$4 -> 4 | M60: 2 | N60: =M60*K60 -> 8 | O60: Plate | P60: A572 Gr. 50 | S60: 10 | T60: 200 | U60: 200
A61: 59 | B61: AY30011 | D61: 1.3 | G61: DT34333 | I61: MID FLOOR HANGER FRONT, PC4100 | J61: 7 | K61: =J61*$K$4 -> 7 | M61: 5 | N61: =M61*K61 -> 35 | O61: Plate | P61: A572 Gr. 50 | S61: 10 | T61: 113 | U61: 745
A62: 60 | B62: AY30011 | D62: 1.4 | G62: DT34386 | I62: FLOOR, WIDE HANGER, PC4100 | J62: 2 | K62: =J62*$K$4 -> 2 | M62: 17 | N62: =M62*K62 -> 34 | O62: Plate | P62: A36 / S275JR / SA 516 GR.70 | S62: 40 | T62: 87 | U62: 813
A63: 61 | B63: AY30011 | D63: 1.5 | G63: DT34385 | I63: HSS, HORIZONTAL ALIGNER, PC4100 | J63: 2 | K63: =J63*$K$4 -> 2 | M63: 11 | N63: =M63*K63 -> 22 | O63: Sub Assy. | P63: ASTM A572 Gr. 50 / A516 Gr.70 / S355JR
A64: 62 | B64: AY30011 | E64: 1.5.1 | I64: HSS, 80 X 80 X 10 LG | J64: 1 | K64: =J64*$K$63 -> 2 | M64: =21.98*U64/1000 -> 13.4078 | N64: =M64*K64 -> 26.8156 | O64: Sq. Tube | P64: A36/S275JR | S64: 80x80x 10thk | U64: 610
A65: 63 | B65: AY30011 | E65: 1.5.2 | I65: PLATE, 97X60X6 | J65: 2 | K65: =J65*$K$63 -> 4 | M65: =S65*T65*U65*0.00000785 -> 0.274122 | N65: =M65*K65 -> 1.096488 | O65: Plate | P65: ASTM A572 Gr. 50 / A516 Gr.70 / S355JR | S65: 6 | T65: 60 | U65: 97
A66: 64 | B66: AY30011 | D66: 1.6 | G66: — | I66: BAR, FLAT, 51 X 25 X 400 LG | J66: 2 | K66: =J66*$K$4 -> 2 | M66: =S66*T66*U66*0.00000785 -> 4.0035 | N66: =M66*K66 -> 8.007 | O66: Plate | P66: A36 / S275JR / SA 516 GR.70 | S66: 25 | T66: 51 | U66: 400
A67: 65 | B67: AY30011 | D67: 1.7 | G67: — | I67: PIPE, 4 SCH 80 X 628 LG | J67: 2 | K67: =J67*$K$4 -> 2 | M67: =22.33*U67/1000 -> 14.02324 | N67: =M67*K67 -> 28.04648 | O67: Pipe | P67: ASTM A106 GR.B | S67: Dia 114.3 x 8.56 thk | U67: 628
A68: 66 | B68: AY30011 | D68: 1.8 | G68: — | I68: UNISTRUCT, 41 X 22 X 368 LG | J68: 2 | K68: =J68*$K$4 -> 2 | N68: =M68*K68 -> 0 | O68: BOP | P68: ASTM A572 Gr. 50 / S355JR
A69: 67 | B69: AY30011 | D69: 1.9 | G69: DT34360 | I69: FLOOR, WIDE HANGER, PC4100 | J69: 2 | K69: =J69*$K$4 -> 2 | M69: 16 | N69: =M69*K69 -> 32 | O69: Plate | P69: A36 / S275JR / SA 516 GR.70 | S69: 40 | T69: 112 | U69: 813
A70: 68 | B70: AY30011 | C70: 2 | G70: DT34384 | I70: WELDMENT, PANEL GUARD, PC4100 | J70: 1 | K70: =J70*$K$3 -> 1 | M70: 20.45 | N70: =M70*K70 -> 20.45 | O70: Sub Assy.
A71: 69 | B71: AY30011 | D71: 2.1 | I71: HSS, 50 X 50 X 5 X 184 LG | J71: 4 | K71: =J71*$K$70 -> 4 | M71: =7.07*U71/1000 -> 1.30088 | N71: =M71*K71 -> 5.20352 | O71: Sq. Tube | P71: ASTM A516 Gr. 70/S275JR | S71: 50x50x 5thk | U71: 184
A72: 70 | B72: AY30011 | D72: 2.2 | I72: HSS, 50 X 50 X 5 X 558 LG | J72: 2 | K72: =J72*$K$70 -> 2 | M72: =7.07*U72/1000 -> 3.94506 | N72: =M72*K72 -> 7.89012 | O72: Sq. Tube | P72: ASTM A516 Gr. 70/S275JR | S72: 50x50x 5thk | U72: 558 | AB72: 2
A73: 71 | B73: AY30011 | D73: 2.3 | I73: HSS, 50 X 50 X 5 X 520 LG | J73: 2 | K73: =J73*$K$70 -> 2 | M73: =7.07*U73/1000 -> 3.6764 | N73: =M73*K73 -> 7.3528 | O73: Sq. Tube | P73: ASTM A516 Gr. 70/S275JR | S73: 50x50x 5thk | U73: 520 | AB73: 2
A74: 72 | B74: AY30011 | C74: 3 | G74: DT34383 | I74: PLATE, SLAVE SKID CHANNEL CAP, PC4100 | J74: 2 | K74: =J74*$K$3 -> 2 | M74: 6.7 | N74: =M74*K74 -> 13.4 | O74: Plate | P74: A572 Gr. 50 | S74: 10 | T74: 121 | U74: 708
A75: 73 | B75: AY30011 | C75: 4 | G75: DT34381 | I75: HSS, RIGHT SIDE LASER POST, PC4100 | J75: 1 | K75: =J75*$K$3 -> 1 | M75: 10 | N75: =M75*K75 -> 10 | O75: Sub Assy.
A76: 74 | B76: AY30011 | D76: 4.1 | I76: PLATE, 116X76X6 | J76: 1 | K76: =J76*$K$75 -> 1 | M76: =S76*T76*U76*0.00000785 -> 0.4152336 | N76: =M76*K76 -> 0.4152336 | O76: Plate | P76: ASTM A572 Gr. 50 / A516 Gr.70 / S355JR | S76: 6 | T76: 76 | U76: 116
A77: 75 | B77: AY30011 | D77: 4.2 | I77: HSS,100 X 80 X 5X 864 LG | J77: 1 | K77: =J77*$K$75 -> 1 | M77: =13.35*U77/1000 -> 11.5344 | N77: =M77*K77 -> 11.5344 | O77: Rec. Tube | P77: A36 / S275JR | S77: 100x80x 5thk | U77: 864 | AB77: 10
A78: 76 | B78: AY30011 | C78: 5 | G78: DT34382 | I78: HSS, LEFT SIDE LASER POST, PC4100 | J78: 1 | K78: =J78*$K$3 -> 1 | M78: 10 | N78: =M78*K78 -> 10 | O78: Sub Assy.
A79: 77 | B79: AY30011 | D79: 5.1 | I79: PLATE, 116X76X6 | J79: 1 | K79: =J79*$K$78 -> 1 | M79: =S79*T79*U79*0.00000785 -> 0.4152336 | N79: =M79*K79 -> 0.4152336 | O79: Plate | P79: ASTM A572 Gr. 50 / A516 Gr.70 / S355JR | S79: 6 | T79: 76 | U79: 116
A80: 78 | B80: AY30011 | D80: 5.2 | I80: HSS,100 X 80 X 5X 864 LG | J80: 1 | K80: =J80*$K$78 -> 1 | M80: =13.35*U80/1000 -> 11.5344 | N80: =M80*K80 -> 11.5344 | O80: Rec. Tube | P80: A36 / S275JR | S80: 100x80x 5thk | U80: 864 | AB80: 10
A81: 79 | B81: AY30011 | C81: 6 | G81: — | I81: CHANNEL, UPN200 X 464 LG | J81: 3 | K81: =J81*$K$3 -> 3 | M81: =25.3*U81/1000 -> 11.7392 | N81: =M81*K81 -> 35.2176 | O81: Channel | P81: A572 Gr. 50 | S81: UPN 200x75 | U81: 464
A82: 80 | B82: AY30011 | C82: 7 | G82: — | I82: CHANNEL, UPN200 X 4321.175 LG | J82: 3 | K82: =J82*$K$3 -> 3 | M82: =25.3*U82/1000 -> 109.3466 | N82: =M82*K82 -> 328.0398 | O82: Channel | P82: A572 Gr. 50 | S82: UPN 200x75 | U82: 4322
A83: 81 | B83: AY30011 | C83: 8 | G83: — | I83: BAR, FLAT, 30 X 10 X 622 LG | J83: 4 | K83: =J83*$K$3 -> 4 | M83: =S83*T83*U83*0.00000785 -> 1.46481 | N83: =M83*K83 -> 5.85924 | O83: Plate | P83: A572 Gr. 50 | S83: 10 | T83: 30 | U83: 622
A84: 82 | B84: AY30011 | C84: 9 | G84: — | I84: COUPLING, HALF, 3/4" NPT | J84: 5 | K84: =J84*$K$3 -> 5 | M84: 0.1 | N84: =M84*K84 -> 0.5 | O84: BOP | P84: —
A85: 83 | B85: AY30011 | C85: 10 | G85: — | I85: CHANNEL, UPN200 X 3025 LG | J85: 3 | K85: =J85*$K$3 -> 3 | M85: =25.3*U85/1000 -> 76.5325 | N85: =M85*K85 -> 229.5975 | O85: Channel | P85: A572 Gr. 50 | S85: UPN 200x75 | U85: 3025
A86: 84 | B86: AY30011 | C86: 11 | G86: AY30014 | I86: WELDMENT, HINGED FLOOR MNT, PC4100 | J86: 1 | K86: =J86*$K$3 -> 1 | M86: 11 | N86: =M86*K86 -> 11 | O86: Sub Assy. | P86: —
A87: 85 | B87: AY30011 | D87: 11.1 | G87: DT34373 | I87: PLATE, HINGED FLOOR FORMING CAP, PC4100 | J87: 2 | K87: =J87*$K$86 -> 2 | M87: 1 | N87: =M87*K87 -> 2 | O87: Plate | P87: A572 Gr. 50 | S87: 10 | T87: 83 | U87: 119
A88: 86 | B88: AY30011 | D88: 11.2 | G88: DT34374 | I88: PLATE, HINGED FLOOR MNT, PC4100 | J88: 2 | K88: =J88*$K$86 -> 2 | M88: 1 | N88: =M88*K88 -> 2 | O88: Plate | P88: A572 Gr. 50 | S88: 10 | T88: 75 | U88: 119
A89: 87 | B89: AY30011 | D89: 11.3 | G89: DT34339 | I89: PLATE, HINGE FLOOR MOUNT SHORT, PC4100 | J89: 2 | K89: =J89*$K$86 -> 2 | M89: =S89*T89*U89*0.00000785 -> 0.25905 | N89: =M89*K89 -> 0.5181 | O89: Plate | P89: A572 Gr. 50 | S89: 10 | T89: 44 | U89: 75
A90: 88 | B90: AY30011 | D90: 11.4 | G90: DT34366 | I90: BAR, RD, 12 x 25 LG, PC4100 | J90: 2 | K90: =J90*$K$86 -> 2 | M90: 0.02 | N90: =M90*K90 -> 0.04 | O90: Rod | P90: A36/275JR | S90: Dia 12 | U90: 25
A91: 89 | B91: AY30011 | D91: 11.5 | G91: DT34379 | I91: PLATE, 6 x 232 x 749, PC4100 | J91: 1 | K91: =J91*$K$86 -> 1 | M91: 8 | N91: =M91*K91 -> 8 | O91: Plate | P91: ASTM A572 Gr. 50 /A516 Gr.70/S355JR | S91: 6 | T91: 232 | U91: 749 | Z91: 2 | AA91: R6

Sheet Sheet1
F2: ITEM | G2: QTY | H2: DESCRIPTION | I2: MATERIAL | J2: CANRIG PART No.
F3: 1 | G3: 3 | H3: PLATE, CARRIER MASTER RIB, PC4100 | I3: A572 Gr. 50 | J3: DT34528
F4: 2 | G4: 1 | H4: W-BEAM, REAR CARRIER BEAM - DS, PC4100 | I4: ASTM A572 Gr. 50 / S355JR | J4: DT34752
F5: 3 | G5: 1 | H5: W-BEAM, REAR CARRIER BEAM - ODS, PC4100 | I5: ASTM A572 Gr. 50 / S355JR | J5: DT34753
F6: 4 | G6: 4 | H6: PLATE, REAR ROLLER EAR, PC4100 | I6: A572 Gr. 50 | J6: DT34754
F7: 5 | G7: 1 | H7: PLATE, TENSIONER ASSEMBLY MOUNT, PC4100 | I7: A36 / S275JR / SA 516 GR.70 | J7: DT34755
F8: 6 | G8: 2 | H8: PLATE, REAR SKATE SUPPORT, PC4100 | I8: A572 Gr. 50 | J8: DT34756
F9: 7 | G9: 4 | H9: SET COLLAR, Ø1.75", PC4100 | I9: AISI C1045 | J9: DT34757
F10: 8 | G10: 1 | H10: HSS, PULLY GUARD, PC4100 | I10: A36 / S275JR | J10: DT34758
F11: 9 | G11: 2 | H11: PLATE, BACK AXLE CAP, PC4100 | I11: A572 Gr. 50 | J11: DT34759
F12: 10 | G12: 2 | H12: FLAT BAR, 25 x 50 x 50 LG [1 x 2 x 2] | I12: G40.21-44W | J12: —
F13: 11 | G13: 4 | H13: GUSSET, FLANGE, CARRIER, PC4100 | I13: A572 Gr. 50 | J13: DT34550
F14: 12 | G14: 2 | H14: PLATE, REAR ROLLER EAR INNER CAP, PC4100 | I14: ASTM A572 Gr. 50 / S355JR OR A516 Gr.70 | J14: DT34760
... F17: 15 | G17: 2 | H17: PLATE, CARRIER FLANGE PLATE GUSSET, PC4100 | I17: A572 Gr. 50 | J17: DT34547

Sheet RM Details
H1: Assembly | I1: DT34962
A2: RM Details Assy. No | E2: =I1 -> DT34962
A3: Type | B3: Drg. Material | C3: Material | D3: Size (thk) | E3: Net Wet(kg) | F3: Gross Weight (kg) | I3: Column Labels
A4: Plate | B4: ASTM A36/ Q235 | C4: IS 2062 E250 A/BO/BR | D4: 8 | E4: =GETPIVOTDATA("Sum of Total Weight (Kg)",$H$3,"Alt. Material","IS 2062 E250 A/BO/BR","IS Thk (mm)",8) -> 158.59462 | F4: =GETPIVOTDATA("Sum of Gross Wt (kg)",$H$3,"Alt. Material","IS 2062 E250 A/BO/BR","IS Thk (mm)",8) -> 218.0676 | I4: ASTM A514 | K4: IS 2062 E250 A/BO/BR | M4: Total Sum of Total Weight (Kg) | N4: Total Sum of Gross Wt (kg)
A5: Plate | B5: ASTM A514/Q690 | C5: ASTM A514 | D5: 20 | E5: =GETPIVOTDATA("Sum of Total Weight (Kg)",$H$3,"Alt. Material","ASTM A514","IS Thk (mm)",20) -> 8.6184 | F5: =GETPIVOTDATA("Sum of Gross Wt (kg)",$H$3,"Alt. Material","ASTM A514","IS Thk (mm)",20) -> 10.084816 | H5: Row Labels | I5: Sum of Total Weight (Kg) | J5: Sum of Gross Wt (kg) | K5: Sum of Total Weight (Kg) | L5: Sum of Gross Wt (kg)
H6: 8 | K6: 158.59462 | L6: 218.0676 | M6: 158.59462 | N6: 218.0676
H7: 20 | I7: 8.6184 | J7: 10.084816 | M7: 8.6184 | N7: 10.084816
H8: Grand Total | I8: 8.6184 | J8: 10.084816 | K8: 158.59462 | L8: 218.0676 | M8: 167.21302 | N8: 228.15242
A11: RM Details Assy. No | E11: =I11 -> DT34961 | H11: Assembly | I11: DT34961
A12: Type | B12: Drg. Material | C12: Material | D12: Size (thk) | E12: Net Wet(kg) | F12: Gross Weight (kg)
A13: Plate | B13: ASTM A36/ Q235 | C13: IS 2062 E250 A/BO/BR | D13: 8 | E13: =GETPIVOTDATA("Sum of Total Weight (Kg)",$H$13,"IS Thk (mm)",8) -> 177.39731 | F13: =GETPIVOTDATA("Sum of Gross Wt (kg)",$H$13,"IS Thk (mm)",8) -> 243.92131 | I13: Column Labels
A14: Plate | B14: ASTM A514/Q690 | C14: ASTM A514 | D14: 20 | E14: =GETPIVOTDATA("Sum of Total Weight (Kg)",$H$13,"Alt. Material","ASTM A514","IS Thk (mm)",20) -> 8.6184 | F14: =GETPIVOTDATA("Sum of Gross Wt (kg)",$H$13,"Alt. Material","ASTM A514","IS Thk (mm)",20) -> 10.084816 | I14: ASTM A514 | K14: IS 2062 E250 A/BO/BR | M14: Total Sum of Total Weight (Kg) | N14: Total Sum of Gross Wt (kg)
H15: Row Labels | I15: Sum of Total Weight (Kg) | J15: Sum of Gross Wt (kg) | K15: Sum of Total Weight (Kg) | L15: Sum of Gross Wt (kg)
H16: 8 | K16: 177.39731 | L16: 243.92131 | M16: 177.39731 | N16: 243.92131
H17: 20 | I17: 8.6184 | J17: 10.084816 | M17: 8.6184 | N17: 10.084816
H18: Grand Total | I18: 8.6184 | J18: 10.084816 | K18: 177.39731 | L18: 243.92131 | M18: 186.01571 | N18: 254.00612
A21: RM Details Assy. No | E21: =I21 -> DT14062 | H21: Assembly | I21: DT14062
A22: Type | B22: Drg. Material | C22: Material | D22: Size (thk) | E22: Net Wet(kg) | F22: Gross Weight (kg)
A23: Plate | B23: ASTM A36/ Q235 | C23: IS 2062 E250 A/BO/BR | D23: 6 | E23: =GETPIVOTDATA("Sum of Total Weight (Kg)",$H$23,"Alt. Material","IS 2062 E250 A/BO/BR","IS Thk (mm)",6) -> 1.0099502 | F23: =GETPIVOTDATA("Sum of Gross Wt (kg)",$H$23,"Alt. Material","IS 2062 E250 A/BO/BR","IS Thk (mm)",6) -> 1.5870646 | I23: Column Labels
A24: Plate | B24: ASTM A36/ Q235 | C24: IS 2062 E250 A/BO/BR | D24: 20 | E24: =GETPIVOTDATA("Sum of Total Weight (Kg)",$H$23,"Alt. Material","IS 2062 E250 A/BO/BR","IS Thk (mm)",20) -> 179.33084 | F24: =GETPIVOTDATA("Sum of Gross Wt (kg)",$H$23,"Alt. Material","IS 2062 E250 A/BO/BR","IS Thk (mm)",20) -> 253.90306 | I24: 42CrMo4 / EN 19 | K24: IS 2062 E250 A/BO/BR | M24: Total Sum of Total Weight (Kg) | N24: Total Sum of Gross Wt (kg)
A25: Rod | B25: AISI 4140 HTSR | C25: 42CrMo4 / EN 19 | D25: Dia 65 | E25: =GETPIVOTDATA("Sum of Total Weight (Kg)",$H$23,"Alt. Material","42CrMo4 / EN 19","IS Thk (mm)","Dia 65") -> 68.04 | F25: =GETPIVOTDATA("Sum of Gross Wt (kg)",$H$23,"Alt. Material","42CrMo4 / EN 19","IS Thk (mm)","Dia 65") -> 97.405 | H25: Row Labels | I25: Sum of Total Weight (Kg) | J25: Sum of Gross Wt (kg) | K25: Sum of Total Weight (Kg) | L25: Sum of Gross Wt (kg)
H26: 6 | K26: 1.0099502 | L26: 1.5870646 | M26: 1.0099502 | N26: 1.5870646
H27: 20 | K27: 179.33084 | L27: 253.90306 | M27: 179.33084 | N27: 253.90306
H28: Dia 65 | I28: 68.04 | J28: 97.405 | M28: 68.04 | N28: 97.405
H29: Grand Total | I29: 68.04 | J29: 97.405 | K29: 180.34079 | L29: 255.49012 | M29: 248.38079 | N29: 352.89512
A33: RM Details Assy. No | E33: =I33 -> DT14077 | H33: Assembly | I33: DT14077
A34: Type | B34: Drg. Material | C34: Material | D34: Size (thk) | E34: Net Wet(kg) | F34: Gross Weight (kg)
A35: Plate | B35: ASTM A36/ Q235 | C35: IS 2062 E250 A/BO/BR | D35: 6 | E35: =GETPIVOTDATA("Sum of Total Weight (Kg)",$H$35,"Alt. Material","IS 2062 E250 A/BO/BR","IS Thk (mm)",6) -> 0.45775031 | F35: =GETPIVOTDATA("Sum of Gross Wt (kg)",$H$35,"Alt. Material","IS 2062 E250 A/BO/BR","IS Thk (mm)",6) -> 0.71932192 | I35: Column Labels
A36: Plate | B36: ASTM A36/ Q235 | C36: IS 2062 E250 A/BO/BR | D36: 20 | E36: =GETPIVOTDATA("Sum of Total Weight (Kg)",$H$35,"Alt. Material","IS 2062 E250 A/BO/BR","IS Thk (mm)",20) -> 73.946179 | F36: =GETPIVOTDATA("Sum of Gross Wt (kg)",$H$35,"Alt. Material","IS 2062 E250 A/BO/BR","IS Thk (mm)",20) -> 104.51115 | I36: 42CrMo4 / EN 19 | K36: IS 2062 E250 A/BO/BR | M36: Total Sum of Total Weight (Kg) | N36: Total Sum of Gross Wt (kg)
A37: Rod | B37: AISI 4140 HTSR | C37: 42CrMo4 / EN 19 | D37: Dia 65 | E37: =GETPIVOTDATA("Sum of Total Weight (Kg)",$H$35,"Alt. Material","42CrMo4 / EN 19","IS Thk (mm)","Dia 65") -> 30.02832 | F37: =GETPIVOTDATA("Sum of Gross Wt (kg)",$H$35,"Alt. Material","42CrMo4 / EN 19","IS Thk (mm)","Dia 65") -> 41.888 | H37: Row Labels | I37: Sum of Total Weight (Kg) | J37: Sum of Gross Wt (kg) | K37: Sum of Total Weight (Kg) | L37: Sum of Gross Wt (kg)
H38: 6 | K38: 0.45775031 | L38: 0.71932192 | M38: 0.45775031 | N38: 0.71932192
H39: 20 | K39: 73.946179 | L39: 104.51115 | M39: 73.946179 | N39: 104.51115
H40: Dia 65 | I40: 30.02832 | J40: 41.888 | M40: 30.02832 | N40: 41.888
H41: Grand Total | I41: 30.02832 | J41: 41.888 | K41: 74.403929 | L41: 105.23047 | M41: 104.43225 | N41: 147.11847
A44: RM Details Assy. No | E44: =I44 -> DT14647 | H44: Assembly | I44: DT14647
A45: Type | B45: Drg. Material | C45: Material | D45: Size (thk) | E45: Net Wet(kg) | F45: Gross Weight (kg)
A46: Plate | B46: ASTM A514 GR B | C46: ASTM A514 GR B | D46: 25 | E46: =GETPIVOTDATA("Sum of Total Weight (Kg)",$H$46,"Alt. Material","ASTM A514 GR B","IS Thk (mm)",25) -> 17.907126 | F46: =GETPIVOTDATA("Sum of Gross Wt (kg)",$H$46,"Alt. Material","ASTM A514 GR B","IS Thk (mm)",25) -> 26.07144 | I46: Column Labels
A47: Plate | B47: ASTM A514 GR B | C47: ASTM A514 GR B | D47: 32 | E47: =GETPIVOTDATA("Sum of Total Weight (Kg)",$H$46,"Alt. Material","ASTM A514 GR B","IS Thk (mm)",32) -> 105.19452 | F47: =GETPIVOTDATA("Sum of Gross Wt (kg)",$H$46,"Alt. Material","ASTM A514 GR B","IS Thk (mm)",32) -> 120.75737 | I47: 1.7218 (25CrMo4) | K47: ASTM A514 GR B | M47: Total Sum of Total Weight (Kg) | N47: Total Sum of Gross Wt (kg)
A48: Plate | B48: AISI 4130 | C48: 1.7218 (25CrMo4) | D48: Dia 90 | E48: =GETPIVOTDATA("Sum of Total Weight (Kg)",$H$46,"Alt. Material","1.7218 (25CrMo4)","IS Thk (mm)","Dia 90") -> 3.3 | F48: =GETPIVOTDATA("Sum of Gross Wt (kg)",$H$46,"Alt. Material","1.7218 (25CrMo4)","IS Thk (mm)","Dia 90") -> 4.015 | H48: Row Labels | I48: Sum of Total Weight (Kg) | J48: Sum of Gross Wt (kg) | K48: Sum of Total Weight (Kg) | L48: Sum of Gross Wt (kg)
H49: 25 | K49: 17.907126 | L49: 26.07144 | M49: 17.907126 | N49: 26.07144
H50: 32 | K50: 105.19452 | L50: 120.75737 | M50: 105.19452 | N50: 120.75737
H51: Dia 90 | I51: 3.3 | J51: 4.015 | M51: 3.3 | N51: 4.015
H52: Grand Total | I52: 3.3 | J52: 4.015 | K52: 123.10165 | L52: 146.82881 | M52: 126.40165 | N52: 150.84381
H63: Assembly | I63: (All)
I65: Column Labels
I66: 1.7218 (25CrMo4) | K66: 42CrMo4 / EN 19 | M66: ASTM A514 GR B | O66: ASTM A514 | Q66: IS 2062 E250 A/BO/BR | S66: Total Sum of Total Weight (Kg) | T66: Total Sum of Gross Wt (kg)
B67: Size (mm) | C67: Material Grade | D67: Total Weight Req. kg | H67: Row Labels | I67: Sum of Total Weight (Kg) | J67: Sum of Gross Wt (kg) | K67: Sum of Total Weight (Kg) | L67: Sum of Gross Wt (kg) | M67: Sum of Total Weight (Kg) | N67: Sum of Gross Wt (kg) | O67: Sum of Total Weight (Kg) | P67: Sum of Gross Wt (kg) | Q67: Sum of Total Weight (Kg) | R67: Sum of Gross Wt (kg)
B68: 6 | C68: IS 2062 E250 BR | D68: 2.3063866 | H68: 6 | Q68: 1.4677005 | R68: 2.3063866 | S68: 1.4677005 | T68: 2.3063866
B69: 8 | C69: IS 2062 E250 BR | D69: 461.98891 | H69: 8 | Q69: 335.99193 | R69: 461.98891 | S69: 335.99193 | T69: 461.98891
B70: 20 | C70: IS 2062 E250 BR | D70: 358.4142 | H70: 20 | O70: 17.2368 | P70: 20.169633 | Q70: 253.27702 | R70: 358.4142 | S70: 270.51382 | T70: 378.58384
B71: 20 | C71: ASTM A514 GR B | D71: 20.169633 | H71: 25 | M71: 17.907126 | N71: 26.07144 | S71: 17.907126 | T71: 26.07144
B72: 25 | C72: ASTM A514 GR B | D72: 26.07144 | H72: 32 | M72: 105.19452 | N72: 120.75737 | S72: 105.19452 | T72: 120.75737
B73: 32 | C73: ASTM A514 GR B | D73: 120.75737 | H73: Dia 65 | K73: 98.06832 | L73: 139.293 | S73: 98.06832 | T73: 139.293
B74: Dia 65 | C74: 42CrMo4 / EN 19 | D74: 139.293 | H74: Dia 90 | I74: 3.3 | J74: 4.015 | S74: 3.3 | T74: 4.015
B75: Dia 90 | C75: 1.7218 (25CrMo4) | D75: 4.015 | H75: Grand Total | I75: 3.3 | J75: 4.015 | K75: 98.06832 | L75: 139.293 | M75: 123.10165 | N75: 146.82881 | O75: 17.2368 | P75: 20.169633 | Q75: 590.73665 | R75: 822.7095 | S75: 832.44342 | T75: 1133.0159
B76: Grand Total | D76: =SUM(D68:D75) -> 1133.0159

Sheet Welding Details
B2: Assy No. | C2: Item No. | D2: Weld Length | E2: No of Run | F2: No of Places | G2: Total Weld

Sheet Paint Details
H2: Akzonobel
G3: Total Area | H3: ='BOM 42D CARRIER REAR_AY3016'!AI3 -> 0 | I3: SQM | J3: As per drawing
C4: Paint Details | D4: DFT | E4: Th Coverage (Area m2) | F4: Wastage factor | G4: Actual Coverage (Area m2) | H4: Req Paint (Litre) | I4: Rate of paint | J4: Amount
B5: Primer | C5: Interzinc 42 | D5: 50-75 | E5: =75*7.33/75 -> 7.33 | F5: 0.35 | G5: =E5*(100%-F5) -> 4.7645 | H5: =(1/G5)*$H$3 -> 0 | I5: 1000 | J5: =H5*I5 -> 0 | K5: 1
B6: Paint | C6: Interthane 990 white | D6: 50-75 | E6: =50*11.4/50 -> 11.4 | F6: 0.35 | G6: =E6*(100%-F6) -> 7.41 | H6: =(1/G6)*$H$3 -> 0 | I6: 1000 | J6: =H6*I6 -> 0 | K6: 1
B7: Thinner | H7: =SUM(H5:H6)*0.3 -> 0 | I7: 400 | J7: =H7*I7 -> 0
B8: Total | H8: =SUM(H5:H7) -> 0 | J8: =SUM(J5:J7) -> 0
G9: Paint Applying Cost (Labour and Consuables) | J9: =H3*250 -> 0 | K9: `@250/SQM
B10: Total Paint Cost | J10: =J8+J9 -> 0
B11: Extra paint touch up cost (5%) | I11: 0.05 | J11: =J10*I11 -> 0
B12: Total cost | J12: =J11+J10 -> 0 | K12: =J12/H3 -> #DIV/0!
H17: Akzonobel
G18: Total Area | H18: =H3 -> 0 | J18: SQM | K18: As per drawing
C19: Paint Details | D19: DFT | E19: Th Coverage (Area m2) | F19: Wastage factor | G19: Actual Coverage (Area m2) | H19: Req Paint (Litre) | I19: Minimum Qty | J19: Rate of paint | K19: Amount
B20: Primer | C20: Interzinc 42 | D20: 75 | E20: =75*7.33/D20 -> 7.33 | F20: 0.35 | G20: =E20*(100%-F20) -> 4.7645 | H20: =(1/G20)*$H$3 -> 0 | I20: =H20 -> 0 | J20: 787.5 | K20: =J20*I20 -> 0 | L20: 1
B21: Paint | C21: Interthane 990 white | D21: 75 | E21: =50*13.6/D21 -> 9.0666667 | F21: 0.35 | G21: =E21*(100%-F21) -> 5.8933333 | H21: =(1/G21)*$H$3 -> 0 | I21: 20 | J21: 1200 | K21: =J21*I21 -> 24000 | L21: 1
B22: Thinner | H22: =SUM(H20:H21)*0.3 -> 0 | I22: =H22 -> 0 | J22: 200 | K22: =J22*I22 -> 0
B23: Total | H23: =SUM(H20:H22) -> 0 | K23: =SUM(K20:K22) -> 24000
G24: Paint Applying Cost (Labour and Consuables) | K24: =H18*250 -> 0 | L24: `@250/SQM
B25: Total Paint Cost | K25: =K23+K24 -> 24000
B26: Extra paint touch up cost (5%) | J26: 0.05 | K26: =K25*J26 -> 1200
B27: Total cost | K27: =K26+K25 -> 25200 | L27: =K27/H18 -> #DIV/0!
